Workbook

Sheet Resumen
B2: Resumen de Ponderacion y Horas
B4: Curso | C4: 768 - Algoritmos
B5: Semestre que aplica | C5: Segundo Semestre 2026
B6: Total de Puntos del Laboratorio
A8: * Esta sección se auto completa al momento en que se llene a la información de la planificación
A9: ** Tomar como base la distribución realizada por el coordinador del area del curso en el documento de criterios y expectativas
A10: Tipo de Actividad | B10: Ponderacion | C10: Horas utilizadas | D10: Aspectos clave que debe abordar | G10: Valor Maximo Recomendado
A11: Actividades durante el peridodo de laboratorio | B11: =S.2!C7+S.3!C7+S.4!C7+S.5!C7+S.6!C7+S.7!C7+S.8!C7+S.9!C7+S.10!C7+S.11!C7 -> 10 | C11: =ROUND((S.2!C6+S.3!C6+S.4!C6+S.5!C6+S.6!C6+S.7!C6+S.8!C6+S.9!C6+S.10!C6+S.11!C6)/60,0) -> 17 | G11: 10
A12: Proyectos | B12: =Proyectos!C6 -> 60 | C12: =Proyectos!C5 -> 70 | G12: 60
A13: Prácticas | B13: =Practicas!C6 -> 20 | C13: =Practicas!C5 -> 25 | G13: 20
A14: Tareas | B14: =Tareas!C6 -> 10 | C14: =Tareas!C5 -> 24 | G14: 10
A15: Total | B15: =SUM(B11:B14) -> 100 | C15: =SUM(C11:C14) -> 136 | D15: Validacion | E15: =IFERROR(__xludf.DUMMYFUNCTION("LET( nombres,A11:A14, p,B11:B14, m,G11:G14, t,SUM(p), exceden, IFERROR(TEXTJOIN(""; "", TRUE, FILTER(nombres&"" (""&p&"">""&m&"")"", p>m)), """"), negs, IF(COUNTIF(p,""<0"")>0, ""Hay valores negativos"", """"), totalmsg, IF(t<>100, ""Total ≠"&" 100 (actual ""&t&"")"", """"), excesomsg, IF(exceden<>"""", ""Exceden: ""&exceden, """"), msg, TEXTJOIN("" | "", TRUE, totalmsg, negs, excesomsg), IF(msg="""", ""✅ Distribución válida"", ""❌ Revisar: ""&msg) )"),"✅ Distribución válida") -> ✅ Distribución válida

Sheet Competencias
B1: Competencias que se formaran en el Segundo Semestre 2026
B2: Curso | C2: 768 - Algoritmos
B3: Semestre que aplica | C3: Segundo Semestre 2026
B5: Competencias relacionadas al perfil del egresado (Especifica) | I5: Competencias relacionadas al perfil del egresado (General)
B6: 1 | C6: Demuestra pensamiento crítico, actitud investigativa y rigor analítico en el planteamiento y la resolución de problemas complejos. | I6: 1 | J6: Aplica principios básicos de ingeniería, ciencias de computación y sistemas de información y comunicación, en la formulación y resolución adecuada de problemas complejos.
B7: 2 | C7: Demuestra destreza y habilidad en la selección, uso y adaptación de herramientas metodológicas, tecnológicas, equipos especializados y en la lectura e interpretación de datos, pertinentes al contexto de su ejercicio profesional. | I7: 2 | J7: Construye soluciones integrales trabajando en forma colaborativa y propositiva en equipos interdisciplinarios, en forma presencial o utilizando plataformas virtuales.
B8: 3 | C8: Toma decisiones profesionales con base en fundamentos teóricos, datos e información pertinente, válida y confiable. | I8: 3 | J8: Aplica estándares de calidad, eficiencia y seguridad en la implementación adecuada de soluciones de software, hardware y TIC en general.
B11: No | C11: Tipo | D11: Verbo en Presente | E11: Objeto de la acción | G11: [Palabras conectoreas] Herramientas o metodología | H11: [Palabras conectoreas] Condiciones específicas | J11: Nivel
B12: 1 | C12: General | D12: Analiza | E12: los fundamentos del hardware, software y arquitectura computacional | G12: mediante el ciclo fetch-decode-execute, sistemas de numeración y codificación de información | H12: para establecer la base conceptual del procesamiento y flujo de datos en sistemas computacionales | J12: Analizar
C13: =D12 & " " & E12 & " " &G12& " " &H12& " " -> Analiza los fundamentos del hardware, software y arquitectura computacional mediante el ciclo fetch-decode-execute, sistemas de numeración y codificación de información para establecer la base conceptual del procesamiento y flujo de datos en sistemas computacionales
B14: 2 | C14: Especifica | D14: Identifica | E14: los componentes físicos y lógicos de un sistema computacional | G14: utilizando el modelo de Von Neumann y la clasificación de software por categorías | H14: para distinguir la función de cada elemento dentro de la arquitectura de procesamiento | J14: Recordar
C15: =D14 & " " & E14 & " " &G14& " " &H14& " " -> Identifica los componentes físicos y lógicos de un sistema computacional utilizando el modelo de Von Neumann y la clasificación de software por categorías para distinguir la función de cada elemento dentro de la arquitectura de procesamiento
B16: 3 | C16: Especifica | D16: Convierte | E16: valores numéricos entre sistemas de numeración decimal, binario, octal y hexadecimal | G16: aplicando los métodos de conversión posicional y los estándares de codificación ASCII, UNICODE e ISO-8859 | H16: para representar datos primitivos, imágenes, audio y video en formato digital | J16: Aplicar
C17: =D16 & " " & E16 & " " &G16& " " &H16& " " -> Convierte valores numéricos entre sistemas de numeración decimal, binario, octal y hexadecimal aplicando los métodos de conversión posicional y los estándares de codificación ASCII, UNICODE e ISO-8859 para representar datos primitivos, imágenes, audio y video en formato digital
B18: 4 | C18: Especifica | D18: Descompone | E18: problemas computacionales en subproblemas definidos | G18: mediante técnicas de descomposición, reconocimiento de patrones y abstracción | H18: para estructurar soluciones algorítmicas a partir de instancias y contextos concretos | J18: Analizar
C19: =D18 & " " & E18 & " " &G18& " " &H18& " " -> Descompone problemas computacionales en subproblemas definidos mediante técnicas de descomposición, reconocimiento de patrones y abstracción para estructurar soluciones algorítmicas a partir de instancias y contextos concretos
B20: 5 | C20: Especifica | D20: Diseña | E20: algoritmos que resuelven problemas determinísticos, condicionales y cíclicos | G20: empleando estructuras de control secuenciales, condicionales y repetitivas en pseudocódigo | H20: para producir soluciones correctas, legibles y verificables en un entorno de desarrollo introductorio | J20: Crear
C21: =D20 & " " & E20 & " " &G20& " " &H20& " " -> Diseña algoritmos que resuelven problemas determinísticos, condicionales y cíclicos empleando estructuras de control secuenciales, condicionales y repetitivas en pseudocódigo para producir soluciones correctas, legibles y verificables en un entorno de desarrollo introductorio
B22: 6 | C22: Especifica | D22: Implementa | E22: algoritmos con manejo de arreglos unidimensionales y multidimensionales | G22: utilizando herramientas de pseudocódigo y diagramas de flujo | H22: para representar y administrar colecciones de datos de forma estructurada | J22: Aplicar
C23: =D22 & " " & E22 & " " &G22& " " &H22& " " -> Implementa algoritmos con manejo de arreglos unidimensionales y multidimensionales utilizando herramientas de pseudocódigo y diagramas de flujo para representar y administrar colecciones de datos de forma estructurada
B24: 7 | C24: Especifica | D24: Evalúa | E24: la calidad y corrección de algoritmos propios y de pares | G24: aplicando criterios de claridad, eficiencia estructural y conformidad con las características de un buen algoritmo | H24: para mejorar la solución antes de su implementación en un lenguaje de programación formal | J24: Evaluar
C25: =D24 & " " & E24 & " " &G24& " " &H24& " " -> Evalúa la calidad y corrección de algoritmos propios y de pares aplicando criterios de claridad, eficiencia estructural y conformidad con las características de un buen algoritmo para mejorar la solución antes de su implementación en un lenguaje de programación formal
B28: Si las competencias son las misma que el semetre anterior compartenos tu opinion de porque no se cambiaron

Sheet Diseño
B2: Diseño de Contenido Curricular
B4: Curso | C4: 768 - Algoritmos
B5: semestre que aplica | C5: Segundo Semestre 2026
B8: No. | C8: Competencia | D8: Nombre de la Unidad | E8: Tema | F8: Subtema | G8: Mes | H8: Semana
B9: 1 | C9: Analiza los fundamentos del hardware, software y arquitectura computacional mediante el ciclo fetch-decode-execute, sistemas de numeración y codificación de información para establecer la base conceptual del procesamiento y flujo de datos en sistemas computacionales | D9: Unidad 1 - La computadora | E9: La computadora | F9: Definición y evolución de la computadora | G9: Agosto | H9: 2
B10: 2 | C10: Analiza los fundamentos del hardware, software y arquitectura computacional mediante el ciclo fetch-decode-execute, sistemas de numeración y codificación de información para establecer la base conceptual del procesamiento y flujo de datos en sistemas computacionales | D10: Unidad 2 - Arquitectura y organización VNA | E10: Hardware de procesamiento | F10: Ciclo fetch - decode - execute | G10: Agosto | H10: 2
B11: 3 | C11: Identifica los componentes físicos y lógicos de un sistema computacional utilizando el modelo de Von Neumann y la clasificación de software por categorías para distinguir la función de cada elemento dentro de la arquitectura de procesamiento | D11: Unidad 2 - Arquitectura y organización VNA | E11: Hardware de procesamiento | F11: Componentes de la unidad de control y ALU | G11: Agosto | H11: 2
B12: 4 | C12: Identifica los componentes físicos y lógicos de un sistema computacional utilizando el modelo de Von Neumann y la clasificación de software por categorías para distinguir la función de cada elemento dentro de la arquitectura de procesamiento | D12: Unidad 2 - Arquitectura y organización VNA | E12: Hardware de procesamiento | F12: Tecnologías RISC/CISC | G12: Agosto | H12: 3
B13: 5 | C13: Identifica los componentes físicos y lógicos de un sistema computacional utilizando el modelo de Von Neumann y la clasificación de software por categorías para distinguir la función de cada elemento dentro de la arquitectura de procesamiento | D13: Unidad 2 - Arquitectura y organización VNA | E13: Hardware de almacenamiento | F13: Memoria principal y secundaria | G13: Agosto | H13: 3
B14: 6 | C14: Identifica los componentes físicos y lógicos de un sistema computacional utilizando el modelo de Von Neumann y la clasificación de software por categorías para distinguir la función de cada elemento dentro de la arquitectura de procesamiento | D14: Unidad 2 - Arquitectura y organización VNA | E14: Hardware de comunicación | F14: Tarjetas de red, routers, switches, APs, HW de seguridad (firewall y otros) | G14: Agosto | H14: 3
B15: 7 | C15: Identifica los componentes físicos y lógicos de un sistema computacional utilizando el modelo de Von Neumann y la clasificación de software por categorías para distinguir la función de cada elemento dentro de la arquitectura de procesamiento | D15: Unidad 2 - Arquitectura y organización VNA | E15: Buses | F15: Bus de control, bus de datos y bus de dirección | G15: Agosto | H15: 3
B16: 8 | C16: Analiza los fundamentos del hardware, software y arquitectura computacional mediante el ciclo fetch-decode-execute, sistemas de numeración y codificación de información para establecer la base conceptual del procesamiento y flujo de datos en sistemas computacionales | D16: Unidad 2 - Arquitectura y organización VNA | E16: Software de sistema | F16: Sistemas operativos, hipervisores y utilitarios | G16: Agosto | H16: 4
B17: 9 | C17: Identifica los componentes físicos y lógicos de un sistema computacional utilizando el modelo de Von Neumann y la clasificación de software por categorías para distinguir la función de cada elemento dentro de la arquitectura de procesamiento | D17: Unidad 2 - Arquitectura y organización VNA | E17: Software de aplicación | F17: ERP, CRM, WMS y ofimática | G17: Agosto | H17: 4
B18: 10 | C18: Analiza los fundamentos del hardware, software y arquitectura computacional mediante el ciclo fetch-decode-execute, sistemas de numeración y codificación de información para establecer la base conceptual del procesamiento y flujo de datos en sistemas computacionales | D18: Unidad 2 - Arquitectura y organización VNA | E18: Software de programación | F18: Lenguajes de programación y su clasificación | G18: Agosto | H18: 4
B19: 11 | C19: Identifica los componentes físicos y lógicos de un sistema computacional utilizando el modelo de Von Neumann y la clasificación de software por categorías para distinguir la función de cada elemento dentro de la arquitectura de procesamiento | D19: Unidad 2 - Arquitectura y organización VNA | E19: Calidad y seguridad | F19: Normativas y estándares internacionales | G19: Agosto | H19: 4
B20: 12 | C20: Analiza los fundamentos del hardware, software y arquitectura computacional mediante el ciclo fetch-decode-execute, sistemas de numeración y codificación de información para establecer la base conceptual del procesamiento y flujo de datos en sistemas computacionales | D20: Unidad 2 - Arquitectura y organización VNA | E20: Firmware | F20: Programación y control del hardware a bajo nivel | G20: Agosto | H20: 4
... B41: 33 | C41: Evalúa la calidad y corrección de algoritmos propios y de pares aplicando criterios de claridad, eficiencia estructural y conformidad con las características de un buen algoritmo para mejorar la solución antes de su implementación en un lenguaje de programación formal | D41: Unidad 6 – Administración y representación de Algoritmos | E41: Pseudocódigo | F41: Software de pseudocódigo | G41: Octubre | H41: 11
B42: 34
B43: 35
B44: 36
B45: 37
B46: 38
B47: 39
B48: 40
B49: 41
B50: 42
B51: 43
B52: 44
B53: 45
... B108: 100

Sheet Semana Diagnostico
B2: Diseño de Contenido Curricular
B4: Curso | C4: ='Diseño'!C4 -> 768 - Algoritmos
B5: Semana | C5: 1
B6: Tiempo | C6: =B15+B22+B29+B41+B47+C48 -> 70
K8: Estos puntos son recomendaciones de los puntos a tratar durante tu presentacion, si no usaras estos eres libre de agregar mas filas para indicar que haras. En los recuadros de la derecha colocar breve resumen de lo que planeas decir. No debes ser muy especifico seran pequeñas anotaciones que te ayudaran a recordar lo que planeaste
A9: 1. Bienvenida y Presentación | G9: Tiempo Aproximado | H9: =B15 -> 10
G10: No puedes excederte mas de 15 minutos
A11: Nombre y Formacion Academica
A12: Experiencia docente y profecional
A13: Rol del auxiliar dentro del curso (funciones, actividades y apoyo a los estudiantes).
A14: Expectativas sobre la dinámica del curso
A15: Tiempo que emplearas | B15: 10
A18: 2. Evaluación de Conocimientos Previos | G18: Tiempo Aproximado | H18: =B22
G19: No puedes excederte mas de 45 minutos | K19: En los recuadors de la derecha deberas colocar las preguntas que planeas realizar con sus respectivas respuestas. En el segundo recuadro deberas colocar un breve resumne de lo que tines planificado para la parte practica del curso previo al que estas impartiendo.
A20: Redactaras de 15 a 20 preguntas con sus respectivas respuestas , por lo que debes escoge los temas que evaluaras | B20: No hay un curso previo
A21: Redactaras una parte practica para realizar la evaluacion de conocimientos previos
A22: Tiempo que emplearas
A25: 3. Presentación de los Estudiantes | G25: Tiempo Aproximado | H25: =B29 -> 20
G26: No puedes excederte mas de 30 minutos
A27: Seleccion al Azar de 5 Estudiantes | K27: En el primer recuadro colocaras la metodollogia que adoptaras para la eleccion de los estudiantes. En el segundo recuadro colocaras la redaccion de las preguntas que comprendan los siguientes puntos respecto al estudiante: Nombre. Intereses y expectativas sobre el curso. Experiencia previa relacionada con el curso (si aplica). Un dato curioso sobre sí mismo. Consideras que la prueba de conociminetos previos esta acorde al conocimiento que se te brindo en su momento Que tan comodo se sintio con la prueba anterior.
A28: Indica las preguntas que responderan los estudiantes afortunados | B28: ¿Cuáles son sus expectativas para este curso? ¿Qué temas específicos tienen interés en aprender o descubrir a lo largo del semestre? ¿Consideran que los contenidos serán una herramienta de apoyo para su carrera o los perciben únicamente como una etapa de nivelación inicial?
A29: Tiempo que emplearas | B29: 20
A32: 4. Censo de Horarios de Calificación | G32: Tiempo Aproximado | H32: =B36 -> 10
A33: Deberas estar recordando que deben contestar el formulario asi mismo dejar el link fijado en la llamada | G33: Esta actividad quedara abierta hasta el fin de la clase. pero emplearas 5 min especificos para la actividad
A34: Link de google forms donde este el cuestionario | B34: https://forms.gle/xWU6mE1cvkmJiyXk8 | K34: Esta actividad te ayudara a realizar un senso de posibles horarios de calificacion y que tus estudiantes esten enterados y puedan preveer los dias de calificacion y asi mismo el horario. Deberas colocar en los reacuadros de la derecha link de Google form libre para correos intitucionales, esto para garantizar una sola respuesta por estudiante. TAmbien deberas colocar los posibles horarios y dias que tentativamente tendrias disponibles. para colocarlos en el google form.
A35: Dias y posibles Horarios de calificacion | B35: Jueves, Sabado de 7:00 a 12:00
A36: Tiempo que emplearas | B36: 10
A39: 5. Mostrar Programa del Curso | G39: Tiempo Aproximado | H39: =B41 -> 25
G40: No puedes excederte mas de 30 minutos
A41: Tiempo que emplearas | B41: 25
A44: 6. Evaluación de Conocimientos del Curso Actual | G44: Tiempo Aproximado | H44: =B47 -> 15
G45: No puedes excederte mas de 15 minutos
A46: Redactaras 20 preguntas con sus respectivas respuestas | B46: Conceptos de algoritmo, flujo de datos y lógica de programación básica
A47: Tiempo que emplearas | B47: 15

Sheet S.2
B2: Diseño de la Sesión de Laboratorio
B4: Curso | C4: ='Diseño'!C4 -> 768 - Algoritmos
B5: Semana | C5: 2
B6: Tiempo | C6: =H10+H21+H44+H68 -> 100
B7: Ponderación | C7: =B49+B60 -> 0
B8: Validación de Tiempo | C8: =IF(H44<=0, "❌ ERROR: La Actividad 1 debe tener un tiempo mayor a 0.", IF(H21>60, "❌ ERROR: El 'Área de Conocimiento' no puede exceder los 60 min.", IF((H10+H21+H44+H68)<100, "❌ ERROR: El tiempo total debe ser de al menos 100 min.", "✅ VALIDACIÓN CORRECTA"))) -> ✅ VALIDACIÓN CORRECTA
A10: 1. Área Actitudinal (Saber Ser) | G10: Tiempo Aproximado | H10: =B13 -> 5
G11: Tiene que estar en un rango de 3 a 5 minutos
A12: Nombre del Valor | B12: Curiosidad intelectual
A13: Tiempo Aproximado | B13: 5
A14: Descripcion
A15: Disposición activa para explorar el origen, evolución y funcionamiento de la tecnología más allá de lo evidente.
A17: Como se relaciona con los conocimientos de la sesion y se aplicaria
A18: Comprender cómo evolucionó la computadora y opera el ciclo fetch-decode-execute exige ir más allá de la memorización. El estudiante investiga por cuenta propia la historia de la computadora antes de la sesión y formula preguntas en clase.
A21: 2. Área Conocimiento (Saber) | G21: Tiempo Aproximado | H21: =SUM(D39:H42) -> 60
G22: No puede exceder los 60 minutos
A23: Competencia a desarrollar | B23: Analiza los fundamentos del hardware, software y arquitectura computacional mediante el ciclo fetch-decode-execute, sistemas de numeración y codificación de información para establecer la base conceptual del procesamiento y flujo de datos en sistemas computacionales
A24: Competencia a desarrollar
A26: 2.1 Contenido
A27: No. | B27: Unidad | D27: Tema | F27: Sub Tema
A28: 1 | B28: =IFERROR(__xludf.DUMMYFUNCTION("FILTER('Diseño'!D:D,'Diseño'!H:H=$C$5)"),"Unidad 1 - La computadora") -> Unidad 1 - La computadora | D28: =IFERROR(__xludf.DUMMYFUNCTION("FILTER('Diseño'!E:E,'Diseño'!H:H=$C$5)"),"La computadora") -> La computadora | F28: =IFERROR(__xludf.DUMMYFUNCTION("FILTER('Diseño'!F:F,'Diseño'!H:H=$C$5)"),"Definición y evolución de la computadora") -> Definición y evolución de la computadora
A29: 2 | B29: =IFERROR(__xludf.DUMMYFUNCTION("""COMPUTED_VALUE"""),"Unidad 2 - Arquitectura y organización VNA") -> Unidad 2 - Arquitectura y organización VNA | D29: =IFERROR(__xludf.DUMMYFUNCTION("""COMPUTED_VALUE"""),"Hardware de procesamiento") -> Hardware de procesamiento | F29: =IFERROR(__xludf.DUMMYFUNCTION("""COMPUTED_VALUE"""),"Ciclo fetch - decode - execute") -> Ciclo fetch - decode - execute
A30: 3 | B30: =IFERROR(__xludf.DUMMYFUNCTION("""COMPUTED_VALUE"""),"Unidad 2 - Arquitectura y organización VNA") -> Unidad 2 - Arquitectura y organización VNA | D30: =IFERROR(__xludf.DUMMYFUNCTION("""COMPUTED_VALUE"""),"Hardware de procesamiento ") -> Hardware de procesamiento | F30: =IFERROR(__xludf.DUMMYFUNCTION("""COMPUTED_VALUE"""),"Componentes de la unidad de control y ALU ") -> Componentes de la unidad de control y ALU
A31: 4
A32: 5
A33: 6
A34: 7
A36: 2.2 Recursos Educativos
A38: Tipo de Recurso a utilizar | B38: Tipo | C38: Valor maximo recomendado en Minutos | D38: Tiempo Aproximado ( unicamente el valor de minutos ) | I38: Validacion
A39: Presentacion | B39: Obligatorio | C39: 30 | D39: 25 | I39: =IF(D39<=C39,"Correcto", "Corregir") -> Correcto
A40: Video | B40: Obligatorio | C40: 6 | D40: 5 | I40: =IF(D40<=C40,"Correcto", "Corregir") -> Correcto
A41: Lectura | B41: Optativo | C41: 10 | D41: 5 | I41: =IF(D41<=C41,"Correcto", "Corregir") -> Correcto
A42: Ejercicio Demostrativo | B42: Obligatorio | C42: 30 | D42: 25 | I42: =IF(D42<=C42,"Correcto", "Corregir") -> Correcto
A44: 3. Área de Habilidades (Saber Hacer) | G44: Tiempo Aproximado | H44: =B50 -> 25
G45: Tiene que estar en un rango de 30 a 50 minutos
A46: Actividad 1 (Obligatoria)
A47: Competencia que predomina en la actividad | B47: Analiza los fundamentos del hardware, software y arquitectura computacional mediante el ciclo fetch-decode-execute, sistemas de numeración y codificación de información para establecer la base conceptual del procesamiento y flujo de datos en sistemas computacionales
A48: Tipo de Actividad | B48: Analisis
A49: Ponderación | B49: 0
A50: Tiempo Aproximado | B50: 25
A51: Coloca el tiempo que usar en la actividad, un tiempo sugerido 30 minutos
A52: Descripcion de la Actividad
A57: Actividad 2 (Optativa puedes hacerla si lo consideras apropiado)
A58: Competencia que predomina en la actividad
A59: Tipo de Actividad
A60: Ponderación
A61: Tiempo Aproximado
A62: Coloca el tiempo que usar en la actividad, un tiempo sugerido 20 minutos
A63: Descripcion de la Actividad
A68: 3. Cierre | G68: Tiempo Aproximado | H68: =B70 -> 10
G69: Tiene que estar en un rango de 10 a 15 minutos
A70: Tiempo Aproximado | B70: 10
A71: Asignacion de Actividades
A72: Tarea 1 (7 dias)
A74: Resuelve alguna duda, asigna las actividades que deben realizar, dudas de proyectos, etc

Sheet S.3
B2: Diseño de la Sesión de Laboratorio
B4: Curso | C4: ='Diseño'!C4 -> 768 - Algoritmos
B5: Semana | C5: 3
B6: Tiempo | C6: =H10+H21+H44+H68 -> 100
B7: Ponderación | C7: =B49+B60 -> 2
B8: Validación de Tiempo | C8: =IF(H44<=0, "❌ ERROR: La Actividad 1 debe tener un tiempo mayor a 0.", IF(H21>60, "❌ ERROR: El 'Área de Conocimiento' no puede exceder los 60 min.", IF((H10+H21+H44+H68)<100, "❌ ERROR: El tiempo total debe ser de al menos 100 min.", "✅ VALIDACIÓN CORRECTA"))) -> ✅ VALIDACIÓN CORRECTA
A10: 1. Área Actitudinal (Saber Ser) | G10: Tiempo Aproximado | H10: =B13 -> 5
G11: Tiene que estar en un rango de 3 a 5 minutos
A12: Nombre del Valor | B12: Pensamiento sistémico
A13: Tiempo Aproximado | B13: 5
A14: Descripcion
A15: Capacidad de ver los componentes individuales como partes interdependientes de un sistema mayor y coherente
A17: Como se relaciona con los conocimientos de la sesion y se aplicaria
A18: RISC/CISC, memoria, comunicación y buses solo tienen sentido cuando se analizan como subsistemas que interactúan. El estudiante elabora un esquema que muestra cómo cada componente de hardware se comunica con los demás.
A21: 2. Área Conocimiento (Saber) | G21: Tiempo Aproximado | H21: =SUM(D39:H42) -> 60
G22: No puede exceder los 60 minutos
A23: Competencia a desarrollar | B23: Identifica los componentes físicos y lógicos de un sistema computacional utilizando el modelo de Von Neumann y la clasificación de software por categorías para distinguir la función de cada elemento dentro de la arquitectura de procesamiento
A24: Competencia a desarrollar
A26: 2.1 Contenido
A27: No. | B27: Unidad | D27: Tema | F27: Sub Tema
A28: 1 | B28: =IFERROR(__xludf.DUMMYFUNCTION("FILTER('Diseño'!D:D,'Diseño'!H:H=$C$5)"),"Unidad 2 - Arquitectura y organización VNA") -> Unidad 2 - Arquitectura y organización VNA | D28: =IFERROR(__xludf.DUMMYFUNCTION("FILTER('Diseño'!E:E,'Diseño'!H:H=$C$5)"),"Hardware de procesamiento") -> Hardware de procesamiento | F28: =IFERROR(__xludf.DUMMYFUNCTION("FILTER('Diseño'!F:F,'Diseño'!H:H=$C$5)"),"Tecnologías RISC/CISC") -> Tecnologías RISC/CISC
A29: 2 | B29: =IFERROR(__xludf.DUMMYFUNCTION("""COMPUTED_VALUE"""),"Unidad 2 - Arquitectura y organización VNA") -> Unidad 2 - Arquitectura y organización VNA | D29: =IFERROR(__xludf.DUMMYFUNCTION("""COMPUTED_VALUE"""),"Hardware de almacenamiento") -> Hardware de almacenamiento | F29: =IFERROR(__xludf.DUMMYFUNCTION("""COMPUTED_VALUE"""),"Memoria principal y secundaria") -> Memoria principal y secundaria
A30: 3 | B30: =IFERROR(__xludf.DUMMYFUNCTION("""COMPUTED_VALUE"""),"Unidad 2 - Arquitectura y organización VNA") -> Unidad 2 - Arquitectura y organización VNA | D30: =IFERROR(__xludf.DUMMYFUNCTION("""COMPUTED_VALUE"""),"Hardware de comunicación") -> Hardware de comunicación | F30: =IFERROR(__xludf.DUMMYFUNCTION("""COMPUTED_VALUE"""),"Tarjetas de red, routers, switches, APs, HW de seguridad (firewall y otros)") -> Tarjetas de red, routers, switches, APs, HW de seguridad (firewall y otros)
A31: 4 | B31: =IFERROR(__xludf.DUMMYFUNCTION("""COMPUTED_VALUE"""),"Unidad 2 - Arquitectura y organización VNA") -> Unidad 2 - Arquitectura y organización VNA | D31: =IFERROR(__xludf.DUMMYFUNCTION("""COMPUTED_VALUE"""),"Buses") -> Buses | F31: =IFERROR(__xludf.DUMMYFUNCTION("""COMPUTED_VALUE"""),"Bus de control, bus de datos y bus de dirección") -> Bus de control, bus de datos y bus de dirección
A32: 5
A33: 6
A34: 7
A36: 2.2 Recursos Educativos
A38: Tipo de Recurso a utilizar | B38: Tipo | C38: Valor maximo recomendado en Minutos | D38: Tiempo Aproximado ( unicamente el valor de minutos ) | I38: Validacion
A39: Presentacion | B39: Obligatorio | C39: 30 | D39: 25 | I39: =IF(D39<=C39,"Correcto", "Corregir") -> Correcto
A40: Video | B40: Obligatorio | C40: 6 | D40: 5 | I40: =IF(D40<=C40,"Correcto", "Corregir") -> Correcto
A41: Lectura | B41: Optativo | C41: 10 | D41: 5 | I41: =IF(D41<=C41,"Correcto", "Corregir") -> Correcto
A42: Ejercicio Demostrativo | B42: Obligatorio | C42: 30 | D42: 25 | I42: =IF(D42<=C42,"Correcto", "Corregir") -> Correcto
A44: 3. Área de Habilidades (Saber Hacer) | G44: Tiempo Aproximado | H44: =B50 -> 20
G45: Tiene que estar en un rango de 30 a 50 minutos
A46: Actividad 1 (Obligatoria)
A47: Competencia que predomina en la actividad | B47: Identifica los componentes físicos y lógicos de un sistema computacional utilizando el modelo de Von Neumann y la clasificación de software por categorías para distinguir la función de cada elemento dentro de la arquitectura de procesamiento
A48: Tipo de Actividad | B48: Cuestionario
A49: Ponderación | B49: 2
A50: Tiempo Aproximado | B50: 20
A51: Coloca el tiempo que usar en la actividad, un tiempo sugerido 30 minutos
A52: Descripcion de la Actividad
A57: Actividad 2 (Optativa puedes hacerla si lo consideras apropiado)
A58: Competencia que predomina en la actividad
A59: Tipo de Actividad
A60: Ponderación
A61: Tiempo Aproximado
A62: Coloca el tiempo que usar en la actividad, un tiempo sugerido 20 minutos
A63: Descripcion de la Actividad
A68: 3. Cierre | G68: Tiempo Aproximado | H68: =B70 -> 15
G69: Tiene que estar en un rango de 10 a 15 minutos
A70: Tiempo Aproximado | B70: 15
A71: Asignacion de Actividades
A72: Corto 1 (mismo dia)
A74: Resuelve alguna duda, asigna las actividades que deben realizar, dudas de proyectos, etc

Sheet S.4
B2: Diseño de la Sesión de Laboratorio
B4: Curso | C4: ='Diseño'!C4 -> 768 - Algoritmos
B5: Semana | C5: 4
B6: Tiempo | C6: =H10+H21+H44+H68 -> 100
B7: Ponderación | C7: =B49+B60 -> 0
B8: Validación de Tiempo | C8: =IF(H44<=0, "❌ ERROR: La Actividad 1 debe tener un tiempo mayor a 0.", IF(H21>60, "❌ ERROR: El 'Área de Conocimiento' no puede exceder los 60 min.", IF((H10+H21+H44+H68)<100, "❌ ERROR: El tiempo total debe ser de al menos 100 min.", "✅ VALIDACIÓN CORRECTA"))) -> ✅ VALIDACIÓN CORRECTA
A10: 1. Área Actitudinal (Saber Ser) | G10: Tiempo Aproximado | H10: =B13 -> 5
G11: Tiene que estar en un rango de 3 a 5 minutos
A12: Nombre del Valor | B12: Responsabilidad profesional
A13: Tiempo Aproximado | B13: 5
A14: Descripcion
A15: Compromiso de actuar conforme a normas, estándares y buenas prácticas vigentes en el ejercicio técnico
A17: Como se relaciona con los conocimientos de la sesion y se aplicaria
A18: El uso correcto de software, cumplimiento de normativas y estándares internacionales define la práctica ética en TI. El estudiante identifica al menos una normativa aplicable a cada categoría de software revisada en la sesión.
A21: 2. Área Conocimiento (Saber) | G21: Tiempo Aproximado | H21: =SUM(D39:H42) -> 60
G22: No puede exceder los 60 minutos
A23: Competencia a desarrollar | B23: Identifica los componentes físicos y lógicos de un sistema computacional utilizando el modelo de Von Neumann y la clasificación de software por categorías para distinguir la función de cada elemento dentro de la arquitectura de procesamiento
A24: Competencia a desarrollar | B24: Analiza los fundamentos del hardware, software y arquitectura computacional mediante el ciclo fetch-decode-execute, sistemas de numeración y codificación de información para establecer la base conceptual del procesamiento y flujo de datos en sistemas computacionales
A26: 2.1 Contenido
A27: No. | B27: Unidad | D27: Tema | F27: Sub Tema
A28: 1 | B28: =IFERROR(__xludf.DUMMYFUNCTION("FILTER('Diseño'!D:D,'Diseño'!H:H=$C$5)"),"Unidad 2 - Arquitectura y organización VNA") -> Unidad 2 - Arquitectura y organización VNA | D28: =IFERROR(__xludf.DUMMYFUNCTION("FILTER('Diseño'!E:E,'Diseño'!H:H=$C$5)"),"Software de sistema") -> Software de sistema | F28: =IFERROR(__xludf.DUMMYFUNCTION("FILTER('Diseño'!F:F,'Diseño'!H:H=$C$5)"),"Sistemas operativos, hipervisores y utilitarios") -> Sistemas operativos, hipervisores y utilitarios
A29: 2 | B29: =IFERROR(__xludf.DUMMYFUNCTION("""COMPUTED_VALUE"""),"Unidad 2 - Arquitectura y organización VNA") -> Unidad 2 - Arquitectura y organización VNA | D29: =IFERROR(__xludf.DUMMYFUNCTION("""COMPUTED_VALUE"""),"Software de aplicación") -> Software de aplicación | F29: =IFERROR(__xludf.DUMMYFUNCTION("""COMPUTED_VALUE"""),"ERP, CRM, WMS y ofimática") -> ERP, CRM, WMS y ofimática
A30: 3 | B30: =IFERROR(__xludf.DUMMYFUNCTION("""COMPUTED_VALUE"""),"Unidad 2 - Arquitectura y organización VNA") -> Unidad 2 - Arquitectura y organización VNA | D30: =IFERROR(__xludf.DUMMYFUNCTION("""COMPUTED_VALUE"""),"Software de programación") -> Software de programación | F30: =IFERROR(__xludf.DUMMYFUNCTION("""COMPUTED_VALUE"""),"Lenguajes de programación y su clasificación") -> Lenguajes de programación y su clasificación
A31: 4 | B31: =IFERROR(__xludf.DUMMYFUNCTION("""COMPUTED_VALUE"""),"Unidad 2 - Arquitectura y organización VNA") -> Unidad 2 - Arquitectura y organización VNA | D31: =IFERROR(__xludf.DUMMYFUNCTION("""COMPUTED_VALUE"""),"Calidad y seguridad") -> Calidad y seguridad | F31: =IFERROR(__xludf.DUMMYFUNCTION("""COMPUTED_VALUE"""),"Normativas y estándares internacionales") -> Normativas y estándares internacionales
A32: 5 | B32: =IFERROR(__xludf.DUMMYFUNCTION("""COMPUTED_VALUE"""),"Unidad 2 - Arquitectura y organización VNA") -> Unidad 2 - Arquitectura y organización VNA | D32: =IFERROR(__xludf.DUMMYFUNCTION("""COMPUTED_VALUE"""),"Firmware") -> Firmware | F32: =IFERROR(__xludf.DUMMYFUNCTION("""COMPUTED_VALUE"""),"Programación y control del hardware a bajo nivel") -> Programación y control del hardware a bajo nivel
A33: 6
A34: 7
A36: 2.2 Recursos Educativos
A38: Tipo de Recurso a utilizar | B38: Tipo | C38: Valor maximo recomendado en Minutos | D38: Tiempo Aproximado ( unicamente el valor de minutos ) | I38: Validacion
A39: Presentacion | B39: Obligatorio | C39: 30 | D39: 25 | I39: =IF(D39<=C39,"Correcto", "Corregir") -> Correcto
A40: Video | B40: Obligatorio | C40: 6 | D40: 5 | I40: =IF(D40<=C40,"Correcto", "Corregir") -> Correcto
A41: Lectura | B41: Optativo | C41: 10 | D41: 5 | I41: =IF(D41<=C41,"Correcto", "Corregir") -> Correcto
A42: Ejercicio Demostrativo | B42: Obligatorio | C42: 30 | D42: 25 | I42: =IF(D42<=C42,"Correcto", "Corregir") -> Correcto
A44: 3. Área de Habilidades (Saber Hacer) | G44: Tiempo Aproximado | H44: =B50 -> 25
G45: Tiene que estar en un rango de 30 a 50 minutos
A46: Actividad 1 (Obligatoria)
A47: Competencia que predomina en la actividad | B47: Identifica los componentes físicos y lógicos de un sistema computacional utilizando el modelo de Von Neumann y la clasificación de software por categorías para distinguir la función de cada elemento dentro de la arquitectura de procesamiento
A48: Tipo de Actividad | B48: Analisis
A49: Ponderación | B49: 0
A50: Tiempo Aproximado | B50: 25
A51: Coloca el tiempo que usar en la actividad, un tiempo sugerido 30 minutos
A52: Descripcion de la Actividad
A57: Actividad 2 (Optativa puedes hacerla si lo consideras apropiado)
A58: Competencia que predomina en la actividad
A59: Tipo de Actividad
A60: Ponderación
A61: Tiempo Aproximado
A62: Coloca el tiempo que usar en la actividad, un tiempo sugerido 20 minutos
A63: Descripcion de la Actividad
A68: 3. Cierre | G68: Tiempo Aproximado | H68: =B70 -> 10
G69: Tiene que estar en un rango de 10 a 15 minutos
A70: Tiempo Aproximado | B70: 10
A71: Asignacion de Actividades
A72: Tarea 2 (7 dias)
A74: Resuelve alguna duda, asigna las actividades que deben realizar, dudas de proyectos, etc

Sheet S.5
B2: Diseño de la Sesión de Laboratorio
B4: Curso | C4: ='Diseño'!C4 -> 768 - Algoritmos
B5: Semana | C5: 5
B6: Tiempo | C6: =H10+H21+H44+H68 -> 100
B7: Ponderación | C7: =B49+B60 -> 2
B8: Validación de Tiempo | C8: =IF(H44<=0, "❌ ERROR: La Actividad 1 debe tener un tiempo mayor a 0.", IF(H21>60, "❌ ERROR: El 'Área de Conocimiento' no puede exceder los 60 min.", IF((H10+H21+H44+H68)<100, "❌ ERROR: El tiempo total debe ser de al menos 100 min.", "✅ VALIDACIÓN CORRECTA"))) -> ✅ VALIDACIÓN CORRECTA
A10: 1. Área Actitudinal (Saber Ser) | G10: Tiempo Aproximado | H10: =B13 -> 5
G11: Tiene que estar en un rango de 3 a 5 minutos
A12: Nombre del Valor | B12: Precisión
A13: Tiempo Aproximado | B13: 5
A14: Descripcion
A15: Precisión en la ejecución de procesos y en la representación de información, evitando errores por descuido
A17: Como se relaciona con los conocimientos de la sesion y se aplicaria
A18: La conversión entre sistemas de numeración y la codificación de datos exigen resultados exactos sin margen de error. El estudiante verifica cada conversión numérica paso a paso y comprueba el resultado en al menos dos métodos distintos.
A21: 2. Área Conocimiento (Saber) | G21: Tiempo Aproximado | H21: =SUM(D39:H42) -> 60
G22: No puede exceder los 60 minutos
A23: Competencia a desarrollar | B23: Convierte valores numéricos entre sistemas de numeración decimal, binario, octal y hexadecimal aplicando los métodos de conversión posicional y los estándares de codificación ASCII, UNICODE e ISO-8859 para representar datos primitivos, imágenes, audio y video en formato digital
A24: Competencia a desarrollar
A26: 2.1 Contenido
A27: No. | B27: Unidad | D27: Tema | F27: Sub Tema
A28: 1 | B28: =IFERROR(__xludf.DUMMYFUNCTION("FILTER('Diseño'!D:D,'Diseño'!H:H=$C$5)"),"Unidad 4 – Codificación de la Información") -> Unidad 4 – Codificación de la Información | D28: =IFERROR(__xludf.DUMMYFUNCTION("FILTER('Diseño'!E:E,'Diseño'!H:H=$C$5)"),"Sistemas de numeración") -> Sistemas de numeración | F28: =IFERROR(__xludf.DUMMYFUNCTION("FILTER('Diseño'!F:F,'Diseño'!H:H=$C$5)"),"Sistema decimal, binario, octal y hexadecimal") -> Sistema decimal, binario, octal y hexadecimal
A29: 2 | B29: =IFERROR(__xludf.DUMMYFUNCTION("""COMPUTED_VALUE"""),"Unidad 4 – Codificación de la Información") -> Unidad 4 – Codificación de la Información | D29: =IFERROR(__xludf.DUMMYFUNCTION("""COMPUTED_VALUE"""),"Codificación") -> Codificación | F29: =IFERROR(__xludf.DUMMYFUNCTION("""COMPUTED_VALUE"""),"ASCII, EBCDIC, UNICODE, ISO-8859") -> ASCII, EBCDIC, UNICODE, ISO-8859
A30: 3 | B30: =IFERROR(__xludf.DUMMYFUNCTION("""COMPUTED_VALUE"""),"Unidad 4 – Codificación de la Información") -> Unidad 4 – Codificación de la Información | D30: =IFERROR(__xludf.DUMMYFUNCTION("""COMPUTED_VALUE"""),"Representación de datos") -> Representación de datos | F30: =IFERROR(__xludf.DUMMYFUNCTION("""COMPUTED_VALUE"""),"Tipos de datos primitivos, imágenes, audio y video") -> Tipos de datos primitivos, imágenes, audio y video
A31: 4
A32: 5
A33: 6
A34: 7
A36: 2.2 Recursos Educativos
A38: Tipo de Recurso a utilizar | B38: Tipo | C38: Valor maximo recomendado en Minutos | D38: Tiempo Aproximado ( unicamente el valor de minutos ) | I38: Validacion
A39: Presentacion | B39: Obligatorio | C39: 30 | D39: 25 | I39: =IF(D39<=C39,"Correcto", "Corregir") -> Correcto
A40: Video | B40: Obligatorio | C40: 6 | D40: 5 | I40: =IF(D40<=C40,"Correcto", "Corregir") -> Correcto
A41: Lectura | B41: Optativo | C41: 10 | D41: 5 | I41: =IF(D41<=C41,"Correcto", "Corregir") -> Correcto
A42: Ejercicio Demostrativo | B42: Obligatorio | C42: 30 | D42: 25 | I42: =IF(D42<=C42,"Correcto", "Corregir") -> Correcto
A44: 3. Área de Habilidades (Saber Hacer) | G44: Tiempo Aproximado | H44: =B50 -> 20
G45: Tiene que estar en un rango de 30 a 50 minutos
A46: Actividad 1 (Obligatoria)
A47: Competencia que predomina en la actividad | B47: Convierte valores numéricos entre sistemas de numeración decimal, binario, octal y hexadecimal aplicando los métodos de conversión posicional y los estándares de codificación ASCII, UNICODE e ISO-8859 para representar datos primitivos, imágenes, audio y video en formato digital
A48: Tipo de Actividad | B48: Cuestionario
A49: Ponderación | B49: 2
A50: Tiempo Aproximado | B50: 20
A51: Coloca el tiempo que usar en la actividad, un tiempo sugerido 30 minutos
A52: Descripcion de la Actividad
A57: Actividad 2 (Optativa puedes hacerla si lo consideras apropiado)
A58: Competencia que predomina en la actividad
A59: Tipo de Actividad
A60: Ponderación
A61: Tiempo Aproximado
A62: Coloca el tiempo que usar en la actividad, un tiempo sugerido 20 minutos
A63: Descripcion de la Actividad
A68: 3. Cierre | G68: Tiempo Aproximado | H68: =B70 -> 15
G69: Tiene que estar en un rango de 10 a 15 minutos
A70: Tiempo Aproximado | B70: 15
A71: Asignacion de Actividades
A72: Corto 3 (mismo dia)
A74: Resuelve alguna duda, asigna las actividades que deben realizar, dudas de proyectos, etc

Sheet S.6
B2: Diseño de la Sesión de Laboratorio
B4: Curso | C4: ='Diseño'!C4 -> 768 - Algoritmos
B5: Semana | C5: 6
B6: Tiempo | C6: =H10+H21+H44+H68 -> 100
B7: Ponderación | C7: =B49+B60 -> 0
B8: Validación de Tiempo | C8: =IF(H44<=0, "❌ ERROR: La Actividad 1 debe tener un tiempo mayor a 0.", IF(H21>60, "❌ ERROR: El 'Área de Conocimiento' no puede exceder los 60 min.", IF((H10+H21+H44+H68)<100, "❌ ERROR: El tiempo total debe ser de al menos 100 min.", "✅ VALIDACIÓN CORRECTA"))) -> ✅ VALIDACIÓN CORRECTA
A10: 1. Área Actitudinal (Saber Ser) | G10: Tiempo Aproximado | H10: =B13 -> 5
G11: Tiene que estar en un rango de 3 a 5 minutos
A12: Nombre del Valor | B12: Pensamiento crítico
A13: Tiempo Aproximado | B13: 5
A14: Descripcion
A15: Habilidad para analizar un problema, cuestionar supuestos y distinguir lo esencial de lo accesorio antes de actuar.
A17: Como se relaciona con los conocimientos de la sesion y se aplicaria
A18: Definir correctamente un problema algorítmico requiere cuestionar el contexto, las instancias y la validez de la solución. El estudiante reformula un enunciado de problema dado en clase identificando sus supuestos implícitos y condiciones reales.
A21: 2. Área Conocimiento (Saber) | G21: Tiempo Aproximado | H21: =SUM(D39:H42) -> 60
G22: No puede exceder los 60 minutos
A23: Competencia a desarrollar | B23: Descompone problemas computacionales en subproblemas definidos mediante técnicas de descomposición, reconocimiento de patrones y abstracción para estructurar soluciones algorítmicas a partir de instancias y contextos concretos
A24: Competencia a desarrollar
A26: 2.1 Contenido
A27: No. | B27: Unidad | D27: Tema | F27: Sub Tema
A28: 1 | B28: =IFERROR(__xludf.DUMMYFUNCTION("FILTER('Diseño'!D:D,'Diseño'!H:H=$C$5)"),"Unidad 4 – Fundamentos de Algoritmos") -> Unidad 4 – Fundamentos de Algoritmos | D28: =IFERROR(__xludf.DUMMYFUNCTION("FILTER('Diseño'!E:E,'Diseño'!H:H=$C$5)"),"Fundamentos de algoritmos") -> Fundamentos de algoritmos | F28: =IFERROR(__xludf.DUMMYFUNCTION("FILTER('Diseño'!F:F,'Diseño'!H:H=$C$5)"),"Descomposición, reconocimiento de patrones y abstracción") -> Descomposición, reconocimiento de patrones y abstracción
A29: 2 | B29: =IFERROR(__xludf.DUMMYFUNCTION("""COMPUTED_VALUE"""),"Unidad 4 – Fundamentos de Algoritmos") -> Unidad 4 – Fundamentos de Algoritmos | D29: =IFERROR(__xludf.DUMMYFUNCTION("""COMPUTED_VALUE"""),"Definición de un problema") -> Definición de un problema | F29: =IFERROR(__xludf.DUMMYFUNCTION("""COMPUTED_VALUE"""),"Instancias y soluciones") -> Instancias y soluciones
A30: 3 | B30: =IFERROR(__xludf.DUMMYFUNCTION("""COMPUTED_VALUE"""),"Unidad 4 – Fundamentos de Algoritmos") -> Unidad 4 – Fundamentos de Algoritmos | D30: =IFERROR(__xludf.DUMMYFUNCTION("""COMPUTED_VALUE"""),"Características de un problema") -> Características de un problema | F30: =IFERROR(__xludf.DUMMYFUNCTION("""COMPUTED_VALUE"""),"Necesidad de la solución, contexto claro, relevancia") -> Necesidad de la solución, contexto claro, relevancia
A31: 4
A32: 5
A33: 6
A34: 7
A36: 2.2 Recursos Educativos
A38: Tipo de Recurso a utilizar | B38: Tipo | C38: Valor maximo recomendado en Minutos | D38: Tiempo Aproximado ( unicamente el valor de minutos ) | I38: Validacion
A39: Presentacion | B39: Obligatorio | C39: 30 | D39: 25 | I39: =IF(D39<=C39,"Correcto", "Corregir") -> Correcto
A40: Video | B40: Obligatorio | C40: 6 | D40: 5 | I40: =IF(D40<=C40,"Correcto", "Corregir") -> Correcto
A41: Lectura | B41: Optativo | C41: 10 | D41: 5 | I41: =IF(D41<=C41,"Correcto", "Corregir") -> Correcto
A42: Ejercicio Demostrativo | B42: Obligatorio | C42: 30 | D42: 25 | I42: =IF(D42<=C42,"Correcto", "Corregir") -> Correcto
A44: 3. Área de Habilidades (Saber Hacer) | G44: Tiempo Aproximado | H44: =B50 -> 25
G45: Tiene que estar en un rango de 30 a 50 minutos
A46: Actividad 1 (Obligatoria)
A47: Competencia que predomina en la actividad | B47: Descompone problemas computacionales en subproblemas definidos mediante técnicas de descomposición, reconocimiento de patrones y abstracción para estructurar soluciones algorítmicas a partir de instancias y contextos concretos
A48: Tipo de Actividad | B48: Analisis
A49: Ponderación | B49: 0
A50: Tiempo Aproximado | B50: 25
A51: Coloca el tiempo que usar en la actividad, un tiempo sugerido 30 minutos
A52: Descripcion de la Actividad
A57: Actividad 2 (Optativa puedes hacerla si lo consideras apropiado)
A58: Competencia que predomina en la actividad
A59: Tipo de Actividad
A60: Ponderación
A61: Tiempo Aproximado
A62: Coloca el tiempo que usar en la actividad, un tiempo sugerido 20 minutos
A63: Descripcion de la Actividad
A68: 3. Cierre | G68: Tiempo Aproximado | H68: =B70 -> 10
G69: Tiene que estar en un rango de 10 a 15 minutos
A70: Tiempo Aproximado | B70: 10
A71: Asignacion de Actividades
A72: Tarea 3 (7 dias)
A74: Resuelve alguna duda, asigna las actividades que deben realizar, dudas de proyectos, etc

Sheet S.7
B2: Diseño de la Sesión de Laboratorio
B4: Curso | C4: ='Diseño'!C4 -> 768 - Algoritmos
B5: Semana | C5: 7
B6: Tiempo | C6: =H10+H21+H44+H68 -> 100
B7: Ponderación | C7: =B49+B60 -> 2
B8: Validación de Tiempo | C8: =IF(H44<=0, "❌ ERROR: La Actividad 1 debe tener un tiempo mayor a 0.", IF(H21>60, "❌ ERROR: El 'Área de Conocimiento' no puede exceder los 60 min.", IF((H10+H21+H44+H68)<100, "❌ ERROR: El tiempo total debe ser de al menos 100 min.", "✅ VALIDACIÓN CORRECTA"))) -> ✅ VALIDACIÓN CORRECTA
A10: 1. Área Actitudinal (Saber Ser) | G10: Tiempo Aproximado | H10: =B13 -> 5
G11: Tiene que estar en un rango de 3 a 5 minutos
A12: Nombre del Valor | B12: Orden y método
A13: Tiempo Aproximado | B13: 5
A14: Descripcion
A15: Hábito de estructurar el trabajo de forma secuencial, jerárquica y documentada para garantizar resultados reproducibles.
A17: Como se relaciona con los conocimientos de la sesion y se aplicaria
A18: Descomponer problemas y representarlos de forma estructurada demanda un proceso ordenado y sistemático. El estudiante aplica una técnica de segmentación específica y entrega la representación estructurada del subproblema asignado.
A21: 2. Área Conocimiento (Saber) | G21: Tiempo Aproximado | H21: =SUM(D39:H42) -> 60
G22: No puede exceder los 60 minutos
A23: Competencia a desarrollar | B23: Descompone problemas computacionales en subproblemas definidos mediante técnicas de descomposición, reconocimiento de patrones y abstracción para estructurar soluciones algorítmicas a partir de instancias y contextos concretos
A24: Competencia a desarrollar | B24: Diseña algoritmos que resuelven problemas determinísticos, condicionales y cíclicos empleando estructuras de control secuenciales, condicionales y repetitivas en pseudocódigo para producir soluciones correctas, legibles y verificables en un entorno de desarrollo introductorio
A26: 2.1 Contenido
A27: No. | B27: Unidad | D27: Tema | F27: Sub Tema
A28: 1 | B28: =IFERROR(__xludf.DUMMYFUNCTION("FILTER('Diseño'!D:D,'Diseño'!H:H=$C$5)"),"Unidad 4 – Fundamentos de Algoritmos") -> Unidad 4 – Fundamentos de Algoritmos | D28: =IFERROR(__xludf.DUMMYFUNCTION("FILTER('Diseño'!E:E,'Diseño'!H:H=$C$5)"),"Tipos de problemas computacionales") -> Tipos de problemas computacionales | F28: =IFERROR(__xludf.DUMMYFUNCTION("FILTER('Diseño'!F:F,'Diseño'!H:H=$C$5)"),"Determinísticos, probabilísticos, secuenciales, condicionales y cíclicos") -> Determinísticos, probabilísticos, secuenciales, condicionales y cíclicos
A29: 2 | B29: =IFERROR(__xludf.DUMMYFUNCTION("""COMPUTED_VALUE"""),"Unidad 4 – Fundamentos de Algoritmos") -> Unidad 4 – Fundamentos de Algoritmos | D29: =IFERROR(__xludf.DUMMYFUNCTION("""COMPUTED_VALUE"""),"Descomposición de problemas") -> Descomposición de problemas | F29: =IFERROR(__xludf.DUMMYFUNCTION("""COMPUTED_VALUE"""),"Técnicas de segmentación e identificación de subproblemas") -> Técnicas de segmentación e identificación de subproblemas
A30: 3 | B30: =IFERROR(__xludf.DUMMYFUNCTION("""COMPUTED_VALUE"""),"Unidad 4 – Fundamentos de Algoritmos") -> Unidad 4 – Fundamentos de Algoritmos | D30: =IFERROR(__xludf.DUMMYFUNCTION("""COMPUTED_VALUE"""),"Representación del problema") -> Representación del problema | F30: =IFERROR(__xludf.DUMMYFUNCTION("""COMPUTED_VALUE"""),"Representación estructurada del problema") -> Representación estructurada del problema
A31: 4
A32: 5
A33: 6
A34: 7
A36: 2.2 Recursos Educativos
A38: Tipo de Recurso a utilizar | B38: Tipo | C38: Valor maximo recomendado en Minutos | D38: Tiempo Aproximado ( unicamente el valor de minutos ) | I38: Validacion
A39: Presentacion | B39: Obligatorio | C39: 30 | D39: 25 | I39: =IF(D39<=C39,"Correcto", "Corregir") -> Correcto
A40: Video | B40: Obligatorio | C40: 6 | D40: 5 | I40: =IF(D40<=C40,"Correcto", "Corregir") -> Correcto
A41: Lectura | B41: Optativo | C41: 10 | D41: 5 | I41: =IF(D41<=C41,"Correcto", "Corregir") -> Correcto
A42: Ejercicio Demostrativo | B42: Obligatorio | C42: 30 | D42: 25 | I42: =IF(D42<=C42,"Correcto", "Corregir") -> Correcto
A44: 3. Área de Habilidades (Saber Hacer) | G44: Tiempo Aproximado | H44: =B50 -> 20
G45: Tiene que estar en un rango de 30 a 50 minutos
A46: Actividad 1 (Obligatoria)
A47: Competencia que predomina en la actividad | B47: Diseña algoritmos que resuelven problemas determinísticos, condicionales y cíclicos empleando estructuras de control secuenciales, condicionales y repetitivas en pseudocódigo para producir soluciones correctas, legibles y verificables en un entorno de desarrollo introductorio
A48: Tipo de Actividad | B48: Cuestionario
A49: Ponderación | B49: 2
A50: Tiempo Aproximado | B50: 20
A51: Coloca el tiempo que usar en la actividad, un tiempo sugerido 30 minutos
A52: Descripcion de la Actividad
A57: Actividad 2 (Optativa puedes hacerla si lo consideras apropiado)
A58: Competencia que predomina en la actividad
A59: Tipo de Actividad
A60: Ponderación
A61: Tiempo Aproximado
A62: Coloca el tiempo que usar en la actividad, un tiempo sugerido 20 minutos
A63: Descripcion de la Actividad
A68: 3. Cierre | G68: Tiempo Aproximado | H68: =B70 -> 15
G69: Tiene que estar en un rango de 10 a 15 minutos
A70: Tiempo Aproximado | B70: 15
A71: Asignacion de Actividades
A74: Resuelve alguna duda, asigna las actividades que deben realizar, dudas de proyectos, etc

Sheet S.8
B2: Diseño de la Sesión de Laboratorio
B4: Curso | C4: ='Diseño'!C4 -> 768 - Algoritmos
B5: Semana | C5: 8
B6: Tiempo | C6: =H10+H21+H44+H68 -> 100
B7: Ponderación | C7: =B49+B60 -> 0
B8: Validación de Tiempo | C8: =IF(H44<=0, "❌ ERROR: La Actividad 1 debe tener un tiempo mayor a 0.", IF(H21>60, "❌ ERROR: El 'Área de Conocimiento' no puede exceder los 60 min.", IF((H10+H21+H44+H68)<100, "❌ ERROR: El tiempo total debe ser de al menos 100 min.", "✅ VALIDACIÓN CORRECTA"))) -> ✅ VALIDACIÓN CORRECTA
A10: 1. Área Actitudinal (Saber Ser) | G10: Tiempo Aproximado | H10: =B13 -> 5
G11: Tiene que estar en un rango de 3 a 5 minutos
A12: Nombre del Valor | B12: Disciplina
A13: Tiempo Aproximado | B13: 5
A14: Descripcion
A15: Constancia en el cumplimiento de reglas, sintaxis y convenciones establecidas, incluso cuando resulta exigente.
A17: Como se relaciona con los conocimientos de la sesion y se aplicaria
A18: Escribir algoritmos con instrucciones, palabras reservadas y estructuras condicionales correctas requiere disciplina sintáctica. El estudiante revisa su pseudocódigo contra una lista de verificación de elementos antes de entregarlo.
A21: 2. Área Conocimiento (Saber) | G21: Tiempo Aproximado | H21: =SUM(D39:H42) -> 60
G22: No puede exceder los 60 minutos
A23: Competencia a desarrollar | B23: Diseña algoritmos que resuelven problemas determinísticos, condicionales y cíclicos empleando estructuras de control secuenciales, condicionales y repetitivas en pseudocódigo para producir soluciones correctas, legibles y verificables en un entorno de desarrollo introductorio
A24: Competencia a desarrollar
A26: 2.1 Contenido
A27: No. | B27: Unidad | D27: Tema | F27: Sub Tema
A28: 1 | B28: =IFERROR(__xludf.DUMMYFUNCTION("FILTER('Diseño'!D:D,'Diseño'!H:H=$C$5)"),"Unidad 5 – Algoritmos") -> Unidad 5 – Algoritmos | D28: =IFERROR(__xludf.DUMMYFUNCTION("FILTER('Diseño'!E:E,'Diseño'!H:H=$C$5)"),"Elementos de un algoritmo") -> Elementos de un algoritmo | F28: =IFERROR(__xludf.DUMMYFUNCTION("FILTER('Diseño'!F:F,'Diseño'!H:H=$C$5)"),"Instrucciones o sentencias y palabras reservadas") -> Instrucciones o sentencias y palabras reservadas
A29: 2 | B29: =IFERROR(__xludf.DUMMYFUNCTION("""COMPUTED_VALUE"""),"Unidad 5 – Algoritmos") -> Unidad 5 – Algoritmos | D29: =IFERROR(__xludf.DUMMYFUNCTION("""COMPUTED_VALUE"""),"Elementos de un algoritmo") -> Elementos de un algoritmo | F29: =IFERROR(__xludf.DUMMYFUNCTION("""COMPUTED_VALUE"""),"Tipos de datos") -> Tipos de datos
A30: 3 | B30: =IFERROR(__xludf.DUMMYFUNCTION("""COMPUTED_VALUE"""),"Unidad 5 – Algoritmos") -> Unidad 5 – Algoritmos | D30: =IFERROR(__xludf.DUMMYFUNCTION("""COMPUTED_VALUE"""),"Elementos de un algoritmo") -> Elementos de un algoritmo | F30: =IFERROR(__xludf.DUMMYFUNCTION("""COMPUTED_VALUE"""),"Estructuras condicionales") -> Estructuras condicionales
A31: 4
A32: 5
A33: 6
A34: 7
A36: 2.2 Recursos Educativos
A38: Tipo de Recurso a utilizar | B38: Tipo | C38: Valor maximo recomendado en Minutos | D38: Tiempo Aproximado ( unicamente el valor de minutos ) | I38: Validacion
A39: Presentacion | B39: Obligatorio | C39: 30 | D39: 25 | I39: =IF(D39<=C39,"Correcto", "Corregir") -> Correcto
A40: Video | B40: Obligatorio | C40: 6 | D40: 5 | I40: =IF(D40<=C40,"Correcto", "Corregir") -> Correcto
A41: Lectura | B41: Optativo | C41: 10 | D41: 5 | I41: =IF(D41<=C41,"Correcto", "Corregir") -> Correcto
A42: Ejercicio Demostrativo | B42: Obligatorio | C42: 30 | D42: 25 | I42: =IF(D42<=C42,"Correcto", "Corregir") -> Correcto
A44: 3. Área de Habilidades (Saber Hacer) | G44: Tiempo Aproximado | H44: =B50 -> 25
G45: Tiene que estar en un rango de 30 a 50 minutos
A46: Actividad 1 (Obligatoria)
A47: Competencia que predomina en la actividad | B47: Diseña algoritmos que resuelven problemas determinísticos, condicionales y cíclicos empleando estructuras de control secuenciales, condicionales y repetitivas en pseudocódigo para producir soluciones correctas, legibles y verificables en un entorno de desarrollo introductorio
A48: Tipo de Actividad | B48: Analisis
A49: Ponderación | B49: 0
A50: Tiempo Aproximado | B50: 25
A51: Coloca el tiempo que usar en la actividad, un tiempo sugerido 30 minutos
A52: Descripcion de la Actividad
A57: Actividad 2 (Optativa puedes hacerla si lo consideras apropiado)
A58: Competencia que predomina en la actividad
A59: Tipo de Actividad
A60: Ponderación
A61: Tiempo Aproximado
A62: Coloca el tiempo que usar en la actividad, un tiempo sugerido 20 minutos
A63: Descripcion de la Actividad
A68: 3. Cierre | G68: Tiempo Aproximado | H68: =B70 -> 10
G69: Tiene que estar en un rango de 10 a 15 minutos
A70: Tiempo Aproximado | B70: 10
A71: Asignacion de Actividades
A72: Tarea 4 (7 dias)
A74: Resuelve alguna duda, asigna las actividades que deben realizar, dudas de proyectos, etc

Sheet S.9
B2: Diseño de la Sesión de Laboratorio
B4: Curso | C4: ='Diseño'!C4 -> 768 - Algoritmos
B5: Semana | C5: 9
B6: Tiempo | C6: =H10+H21+H44+H68 -> 100
B7: Ponderación | C7: =B49+B60 -> 2
B8: Validación de Tiempo | C8: =IF(H44<=0, "❌ ERROR: La Actividad 1 debe tener un tiempo mayor a 0.", IF(H21>60, "❌ ERROR: El 'Área de Conocimiento' no puede exceder los 60 min.", IF((H10+H21+H44+H68)<100, "❌ ERROR: El tiempo total debe ser de al menos 100 min.", "✅ VALIDACIÓN CORRECTA"))) -> ✅ VALIDACIÓN CORRECTA
A10: 1. Área Actitudinal (Saber Ser) | G10: Tiempo Aproximado | H10: =B13 -> 5
G11: Tiene que estar en un rango de 3 a 5 minutos
A12: Nombre del Valor | B12: Perseverancia
A13: Tiempo Aproximado | B13: 5
A14: Descripcion
A15: Capacidad de continuar trabajando ante dificultades, errores o resultados inesperados sin abandonar el proceso.
A17: Como se relaciona con los conocimientos de la sesion y se aplicaria
A18: Dominar estructuras cíclicas y manipulación de cadenas implica depurar errores repetidamente hasta lograr el resultado correcto. El estudiante registra cada error encontrado en su algoritmo y documenta la corrección aplicada en cada caso.
A21: 2. Área Conocimiento (Saber) | G21: Tiempo Aproximado | H21: =SUM(D39:H42) -> 60
G22: No puede exceder los 60 minutos
A23: Competencia a desarrollar | B23: Diseña algoritmos que resuelven problemas determinísticos, condicionales y cíclicos empleando estructuras de control secuenciales, condicionales y repetitivas en pseudocódigo para producir soluciones correctas, legibles y verificables en un entorno de desarrollo introductorio
A24: Competencia a desarrollar
A26: 2.1 Contenido
A27: No. | B27: Unidad | D27: Tema | F27: Sub Tema
A28: 1 | B28: =IFERROR(__xludf.DUMMYFUNCTION("FILTER('Diseño'!D:D,'Diseño'!H:H=$C$5)"),"Unidad 5 – Algoritmos") -> Unidad 5 – Algoritmos | D28: =IFERROR(__xludf.DUMMYFUNCTION("FILTER('Diseño'!E:E,'Diseño'!H:H=$C$5)"),"Elementos de un algoritmo") -> Elementos de un algoritmo | F28: =IFERROR(__xludf.DUMMYFUNCTION("FILTER('Diseño'!F:F,'Diseño'!H:H=$C$5)"),"Estructuras cíclicas") -> Estructuras cíclicas
A29: 2 | B29: =IFERROR(__xludf.DUMMYFUNCTION("""COMPUTED_VALUE"""),"Unidad 5 – Algoritmos") -> Unidad 5 – Algoritmos | D29: =IFERROR(__xludf.DUMMYFUNCTION("""COMPUTED_VALUE"""),"Elementos de un algoritmo") -> Elementos de un algoritmo | F29: =IFERROR(__xludf.DUMMYFUNCTION("""COMPUTED_VALUE"""),"Estructuras secuenciales") -> Estructuras secuenciales
A30: 3 | B30: =IFERROR(__xludf.DUMMYFUNCTION("""COMPUTED_VALUE"""),"Unidad 5 – Algoritmos") -> Unidad 5 – Algoritmos | D30: =IFERROR(__xludf.DUMMYFUNCTION("""COMPUTED_VALUE"""),"Manipulación de cadenas de caracteres") -> Manipulación de cadenas de caracteres | F30: =IFERROR(__xludf.DUMMYFUNCTION("""COMPUTED_VALUE"""),"Ventajas, desventajas y software de pseudocódigo") -> Ventajas, desventajas y software de pseudocódigo
A31: 4
A32: 5
A33: 6
A34: 7
A36: 2.2 Recursos Educativos
A38: Tipo de Recurso a utilizar | B38: Tipo | C38: Valor maximo recomendado en Minutos | D38: Tiempo Aproximado ( unicamente el valor de minutos ) | I38: Validacion
A39: Presentacion | B39: Obligatorio | C39: 30 | D39: 25 | I39: =IF(D39<=C39,"Correcto", "Corregir") -> Correcto
A40: Video | B40: Obligatorio | C40: 6 | D40: 5 | I40: =IF(D40<=C40,"Correcto", "Corregir") -> Correcto
A41: Lectura | B41: Optativo | C41: 10 | D41: 5 | I41: =IF(D41<=C41,"Correcto", "Corregir") -> Correcto
A42: Ejercicio Demostrativo | B42: Obligatorio | C42: 30 | D42: 25 | I42: =IF(D42<=C42,"Correcto", "Corregir") -> Correcto
A44: 3. Área de Habilidades (Saber Hacer) | G44: Tiempo Aproximado | H44: =B50 -> 20
G45: Tiene que estar en un rango de 30 a 50 minutos
A46: Actividad 1 (Obligatoria)
A47: Competencia que predomina en la actividad | B47: Diseña algoritmos que resuelven problemas determinísticos, condicionales y cíclicos empleando estructuras de control secuenciales, condicionales y repetitivas en pseudocódigo para producir soluciones correctas, legibles y verificables en un entorno de desarrollo introductorio
A48: Tipo de Actividad | B48: Cuestionario
A49: Ponderación | B49: 2
A50: Tiempo Aproximado | B50: 20
A51: Coloca el tiempo que usar en la actividad, un tiempo sugerido 30 minutos
A52: Descripcion de la Actividad
A57: Actividad 2 (Optativa puedes hacerla si lo consideras apropiado)
A58: Competencia que predomina en la actividad
A59: Tipo de Actividad
A60: Ponderación
A61: Tiempo Aproximado
A62: Coloca el tiempo que usar en la actividad, un tiempo sugerido 20 minutos
A63: Descripcion de la Actividad
A68: 3. Cierre | G68: Tiempo Aproximado | H68: =B70 -> 15
G69: Tiene que estar en un rango de 10 a 15 minutos
A70: Tiempo Aproximado | B70: 15
A71: Asignacion de Actividades
A72: Corto 3 (mismo dia)
A74: Resuelve alguna duda, asigna las actividades que deben realizar, dudas de proyectos, etc

Sheet S.10
B2: Diseño de la Sesión de Laboratorio
B4: Curso | C4: ='Diseño'!C4 -> 768 - Algoritmos
B5: Semana | C5: 10
B6: Tiempo | C6: =H10+H21+H44+H68 -> 105
B7: Ponderación | C7: =B49+B60 -> 0
B8: Validación de Tiempo | C8: =IF(H44<=0, "❌ ERROR: La Actividad 1 debe tener un tiempo mayor a 0.", IF(H21>60, "❌ ERROR: El 'Área de Conocimiento' no puede exceder los 60 min.", IF((H10+H21+H44+H68)<100, "❌ ERROR: El tiempo total debe ser de al menos 100 min.", "✅ VALIDACIÓN CORRECTA"))) -> ✅ VALIDACIÓN CORRECTA
A10: 1. Área Actitudinal (Saber Ser) | G10: Tiempo Aproximado | H10: =B13 -> 5
G11: Tiene que estar en un rango de 3 a 5 minutos
A12: Nombre del Valor | B12: Organización
A13: Tiempo Aproximado | B13: 5
A14: Descripcion
A15: Habilidad para estructurar datos, recursos y procesos de manera que faciliten su acceso, uso y mantenimiento.
A17: Como se relaciona con los conocimientos de la sesion y se aplicaria
A18: El uso de arreglos y diagramas de flujo refleja la necesidad de organizar datos y representar la lógica con claridad. El estudiante diseña el diagrama de flujo de su algoritmo con arreglos antes de escribir una sola línea de pseudocódigo.
A21: 2. Área Conocimiento (Saber) | G21: Tiempo Aproximado | H21: =SUM(D39:H42) -> 60
G22: No puede exceder los 60 minutos
A23: Competencia a desarrollar | B23: Implementa algoritmos con manejo de arreglos unidimensionales y multidimensionales utilizando herramientas de pseudocódigo y diagramas de flujo para representar y administrar colecciones de datos de forma estructurada
A24: Competencia a desarrollar
A26: 2.1 Contenido
A27: No. | B27: Unidad | D27: Tema | F27: Sub Tema
A28: 1 | B28: =IFERROR(__xludf.DUMMYFUNCTION("FILTER('Diseño'!D:D,'Diseño'!H:H=$C$5)"),"Unidad 5 – Algoritmos") -> Unidad 5 – Algoritmos | D28: =IFERROR(__xludf.DUMMYFUNCTION("FILTER('Diseño'!E:E,'Diseño'!H:H=$C$5)"),"Arreglos") -> Arreglos | F28: =IFERROR(__xludf.DUMMYFUNCTION("FILTER('Diseño'!F:F,'Diseño'!H:H=$C$5)"),"Arreglos unidimensionales y multidimensionales") -> Arreglos unidimensionales y multidimensionales
A29: 2 | B29: =IFERROR(__xludf.DUMMYFUNCTION("""COMPUTED_VALUE"""),"Unidad 5 – Algoritmos") -> Unidad 5 – Algoritmos | D29: =IFERROR(__xludf.DUMMYFUNCTION("""COMPUTED_VALUE"""),"Administración de algoritmos") -> Administración de algoritmos | F29: =IFERROR(__xludf.DUMMYFUNCTION("""COMPUTED_VALUE"""),"Herramientas de representación de algoritmos") -> Herramientas de representación de algoritmos
A30: 3 | B30: =IFERROR(__xludf.DUMMYFUNCTION("""COMPUTED_VALUE"""),"Unidad 5 – Algoritmos") -> Unidad 5 – Algoritmos | D30: =IFERROR(__xludf.DUMMYFUNCTION("""COMPUTED_VALUE"""),"Administración de algoritmos") -> Administración de algoritmos | F30: =IFERROR(__xludf.DUMMYFUNCTION("""COMPUTED_VALUE"""),"Diagramas de flujo") -> Diagramas de flujo
A31: 4
A32: 5
A33: 6
A34: 7
A36: 2.2 Recursos Educativos
A38: Tipo de Recurso a utilizar | B38: Tipo | C38: Valor maximo recomendado en Minutos | D38: Tiempo Aproximado ( unicamente el valor de minutos ) | I38: Validacion
A39: Presentacion | B39: Obligatorio | C39: 30 | D39: 25 | I39: =IF(D39<=C39,"Correcto", "Corregir") -> Correcto
A40: Video | B40: Obligatorio | C40: 6 | D40: 5 | I40: =IF(D40<=C40,"Correcto", "Corregir") -> Correcto
A41: Lectura | B41: Optativo | C41: 10 | D41: 5 | I41: =IF(D41<=C41,"Correcto", "Corregir") -> Correcto
A42: Ejercicio Demostrativo | B42: Obligatorio | C42: 30 | D42: 25 | I42: =IF(D42<=C42,"Correcto", "Corregir") -> Correcto
A44: 3. Área de Habilidades (Saber Hacer) | G44: Tiempo Aproximado | H44: =B50 -> 25
G45: Tiene que estar en un rango de 30 a 50 minutos
A46: Actividad 1 (Obligatoria)
A47: Competencia que predomina en la actividad | B47: Implementa algoritmos con manejo de arreglos unidimensionales y multidimensionales utilizando herramientas de pseudocódigo y diagramas de flujo para representar y administrar colecciones de datos de forma estructurada
A48: Tipo de Actividad | B48: Analisis
A49: Ponderación | B49: 0
A50: Tiempo Aproximado | B50: 25
A51: Coloca el tiempo que usar en la actividad, un tiempo sugerido 30 minutos
A52: Descripcion de la Actividad
A57: Actividad 2 (Optativa puedes hacerla si lo consideras apropiado)
A58: Competencia que predomina en la actividad
A59: Tipo de Actividad
A60: Ponderación
A61: Tiempo Aproximado
A62: Coloca el tiempo que usar en la actividad, un tiempo sugerido 20 minutos
A63: Descripcion de la Actividad
A68: 3. Cierre | G68: Tiempo Aproximado | H68: =B70 -> 15
G69: Tiene que estar en un rango de 10 a 15 minutos
A70: Tiempo Aproximado | B70: 15
A71: Asignacion de Actividades
A72: Tarea 5 (7 dias)
A74: Resuelve alguna duda, asigna las actividades que deben realizar, dudas de proyectos, etc

Sheet S.11
B2: Diseño de la Sesión de Laboratorio
B4: Curso | C4: ='Diseño'!C4 -> 768 - Algoritmos
B5: Semana | C5: 11
B6: Tiempo | C6: =H10+H21+H44+H68 -> 100
B7: Ponderación | C7: =B49+B60 -> 2
B8: Validación de Tiempo | C8: =IF(H44<=0, "❌ ERROR: La Actividad 1 debe tener un tiempo mayor a 0.", IF(H21>60, "❌ ERROR: El 'Área de Conocimiento' no puede exceder los 60 min.", IF((H10+H21+H44+H68)<100, "❌ ERROR: El tiempo total debe ser de al menos 100 min.", "✅ VALIDACIÓN CORRECTA"))) -> ✅ VALIDACIÓN CORRECTA
A10: 1. Área Actitudinal (Saber Ser) | G10: Tiempo Aproximado | H10: =B13 -> 5
G11: Tiene que estar en un rango de 3 a 5 minutos
A12: Nombre del Valor | B12: Comunicación técnica
A13: Tiempo Aproximado | B13: 5
A14: Descripcion
A15: Capacidad de expresar ideas, procesos y soluciones de forma clara, precisa y comprensible para distintos receptores.
A17: Como se relaciona con los conocimientos de la sesion y se aplicaria
A18: El pseudocódigo es un lenguaje intermediario; escribirlo bien implica comunicar la lógica de forma que otro pueda entenderla. Se tendria un problema y se intercambiaria la solucion entre compañeros para evalúar si la lógica es comprensible sin explicación verbal.
A21: 2. Área Conocimiento (Saber) | G21: Tiempo Aproximado | H21: =SUM(D39:H42) -> 60
G22: No puede exceder los 60 minutos
A23: Competencia a desarrollar | B23: Implementa algoritmos con manejo de arreglos unidimensionales y multidimensionales utilizando herramientas de pseudocódigo y diagramas de flujo para representar y administrar colecciones de datos de forma estructurada
A24: Competencia a desarrollar | B24: Evalúa la calidad y corrección de algoritmos propios y de pares aplicando criterios de claridad, eficiencia estructural y conformidad con las características de un buen algoritmo para mejorar la solución antes de su implementación en un lenguaje de programación formal
A26: 2.1 Contenido
A27: No. | B27: Unidad | D27: Tema | F27: Sub Tema
A28: 1 | B28: =IFERROR(__xludf.DUMMYFUNCTION("FILTER('Diseño'!D:D,'Diseño'!H:H=$C$5)"),"Unidad 6 – Administración y representación de Algoritmos") -> Unidad 6 – Administración y representación de Algoritmos | D28: =IFERROR(__xludf.DUMMYFUNCTION("FILTER('Diseño'!E:E,'Diseño'!H:H=$C$5)"),"Pseudocódigo") -> Pseudocódigo | F28: =IFERROR(__xludf.DUMMYFUNCTION("FILTER('Diseño'!F:F,'Diseño'!H:H=$C$5)"),"Características, estructura y componentes") -> Características, estructura y componentes
A29: 2 | B29: =IFERROR(__xludf.DUMMYFUNCTION("""COMPUTED_VALUE"""),"Unidad 6 – Administración y representación de Algoritmos") -> Unidad 6 – Administración y representación de Algoritmos | D29: =IFERROR(__xludf.DUMMYFUNCTION("""COMPUTED_VALUE"""),"Pseudocódigo") -> Pseudocódigo | F29: =IFERROR(__xludf.DUMMYFUNCTION("""COMPUTED_VALUE"""),"Ventajas y desventajas") -> Ventajas y desventajas
A30: 3 | B30: =IFERROR(__xludf.DUMMYFUNCTION("""COMPUTED_VALUE"""),"Unidad 6 – Administración y representación de Algoritmos") -> Unidad 6 – Administración y representación de Algoritmos | D30: =IFERROR(__xludf.DUMMYFUNCTION("""COMPUTED_VALUE"""),"Pseudocódigo") -> Pseudocódigo | F30: =IFERROR(__xludf.DUMMYFUNCTION("""COMPUTED_VALUE"""),"Software de pseudocódigo") -> Software de pseudocódigo
A31: 4
A32: 5
A33: 6
A34: 7
A36: 2.2 Recursos Educativos
A38: Tipo de Recurso a utilizar | B38: Tipo | C38: Valor maximo recomendado en Minutos | D38: Tiempo Aproximado ( unicamente el valor de minutos ) | I38: Validacion
A39: Presentacion | B39: Obligatorio | C39: 30 | D39: 25 | I39: =IF(D39<=C39,"Correcto", "Corregir") -> Correcto
A40: Video | B40: Obligatorio | C40: 6 | D40: 5 | I40: =IF(D40<=C40,"Correcto", "Corregir") -> Correcto
A41: Lectura | B41: Optativo | C41: 10 | D41: 5 | I41: =IF(D41<=C41,"Correcto", "Corregir") -> Correcto
A42: Ejercicio Demostrativo | B42: Obligatorio | C42: 30 | D42: 25 | I42: =IF(D42<=C42,"Correcto", "Corregir") -> Correcto
A44: 3. Área de Habilidades (Saber Hacer) | G44: Tiempo Aproximado | H44: =B50 -> 20
G45: Tiene que estar en un rango de 30 a 50 minutos
A46: Actividad 1 (Obligatoria)
A47: Competencia que predomina en la actividad | B47: Evalúa la calidad y corrección de algoritmos propios y de pares aplicando criterios de claridad, eficiencia estructural y conformidad con las características de un buen algoritmo para mejorar la solución antes de su implementación en un lenguaje de programación formal
A48: Tipo de Actividad | B48: Cuestionario
A49: Ponderación | B49: 2
A50: Tiempo Aproximado | B50: 20
A51: Coloca el tiempo que usar en la actividad, un tiempo sugerido 30 minutos
A52: Descripcion de la Actividad
A57: Actividad 2 (Optativa puedes hacerla si lo consideras apropiado)
A58: Competencia que predomina en la actividad
A59: Tipo de Actividad
A60: Ponderación
A61: Tiempo Aproximado
A62: Coloca el tiempo que usar en la actividad, un tiempo sugerido 20 minutos
A63: Descripcion de la Actividad
A68: 3. Cierre | G68: Tiempo Aproximado | H68: =B70 -> 15
G69: Tiene que estar en un rango de 10 a 15 minutos
A70: Tiempo Aproximado | B70: 15
A71: Asignacion de Actividades
A72: Corto 4 (mismo dia)
A74: Resuelve alguna duda, asigna las actividades que deben realizar, dudas de proyectos, etc

Sheet Proyectos
B2: Proyectos
B4: Curso | C4: ='Diseño'!C4 -> 768 - Algoritmos
B5: Tiempo | C5: =H9+H26+H43 -> 70
B6: Ponderación | C6: =F9+F26+F43 -> 60
B7: La sumatoria de los puntos de los proyectos debe superar el 60% del total de la nota, no puede ser un 100%
A9: 1. Primer Proyecto | E9: Ponderación | F9: 25 | G9: Horas para realizarlo | H9: 30
A10: Obligatorio
A11: Competencia a desarrollar | B11: Identifica los componentes físicos y lógicos de un sistema computacional utilizando el modelo de Von Neumann y la clasificación de software por categorías para distinguir la función de cada elemento dentro de la arquitectura de procesamiento
A12: Competencia a desarrollar | B12: Implementa algoritmos con manejo de arreglos unidimensionales y multidimensionales utilizando herramientas de pseudocódigo y diagramas de flujo para representar y administrar colecciones de datos de forma estructurada
A13: Competencia a desarrollar | B13: Diseña algoritmos que resuelven problemas determinísticos, condicionales y cíclicos empleando estructuras de control secuenciales, condicionales y repetitivas en pseudocódigo para producir soluciones correctas, legibles y verificables en un entorno de desarrollo introductorio
A14: Titulo | B14: PokeSystem - Simulador de Combate y Gestión de Arreglos
A15: Qué tecnologías, lenguajes de programación, plataformas, hardware o software se utilizaran
A16: PSeInt (Pseudocódigo), arreglos (vectores/matrices), lógica de subprocesos y renderizado de texto masivo
A19: Descripción de lo que se realizara
A20: Desarrollo de un sistema de combate por turnos que gestiona bases de datos de personajes mediante arreglos. El reto técnico principal consiste en procesar y visualizar ASCII ART a escala (100x50), aplicando modularización para separar la lógica de daño, la selección de equipos y la transferencia de datos entre los estados de juego.
A26: 2. Segundo Proyecto | E26: Ponderación | F26: 35 | G26: Horas para realizarlo | H26: 40
A27: Obligatorio
A28: Competencia a desarrollar | B28: Descompone problemas computacionales en subproblemas definidos mediante técnicas de descomposición, reconocimiento de patrones y abstracción para estructurar soluciones algorítmicas a partir de instancias y contextos concretos
A29: Competencia a desarrollar | B29: Diseña algoritmos que resuelven problemas determinísticos, condicionales y cíclicos empleando estructuras de control secuenciales, condicionales y repetitivas en pseudocódigo para producir soluciones correctas, legibles y verificables en un entorno de desarrollo introductorio
A30: Competencia a desarrollar | B30: Evalúa la calidad y corrección de algoritmos propios y de pares aplicando criterios de claridad, eficiencia estructural y conformidad con las características de un buen algoritmo para mejorar la solución antes de su implementación en un lenguaje de programación formal
A31: Titulo | B31: Conversor de Sistemas Numéricos Móvil
A32: Qué tecnologías, lenguajes de programación, plataformas, hardware o software se utilizaran
A33: MIT App Inventor (Programación por bloques), lógica de eventos y algoritmos de conversión matemática
A36: Descripción de lo que se realizara
A37: Creación de una aplicación para Android capaz de convertir valores entre bases decimal, binaria, octal y hexadecimal. Los estudiantes implementarán algoritmos de divisiones sucesivas y notación posicional, gestionando una interfaz gráfica de usuario con validación de errores, filtros de entrada y notificación de resultados en tiempo real sobre un dispositivo móvil.
A43: 3. Tercer Proyecto | E43: Ponderación | G43: Horas para realizarlo
A44: Optativa
A45: Competencia a desarrollar
A46: Competencia a desarrollar
A47: Competencia a desarrollar
A48: Titulo
A49: Qué tecnologías, lenguajes de programación, plataformas, hardware o software se utilizaran
A53: Descripción de lo que se realizara

Sheet Practicas
B2: Practicas
B4: Curso | C4: ='Diseño'!C4 -> 768 - Algoritmos
B5: Tiempo | C5: =H9+H26+H43+H60+H77+H94+H111 -> 25
B6: Ponderación | C6: =F9+F26+F43+F60+F77+F94+F111 -> 20
B7: La sumatoria de los puntos de los practicas debe no debe super el 20%
A9: 1. Primera Practica | E9: Ponderación | F9: 5 | G9: Horas para realizarlo | H9: 10
A10: Obligatoria
A11: Competencia a desarrollar | B11: Analiza los fundamentos del hardware, software y arquitectura computacional mediante el ciclo fetch-decode-execute, sistemas de numeración y codificación de información para establecer la base conceptual del procesamiento y flujo de datos en sistemas computacionales
A12: Competencia a desarrollar | B12: Identifica los componentes físicos y lógicos de un sistema computacional utilizando el modelo de Von Neumann y la clasificación de software por categorías para distinguir la función de cada elemento dentro de la arquitectura de procesamiento
A13: Competencia a desarrollar | B13: Convierte valores numéricos entre sistemas de numeración decimal, binario, octal y hexadecimal aplicando los métodos de conversión posicional y los estándares de codificación ASCII, UNICODE e ISO-8859 para representar datos primitivos, imágenes, audio y video en formato digital
A14: Titulo | B14: La Odisea del Dato (Arquitectura y Flujo)
A15: Qué tecnologías, lenguajes de programación, plataformas, hardware o software se utilizaran
A16: RAPTOR (Diagramación por simbolos y codificación por sentencias), Arquitectura de Von Neumann (VNA), conceptos de ALU, Registros y Ciclo Fetch-Decode-Execute
A19: Descripción de lo que se realizara
A20: Los estudiantes diseñarán 6 diagramas que representen el movimiento físico y lógico de los datos. Deberán resolver retos como conversiones binarias de sensores, validación de acceso a memoria mediante estructuras IF y simulación de ciclos de procesamiento, conectando la teoría del hardware con la lógica de control básica.
A26: 2. Segunda Practica | E26: Ponderación | F26: 15 | G26: Horas para realizarlo | H26: 15
A27: Optativa
A28: Competencia a desarrollar | B28: Analiza los fundamentos del hardware, software y arquitectura computacional mediante el ciclo fetch-decode-execute, sistemas de numeración y codificación de información para establecer la base conceptual del procesamiento y flujo de datos en sistemas computacionales
A29: Competencia a desarrollar | B29: Identifica los componentes físicos y lógicos de un sistema computacional utilizando el modelo de Von Neumann y la clasificación de software por categorías para distinguir la función de cada elemento dentro de la arquitectura de procesamiento
A30: Competencia a desarrollar | B30: Descompone problemas computacionales en subproblemas definidos mediante técnicas de descomposición, reconocimiento de patrones y abstracción para estructurar soluciones algorítmicas a partir de instancias y contextos concretos
A31: Titulo | B31: Lógica de Juegos y Control de Estados
A32: Qué tecnologías, lenguajes de programación, plataformas, hardware o software se utilizaran
A33: RAPTOR (Programación visual), funciones de aleatoriedad (Random), manejo de contadores y acumuladores.
A36: Descripción de lo que se realizara
A37: Implementación de juegos clásicos (Totito, Ahorcado, Adivina el número y Batalla Naval) para dominar estructuras repetitivas y condicionales anidados. El enfoque principal es la gestión de estados (cambio de turnos, validación de victorias y control de intentos), asegurando que el programa sea robusto ante errores de entrada del usuario mediante un flujo lógico coherente.
A43: 3. Tercera Practica | E43: Ponderación | G43: Horas para realizarlo
A44: Optativa
A45: Competencia a desarrollar
A46: Competencia a desarrollar
A47: Competencia a desarrollar
A48: Titulo
A49: Qué tecnologías, lenguajes de programación, plataformas, hardware o software se utilizaran
A53: Descripción de lo que se realizara
A60: 4. Cuarta Practica | E60: Ponderación | G60: Horas para realizarlo
A61: Optativa
A62: Competencia a desarrollar
A63: Competencia a desarrollar
A64: Competencia a desarrollar
A65: Titulo
A66: Qué tecnologías, lenguajes de programación, plataformas, hardware o software se utilizaran
A70: Descripción de lo que se realizara
A77: 5. Quinta Practica | E77: Ponderación | G77: Horas para realizarlo
A78: Optativa
A79: Competencia a desarrollar
A80: Competencia a desarrollar
A81: Competencia a desarrollar
A82: Titulo
A83: Qué tecnologías, lenguajes de programación, plataformas, hardware o software se utilizaran
A87: Descripción de lo que se realizara
A94: 6. Sexta Practica | E94: Ponderación | G94: Horas para realizarlo
A95: Optativa
A96: Competencia a desarrollar
A97: Competencia a desarrollar
A98: Competencia a desarrollar
A99: Titulo
A100: Qué tecnologías, lenguajes de programación, plataformas, hardware o software se utilizaran
A104: Descripción de lo que se realizara
A111: 7. Septima Practica | E111: Ponderación | G111: Horas para realizarlo
A112: Optativa
A113: Competencia a desarrollar
A114: Competencia a desarrollar
A115: Competencia a desarrollar
A116: Titulo
A117: Qué tecnologías, lenguajes de programación, plataformas, hardware o software se utilizaran
A121: Descripción de lo que se realizara

Sheet Tareas
B2: Tareas
B4: Curso | C4: ='Diseño'!C4 -> 768 - Algoritmos
B5: Tiempo | C5: =H9+H26+H43+H60+H77+H94+H111+H128 -> 24
B6: Ponderación | C6: =F9+F26+F43+F60+F77+F94+F111+F128 -> 10
B7: La sumatoria de los puntos de los practicas debe no debe super el 10% de la nota
A9: Tarea de fortalecimiento académico | E9: Ponderación | F9: 0 | G9: Horas para realizarlo | H9: 2
A10: Obligatoria se debe dejar en la sesion de diagnistico
A11: Competencia a desarrollar | B11: Analiza los fundamentos del hardware, software y arquitectura computacional mediante el ciclo fetch-decode-execute, sistemas de numeración y codificación de información para establecer la base conceptual del procesamiento y flujo de datos en sistemas computacionales
A12: Competencia a desarrollar
A13: Competencia a desarrollar
A14: Titulo | B14: Algoritmos Cotidianos: Introducción al Pensamiento Lógico y Computacional
A15: Qué tecnologías, lenguajes de programación, plataformas, hardware o software se utilizaran
A16: Herramientas de diseño (Canva, Genially o Lucidchart), Herramientas de Pseudocodigo (Raptor, PSeint)
A19: Que conocimientos base y competencias esenciales se deben reforzar que permitan al estudiante afrontar con mayor solidez los contenidos del curso
A20: Se introduce el concepto de resolver problemas paso a paso y trabajar solo con lo necesario. El estudiante desarrolla la competencia de traducir procesos humanos a secuencias lógicas, comprendiendo la importancia de las condiciones (Sí/No) y la estructura de entrada-proceso-salida antes de codificar
A26: 1. Primera Tarea | E26: Ponderación | F26: 2 | G26: Horas para realizarlo | H26: 3
A27: Obligatoria
A28: Competencia a desarrollar | B28: Analiza los fundamentos del hardware, software y arquitectura computacional mediante el ciclo fetch-decode-execute, sistemas de numeración y codificación de información para establecer la base conceptual del procesamiento y flujo de datos en sistemas computacionales
A29: Competencia a desarrollar | B29: Identifica los componentes físicos y lógicos de un sistema computacional utilizando el modelo de Von Neumann y la clasificación de software por categorías para distinguir la función de cada elemento dentro de la arquitectura de procesamiento
A30: Competencia a desarrollar
A31: Titulo | B31: Arquitectura, Hardware y los Fundamentos del Procesamiento Computacional
A32: Qué tecnologías, lenguajes de programación, plataformas, hardware o software se utilizaran
A33: Canva, Raptor
A36: Descripción de lo que se realizara
A37: El estudiante elaborará una infografía que explique visualmente los conceptos fundamentales de la computadora, cubriendo: definición y evolución de la computadora, arquitectura Von Neumann, y el hardware de procesamiento (ciclo fetch-decode-execute, Unidad de Control y ALU). Además, deberá instalar RAPTOR y tomar una captura de pantalla del software.
A43: 2. Segunda Tarea | E43: Ponderación | F43: 2 | G43: Horas para realizarlo | H43: 4
A44: Obligatoria
A45: Competencia a desarrollar | B45: Identifica los componentes físicos y lógicos de un sistema computacional utilizando el modelo de Von Neumann y la clasificación de software por categorías para distinguir la función de cada elemento dentro de la arquitectura de procesamiento
A46: Competencia a desarrollar
A47: Competencia a desarrollar
A48: Titulo | B48: Árbitro de Decisiones
A49: Qué tecnologías, lenguajes de programación, plataformas, hardware o software se utilizaran
A50: RAPTOR (Uso de operadores lógicos AND, OR, NOT)
A53: Descripción de lo que se realizara
A54: Se implementara un simulador de compra de objetos en un ecommerce para reforzar las condiciones compuestas. Competencia: Evaluar múltiples estados a la vez (ej. "El sistema procesó la compra de los zapatos, pero NO incluyó el costo de envío porque el cupón de descuento estaba activo")
A60: 3. Tercera Tarea | E60: Ponderación | F60: 2 | G60: Horas para realizarlo | H60: 6
A61: Optativa
A62: Competencia a desarrollar | B62: Diseña algoritmos que resuelven problemas determinísticos, condicionales y cíclicos empleando estructuras de control secuenciales, condicionales y repetitivas en pseudocódigo para producir soluciones correctas, legibles y verificables en un entorno de desarrollo introductorio
A63: Competencia a desarrollar
A64: Competencia a desarrollar
A65: Titulo | B65: Gestor de Inventarios
A66: Qué tecnologías, lenguajes de programación, plataformas, hardware o software se utilizaran
A67: PSeInt (Arreglos unidimensionales/Vectores)
A70: Descripción de lo que se realizara
A71: Implementar una agenda telefónica que contenga Nombre y Número permitiendo manipular Índices y Arreglos. Competencia: Relacionar datos en diferentes vectores (ej. Nombres[1] con Telefonos[1])
A77: 4. Cuarta Tarea | E77: Ponderación | F77: 2 | G77: Horas para realizarlo | H77: 6
A78: Optativa
A79: Competencia a desarrollar | B79: Implementa algoritmos con manejo de arreglos unidimensionales y multidimensionales utilizando herramientas de pseudocódigo y diagramas de flujo para representar y administrar colecciones de datos de forma estructurada
A80: Competencia a desarrollar
A81: Competencia a desarrollar
A82: Titulo | B82: Dibujante de Matrices
A83: Qué tecnologías, lenguajes de programación, plataformas, hardware o software se utilizaran
A84: PSeInt (Ciclos anidados Para / For)
A87: Descripción de lo que se realizara
A88: Un coleccionista solicita generar en ASCII art los cinco últimos goleadores del mundial 2026 para completar su álbum digital sin imágenes. Control de coordenadas en pantalla utilizando matrices. Competencia: Recorrer estructuras de datos (arreglos de dos dimensiones) para imprimir información organizada
A94: 5. Quinta Tarea | E94: Ponderación | F94: 2 | G94: Horas para realizarlo | H94: 3
A95: Optativa
A96: Competencia a desarrollar | B96: Diseña algoritmos que resuelven problemas determinísticos, condicionales y cíclicos empleando estructuras de control secuenciales, condicionales y repetitivas en pseudocódigo para producir soluciones correctas, legibles y verificables en un entorno de desarrollo introductorio
A97: Competencia a desarrollar | B97: Implementa algoritmos con manejo de arreglos unidimensionales y multidimensionales utilizando herramientas de pseudocódigo y diagramas de flujo para representar y administrar colecciones de datos de forma estructurada
A98: Competencia a desarrollar | B98: Evalúa la calidad y corrección de algoritmos propios y de pares aplicando criterios de claridad, eficiencia estructural y conformidad con las características de un buen algoritmo para mejorar la solución antes de su implementación en un lenguaje de programación formal
A99: Titulo | B99: Sistema de cálculo de promedios utilizando arreglos bidimensionales y estructuras de control
A100: Qué tecnologías, lenguajes de programación, plataformas, hardware o software se utilizaran
A101: PSeInt, RAPTOR
A104: Descripción de lo que se realizara
A105: Se desarrollará un algoritmo que almacene las notas de 5 estudiantes en 3 evaluaciones utilizando un arreglo bidimensional, calcule el promedio de cada estudiante y determine si aprueba o reprueba, representando la solución en pseudocódigo y diagrama de flujo.
A111: 6. Sexta Tarea | E111: Ponderación | G111: Horas para realizarlo
A112: Optativa
A113: Competencia a desarrollar
A114: Competencia a desarrollar
A115: Competencia a desarrollar
A116: Titulo
A117: Qué tecnologías, lenguajes de programación, plataformas, hardware o software se utilizaran
A121: Descripción de lo que se realizara
A128: 7. Septima Tarea | E128: Ponderación | G128: Horas para realizarlo
A129: Optativa
A130: Competencia a desarrollar
A131: Competencia a desarrollar
A132: Competencia a desarrollar
A133: Titulo
A134: Qué tecnologías, lenguajes de programación, plataformas, hardware o software se utilizaran
A138: Descripción de lo que se realizara

Sheet Metadata
A1: Codigo-Nombre | B1: Competencias | C1: Competencias relacionadas al perfil del egresado (Especifica) | D1: Competencias relacionadas al perfil del egresado (General)
A2: 17 - Área Social Humanística 1 | B2: =Competencias!C13 -> Analiza los fundamentos del hardware, software y arquitectura computacional mediante el ciclo fetch-decode-execute, sistemas de numeración y codificación de información para establecer la base conceptual del procesamiento y flujo de datos en sistemas computacionales | C2: Aplica los conocimientos de su disciplina en la elaboración, fundamentación y defensa de argumentos para prevenir y resolver problemas complejos en su campo profesional, identificando y aplicando innovaciones. | D2: Aplica principios básicos de ingeniería, ciencias de computación y sistemas de información y comunicación, en la formulación y resolución adecuada de problemas complejos.
A3: 101 - Área Matemática Básica 1 | B3: =Competencias!C15 -> Identifica los componentes físicos y lógicos de un sistema computacional utilizando el modelo de Von Neumann y la clasificación de software por categorías para distinguir la función de cada elemento dentro de la arquitectura de procesamiento | C3: Identifica oportunidades y riesgos para la innovación y adaptación de conocimientos y tecnologías para resolver problemas. | D3: Aplica estándares de calidad, eficiencia y seguridad en la implementación adecuada de soluciones de software, hardware y TIC en general.
A4: 5 - Técnicas de Estudio e Investigación | B4: =Competencias!C17 -> Convierte valores numéricos entre sistemas de numeración decimal, binario, octal y hexadecimal aplicando los métodos de conversión posicional y los estándares de codificación ASCII, UNICODE e ISO-8859 para representar datos primitivos, imágenes, audio y video en formato digital | C4: Demuestra pensamiento crítico, actitud investigativa y rigor analítico en el planteamiento y la resolución de problemas complejos. | D4: Aplica conocimientos tecnológicos con ética profesional y respetando y cuidando los recursos naturales, humanos y financieros.
A5: 39 - Deportes 1 | B5: =Competencias!C19 -> Descompone problemas computacionales en subproblemas definidos mediante técnicas de descomposición, reconocimiento de patrones y abstracción para estructurar soluciones algorítmicas a partir de instancias y contextos concretos | C5: Toma decisiones profesionales con base en fundamentos teóricos, datos e información pertinente, válida y confiable. | D5: Maneja e Interpreta adecuadamente datos masivos, sean estos estructurados o no estructurados, facilitando su visualización e interpretación de forma eficaz en apoyo a la toma de decisiones.
A6: 6 - Idioma Tecnico 1 | B6: =Competencias!C21 -> Diseña algoritmos que resuelven problemas determinísticos, condicionales y cíclicos empleando estructuras de control secuenciales, condicionales y repetitivas en pseudocódigo para producir soluciones correctas, legibles y verificables en un entorno de desarrollo introductorio | C6: Demuestra destreza y habilidad en la selección, uso y adaptación de herramientas metodológicas, tecnológicas, equipos especializados y en la lectura e interpretación de datos, pertinentes al contexto de su ejercicio profesional. | D6: Domina diversos recursos de comunicación con el objetivo de presentar adecuadamente sus propuestas a variados tipos de audiencias, en idioma español, inglés e idealmente en un tercer idioma acorde a las necesidades globales.
A7: 19 - Área Social Humanística 2 | B7: =Competencias!C23 -> Implementa algoritmos con manejo de arreglos unidimensionales y multidimensionales utilizando herramientas de pseudocódigo y diagramas de flujo para representar y administrar colecciones de datos de forma estructurada | C7: Identifica sus necesidades de actualización, capacitación y formación, durante su proceso formativo y en el ejercicio profesional, y busca los medios para cubrirlas por medios formales e informales, nacionales e internacionales, presenciales y en línea. | D7: Construye soluciones integrales trabajando en forma colaborativa y propositiva en equipos interdisciplinarios, en forma presencial o utilizando plataformas virtuales.
A8: 103 - Área Matemática Básica 2 | B8: =Competencias!C25 -> Evalúa la calidad y corrección de algoritmos propios y de pares aplicando criterios de claridad, eficiencia estructural y conformidad con las características de un buen algoritmo para mejorar la solución antes de su implementación en un lenguaje de programación formal | C8: Comunica a diversos públicos, información de su campo profesional, en varios lenguajes y formatos de manera asertiva, clara, rigurosa y precisa, con el uso apropiado de recursos tecnológicos. | D8: Actualiza permanente sus conocimientos relacionados con TIC en general, apoyándose en las estrategias de aprendizaje apropiadas.
A9: 960 - Matemática Para Computación 1 | C9: Se comunica correctamente en su lengua oficial y utiliza una lengua extranjera con el dominio requerido para el ejercicio de su profesión.
A10: 147 - Física Básica | C10: Lidera y colabora proactivamente en equipos de trabajo y en comunidades profesionales para el logro de objetivos y mejoramiento de la calidad de vida.
A11: 40 - Deportes 2
A12: 8 - Idioma Técnico 2
A13: 795 - Logica de Sitemas
A14: 962 - Matemática Para Computación 2
A15: 770 - Introducción a ala programación y computación 1
A16: 107 - Área Matemática Intermedia 1
A17: 150 - Fisica 1
A18: 1 - Ética Profesional
A19: 9 - Idioma Técnico 3
A20: 796 - Lenguajes Formales y de Programación
A21: 771 - Introducción a la Programación y Computación 2
A22: 112 - Área Matemática Intermedia 2
... A81: 0089 - Comunicación Asertiva
