Workbook

Sheet Resumen
B2: Resumen de Ponderacion y Horas
B4: Curso | C4: 780 - Software Avanzado
B5: Semestre que aplica | C5: Segundo Semestre 2026
B6: Total de Puntos del Laboratorio | C6: 30
A8: * Esta sección se auto completa al momento en que se llene a la información de la planificación
A9: ** Tomar como base la distribución realizada por el coordinador del area del curso en el documento de criterios y expectativas
A10: Tipo de Actividad | B10: Ponderacion | C10: Horas utilizadas | D10: Aspectos clave que debe abordar | G10: Valor Maximo Recomendado
A11: Actividades durante el peridodo de laboratorio | B11: 10 | C11: 0.3 | D11: Conocimientos adquiridos en clase | G11: 10
A12: Proyectos | B12: 60 | C12: 240 | D12: Desarrollo, CI/CD, DevOps, DevSecOps y Monitorización | G12: 60
A13: Prácticas | B13: 20 | C13: 56 | D13: Desarrollo, CI/CD, DevOps, DevSecOps y Monitorización | G13: 20
A14: Tareas | B14: 10 | C14: 0 | D14: Investigaciones sobre temas concretos de desarrollo y el ciclo de vida DevOps | G14: 10
A15: Total | B15: =SUM(B11:B14) -> 100 | C15: =SUM(C11:C14) -> 296.3 | D15: Validacion | E15: =IFERROR(__xludf.DUMMYFUNCTION("LET( nombres,A11:A14, p,B11:B14, m,G11:G14, t,SUM(p), exceden, IFERROR(TEXTJOIN(""; "", TRUE, FILTER(nombres&"" (""&p&"">""&m&"")"", p>m)), """"), negs, IF(COUNTIF(p,""<0"")>0, ""Hay valores negativos"", """"), totalmsg, IF(t<>100, ""Total ≠"&" 100 (actual ""&t&"")"", """"), excesomsg, IF(exceden<>"""", ""Exceden: ""&exceden, """"), msg, TEXTJOIN("" | "", TRUE, totalmsg, negs, excesomsg), IF(msg="""", ""✅ Distribución válida"", ""❌ Revisar: ""&msg) )"),"✅ Distribución válida") -> ✅ Distribución válida

Sheet Competencias
B1: Competencias que se formaran en el Segundo Semestre 2026
B2: Curso | C2: 780 - Software Avanzado
B3: Semestre que aplica | C3: Segundo Semestre 2026
B5: Competencias relacionadas al perfil del egresado (Especifica) | I5: Competencias relacionadas al perfil del egresado (General)
B6: 1 | C6: Demuestra pensamiento crítico, actitud investigativa y rigor analítico en el planteamiento y la resolución de problemas complejos. | I6: 1 | J6: Construye soluciones integrales trabajando en forma colaborativa y propositiva en equipos interdisciplinarios, en forma presencial o utilizando plataformas virtuales.
B7: 2 | C7: Identifica sus necesidades de actualización, capacitación y formación, durante su proceso formativo y en el ejercicio profesional, y busca los medios para cubrirlas por medios formales e informales, nacionales e internacionales, presenciales y en línea. | I7: 2 | J7: Aplica estándares de calidad, eficiencia y seguridad en la implementación adecuada de soluciones de software, hardware y TIC en general.
B8: 3 | C8: Lidera y colabora proactivamente en equipos de trabajo y en comunidades profesionales para el logro de objetivos y mejoramiento de la calidad de vida. | I8: 3 | J8: Aplica principios básicos de ingeniería, ciencias de computación y sistemas de información y comunicación, en la formulación y resolución adecuada de problemas complejos.
B11: No | C11: Tipo | D11: Verbo en Presente | E11: Objeto de la acción | G11: [Palabras conectoreas] Herramientas o metodología | H11: [Palabras conectoreas] Condiciones específicas | J11: Nivel
B12: 1 | C12: Especifica | D12: Analiza .. | E12: arquitecturas de software basadas en microservicios | G12: utilizando diagramas y patrones arquitectónicos | H12: en estudios de caso reales | J12: Analizar
C13: ="El estudiante " & D12 & " " & E12 & " " &G12& " " &H12& " " -> El estudiante Analiza .. arquitecturas de software basadas en microservicios utilizando diagramas y patrones arquitectónicos en estudios de caso reales
B14: 2 | C14: Especifica | D14: Crea .. | E14: soluciones de software basadas en microservicios poniendo en practica los principios SOLID | G14: usando herramientas de desarrollo y contenedores | H14: en entornos prácticos de laboratorio | J14: Crear
C15: ="El estudiante " & D14 & " " & E14 & " " &G14& " " &H14& " " -> El estudiante Crea .. soluciones de software basadas en microservicios poniendo en practica los principios SOLID usando herramientas de desarrollo y contenedores en entornos prácticos de laboratorio
B16: 3 | C16: Especifica | D16: Implementa ... | E16: servicios y APIs en arquitectura de microservicios | G16: mediante Docker y frameworks de desarrollo | H16: en proyectos prácticos | J16: Aplicar
C17: ="El estudiante " & D16 & " " & E16 & " " &G16& " " &H16& " " -> El estudiante Implementa ... servicios y APIs en arquitectura de microservicios mediante Docker y frameworks de desarrollo en proyectos prácticos
B18: 4 | C18: Especifica | D18: Explica | E18: el funcionamiento de pipelines CI/CD | G18: utilizando herramientas de integración continua | H18: mediante ejemplos prácticos | J18: Comprender
C19: ="El estudiante " & D18 & " " & E18 & " " &G18& " " &H18& " " -> El estudiante Explica el funcionamiento de pipelines CI/CD utilizando herramientas de integración continua mediante ejemplos prácticos
B20: 5 | C20: Especifica | D20: Evalúa | E20: estrategias de despliegue y monitoreo | G20: utilizando Kubernetes y herramientas de observabilidad | H20: en distintos escenarios de implementación | J20: Evaluar
C21: ="El estudiante " & D20 & " " & E20 & " " &G20& " " &H20& " " -> El estudiante Evalúa estrategias de despliegue y monitoreo utilizando Kubernetes y herramientas de observabilidad en distintos escenarios de implementación
B22: 6 | C22: Especifica | D22: Aplica | E22: prácticas de DevOps y DevSecOps | G22: mediante pipelines automatizados | H22: en proyectos de software | J22: Aplicar
C23: ="El estudiante " & D22 & " " & E22 & " " &G22& " " &H22& " " -> El estudiante Aplica prácticas de DevOps y DevSecOps mediante pipelines automatizados en proyectos de software
B24: 7 | C24: Especifica | D24: Identifica | E24: conceptos clave de arquitecturas modernas y herramientas DevOps | G24: a partir de documentación técnica | H24: en actividades teóricas | J24: Recordar
C25: ="El estudiante " & D24 & " " & E24 & " " &G24& " " &H24& " " -> El estudiante Identifica conceptos clave de arquitecturas modernas y herramientas DevOps a partir de documentación técnica en actividades teóricas | L25: Manual de competencias: https://drive.google.com/file/d/1n5es0M20vXxa7i4eLN7pbgTXc2C1dmCQ/view?usp=sharing
L26: Video de como hacer competencias: https://youtu.be/C8Q9dKo4t-w?si=yErgF_ihe1tsaHM0
B28: Si las competencias son las misma que el semetre anterior compartenos tu opinion de porque no se cambiaron

Sheet Diseño
B2: Diseño de Contenido Curricular
B4: Curso | C4: 780 - Software Avanzado
B5: semestre que aplica | C5: Segundo Semestre 2026
B8: No. | C8: Competencia | D8: Nombre de la Unidad | E8: Tema | F8: Subtema | G8: Mes | H8: Semana
B9: 1 | C9: El estudiante Crea .. soluciones de software basadas en microservicios poniendo en practica los principios SOLID usando herramientas de desarrollo y contenedores en entornos prácticos de laboratorio | D9: Buenas practicas en el desarrollo de Software | E9: Clean CODE | F9: SOLID | G9: Julio | H9: 2
B10: 2 | C10: El estudiante Crea .. soluciones de software basadas en microservicios poniendo en practica los principios SOLID usando herramientas de desarrollo y contenedores en entornos prácticos de laboratorio | D10: Buenas practicas en el desarrollo de Software | E10: Clean CODE | F10: KISS | G10: Julio | H10: 2
B11: 3 | C11: El estudiante Crea .. soluciones de software basadas en microservicios poniendo en practica los principios SOLID usando herramientas de desarrollo y contenedores en entornos prácticos de laboratorio | D11: Buenas practicas en el desarrollo de Software | E11: Clean CODE | F11: STUPID | G11: Julio | H11: 2
B12: 4 | C12: El estudiante Crea .. soluciones de software basadas en microservicios poniendo en practica los principios SOLID usando herramientas de desarrollo y contenedores en entornos prácticos de laboratorio | D12: Buenas practicas en el desarrollo de Software | E12: Deuda Tecnica | F12: Refactorizacion basada en SOLID | G12: Julio | H12: 2
B13: 5 | C13: El estudiante Crea .. soluciones de software basadas en microservicios poniendo en practica los principios SOLID usando herramientas de desarrollo y contenedores en entornos prácticos de laboratorio | D13: Backend y Frontend | E13: Frameworks: Frontend | F13: Angular, Vuejs, Vite | G13: Julio | H13: 3
B14: 6 | C14: El estudiante Crea .. soluciones de software basadas en microservicios poniendo en practica los principios SOLID usando herramientas de desarrollo y contenedores en entornos prácticos de laboratorio | D14: Backend y Frontend | E14: Frameworks: Backend | F14: NestJs, Springboot, FastAPI | G14: Julio | H14: 3
B15: 7 | C15: El estudiante Crea .. soluciones de software basadas en microservicios poniendo en practica los principios SOLID usando herramientas de desarrollo y contenedores en entornos prácticos de laboratorio | D15: Backend y Frontend | E15: Bases de datos | F15: Redis, Postsql,mysql | G15: Julio | H15: 3
B16: 8 | C16: El estudiante Crea .. soluciones de software basadas en microservicios poniendo en practica los principios SOLID usando herramientas de desarrollo y contenedores en entornos prácticos de laboratorio | D16: Backend y Frontend | E16: Metodos de autenticacion | F16: JWT,OAuth | G16: Julio | H16: 3
B17: 9 | C17: El estudiante Analiza .. arquitecturas de software basadas en microservicios utilizando diagramas y patrones arquitectónicos en estudios de caso reales | D17: Arquitectura de Software | E17: Clean Architecture | F17: Monolito | G17: Julio | H17: 4
B18: 10 | C18: El estudiante Analiza .. arquitecturas de software basadas en microservicios utilizando diagramas y patrones arquitectónicos en estudios de caso reales | D18: Arquitectura de Software | E18: Clean Architecture | F18: Microservicios | G18: Julio | H18: 4
B19: 11 | C19: El estudiante Analiza .. arquitecturas de software basadas en microservicios utilizando diagramas y patrones arquitectónicos en estudios de caso reales | D19: Arquitectura de Software | E19: Clean Architecture | F19: SOA | G19: Julio | H19: 4
B20: 12 | C20: El estudiante Analiza .. arquitecturas de software basadas en microservicios utilizando diagramas y patrones arquitectónicos en estudios de caso reales | D20: Arquitectura de Software | E20: Clean Architecture | F20: DDD | G20: Julio | H20: 4
... B85: 77 | C85: El estudiante Evalúa estrategias de despliegue y monitoreo utilizando Kubernetes y herramientas de observabilidad en distintos escenarios de implementación | D85: Orquestacion | E85: Servicios Cloud | F85: GCP,AWS, Digital Ocean, Azure | G85: Agosto | H85: 7
B86: 78
B87: 79
B88: 80
B89: 81
B90: 82
B91: 83
B92: 84
B93: 85
B94: 86
B95: 87
B96: 88
B97: 89
... B108: 100

Sheet Semana Diagnostico
B2: Diseño de Contenido Curricular
B4: Curso | C4: ='Diseño'!C4 -> 780 - Software Avanzado
B5: Semana | C5: 1
B6: Tiempo | C6: =B15+B22+B29+B41+B47+C48 -> 115
K8: Estos puntos son recomendaciones de los puntos a tratar durante tu presentacion, si no usaras estos eres libre de agregar mas filas para indicar que haras. En los recuadros de la derecha colocar breve resumen de lo que planeas decir. No debes ser muy especifico seran pequeñas anotaciones que te ayudaran a recordar lo que planeaste
A9: 1. Bienvenida y Presentación | G9: Tiempo Aproximado | H9: 15
G10: No puedes excederte mas de 15 minutos
A11: Nombre y Formacion Academica | B11: Nombre del auxiliar y formación academica
A12: Experiencia docente y profecional | B12: Información sobre la experiencia durante la carrera, formación profecional extra (Ej; Certificaciones) y experiencia laboral en el área (Si es que hay)
A13: Rol del auxiliar dentro del curso (funciones, actividades y apoyo a los estudiantes). | B13: Información de contacto, metodo de resolución de dudas
A14: Expectativas sobre la dinámica del curso | B14: Información breve de lo que trata el curso
A15: Tiempo que emplearas | B15: 15
A18: 2. Evaluación de Conocimientos Previos | G18: Tiempo Aproximado | H18: 45
G19: No puedes excederte mas de 45 minutos | K19: En los recuadors de la derecha deberas colocar las preguntas que planeas realizar con sus respectivas respuestas. En el segundo recuadro deberas colocar un breve resumne de lo que tines planificado para la parte practica del curso previo al que estas impartiendo.
A20: Redactaras de 15 a 20 preguntas con sus respectivas respuestas , por lo que debes escoge los temas que evaluaras | B20: ¿Qué metodología exige escribir las pruebas antes que el código fuente? Respuesta: TDD ¿Qué tipo de prueba evalúa una sola función o método de forma aislada? Respuesta: Unitaria ¿Qué nombre recibe un objeto simulado que imita a una base de datos en una prueba? Respuesta: Mock ¿Qué métrica indica el porcentaje de código que es ejecutado por las pruebas? Respuesta: Cobertura (o Coverage) ¿Qué proceso busca mejorar la estructura del código sin cambiar su comportamiento externo? Respuesta: Refactorización Menciona una herramienta estándar para realizar análisis estático de código. Respuesta: SonarQube ¿Qué pruebas verifican que dos o más módulos funcionen correctamente juntos? Respuesta: Integración ¿Qué siglas definen la práctica de unir código frecuentemente en un repositorio central? Respuesta: CI (o Integración Continua) ¿Qué pruebas evalúan el flujo completo del sistema como si lo usara el cliente final? Respuesta: E2E (o End-to-End) Menciona una herramienta popular de Apache para automatizar pruebas de rendimiento. Respuesta: JMeter ¿Qué proceso confirma que el software construido resuelve el problema real del cliente? Respuesta: Validación ¿Qué patrón de arquitectura divide el sistema en Modelo, Vista y Controlador? Respuesta: MVC ¿Cuál de los principios SOLID exige que una clase tenga una sola razón para cambiar? Respuesta: SRP (o Responsabilidad Única) ¿Qué herramienta estándar se utiliza para el control de versiones de código fuente? Respuesta: Git ¿Qué framework de pruebas unitarias es el más utilizado en Java? Respuesta: JUnit
A21: Redactaras una parte practica para realizar la evaluacion de conocimientos previos | B21: Caso Práctico Corto Contexto: Una cafetería universitaria necesita un mini-sistema web para gestionar pedidos en línea y evitar filas. Instrucciones para el estudiante: Con base en los requerimientos básicos de una cafetería: Identifica al menos dos actores principales del sistema. Lista tres casos de uso fundamentales. Indica qué patrón arquitectónico utilizarías para estructurar el proyecto (ej. MVC, Cliente-Servidor) y justifica tu elección en una sola oración.
A22: Tiempo que emplearas | B22: 45
A25: 3. Presentación de los Estudiantes | G25: Tiempo Aproximado | H25: 10
G26: No puedes excederte mas de 30 minutos
A27: Seleccion al Azar de 5 Estudiantes | B27: Se buscará un estudiante en la sala de meet para que se presente | K27: En el primer recuadro colocaras la metodollogia que adoptaras para la eleccion de los estudiantes. En el segundo recuadro colocaras la redaccion de las preguntas que comprendan los siguientes puntos respecto al estudiante: Nombre. Intereses y expectativas sobre el curso. Experiencia previa relacionada con el curso (si aplica). Un dato curioso sobre sí mismo. Consideras que la prueba de conociminetos previos esta acorde al conocimiento que se te brindo en su momento Que tan comodo se sintio con la prueba anterior.
A28: Indica las preguntas que responderan los estudiantes afortunados | B28: 1, ¿Cual es su nombre? 2. ¿Cules son las expectativas del curso? 3. ¿Trabaja? 4. ¿Es primera vez llevando el curso?
A29: Tiempo que emplearas | B29: 10
A32: 4. Senso de Horarios de Calificación | G32: Tiempo Aproximado | H32: 5
A33: Deberas estar recordando que deben contestar el formulario asi mismo dejar el link fijado en la llamada | G33: Esta actividad quedara abierta hasta el fin de la clase. pero emplearas 5 min especificos para la actividad
A34: Link de google forms donde este el cuestionario | B34: https://docs.google.com/forms/d/e/1FAIpQLSdOywQHJ5K66bdM7YP6RPQGLGuSX0RyhTj40jQ2_Smw8N7Mhg/viewform?usp=publish-editor | K34: Esta actividad te ayudara a realizar un senso de posibles horarios de calificacion y que tus estudiantes esten enterados y puedan preveer los dias de calificacion y asi mismo el horario. Deberas colocar en los reacuadros de la derecha link de Google form libre para correos intitucionales, esto para garantizar una sola respuesta por estudiante. TAmbien deberas colocar los posibles horarios y dias que tentativamente tendrias disponibles. para colocarlos en el google form.
A35: Dias y posibles Horarios de calificacion | B35: Jueves, Viernes 7:00 - 19:00, Sábado 10:00-14:00 (Solo para estudiantes que trabajan)
A36: Tiempo que emplearas | B36: 5
A39: 5. Mostrar Programa del Curso | G39: Tiempo Aproximado | H39: 30
G40: No puedes excederte mas de 30 minutos
A41: Tiempo que emplearas | B41: 30
A44: 6. Evaluación de Conocimientos del Curso Actual | G44: Tiempo Aproximado | H44: 15
G45: No puedes excederte mas de 15 minutos
A46: Redactaras 20 preguntas con sus respectivas respuestas | B46: ¿Qué tecnología es el estándar actual de la industria para la creación y ejecución de contenedores? ¿Qué tipo de arquitectura basa la comunicación entre sus componentes en la producción, detección y consumo de sucesos o mensajes? Respuesta: Eventos (u Orientada a Eventos) ¿Cuál es el gestor de paquetes por defecto utilizado en entornos de desarrollo con Node.js? Respuesta: npm ¿Qué siglas identifican a la plataforma principal de servicios en la nube pública de Google? Respuesta: GCP (Google Cloud Platform) Menciona un servidor de automatización de código abierto muy popular y veterano en la industria, escrito en Java y utilizado para montar pipelines de CI/CD. Respuesta: Jenkins ¿Qué lenguaje de programación y superconjunto de JavaScript, que añade tipado estático, es la base del framework Angular? Respuesta: TypeScript Respuesta: Docker ¿Qué plataforma de código abierto se utiliza para la orquestación de contenedores? Respuesta: Kubernetes ¿Qué siglas definen la práctica de gestionar y aprovisionar servidores mediante archivos de configuración en lugar de procesos manuales? Respuesta: IaC (Infraestructura como Código) Menciona una herramienta popular de HashiCorp utilizada para aprovisionar infraestructura en la nube. Respuesta: Terraform ¿Qué práctica automatiza la construcción y pruebas del código cada vez que un desarrollador hace un commit? Respuesta: CI (Integración Continua) ¿Qué plataforma integrada directamente en repositorios de código permite crear pipelines de automatización? Respuesta: GitHub Actions (o GitLab CI) ¿Qué estilo de arquitectura divide una aplicación en servicios pequeños, independientes y débilmente acoplados? Respuesta: Microservicios ¿Qué framework de comunicación de alto rendimiento desarrollado por Google se utiliza frecuentemente entre microservicios? Respuesta: gRPC ¿Qué concepto define la capacidad de entender el estado interno de un sistema analizando sus logs, métricas y trazas? Respuesta: Observabilidad Menciona una herramienta estándar para la recolección de métricas y monitoreo en entornos Cloud Native. Respuesta: Prometheus ¿Qué plataforma se utiliza comúnmente junto a Prometheus para la visualización de datos en dashboards? Respuesta: Grafana ¿Qué siglas representan el conjunto de cinco principios de diseño que buscan hacer el software más mantenible y escalable? Respuesta: SOLID ¿Qué proveedor de nube pública incluye servicios como EC2, S3 y RDS? Respuesta: AWS ¿Qué herramienta de automatización de TI utiliza "Playbooks" escritos en YAML para configurar servidores? Respuesta: Ansible ¿Qué tipo de base de datos orientada a documentos es MongoDB? Respuesta: NoSQL (o No Relacional)
A47: Tiempo que emplearas | B47: 15

Sheet S.2
B2: Diseño de la Sesión de Laboratorio
B4: Curso | C4: ='Diseño'!C4 -> 780 - Software Avanzado
B5: Semana | C5: 2
B6: Tiempo | C6: =H10+H21+H44+H68 -> 115
B7: Ponderación | C7: =B49+B60 -> 0
B8: Validación de Tiempo | C8: =IF(H44<=0, "❌ ERROR: La Actividad 1 debe tener un tiempo mayor a 0.", IF(H21>60, "❌ ERROR: El 'Área de Conocimiento' no puede exceder los 60 min.", IF((H10+H21+H44)<100, "❌ ERROR: El tiempo total debe ser de al menos 100 min.", "✅ VALIDACIÓN CORRECTA"))) -> ✅ VALIDACIÓN CORRECTA
A10: 1. Área Actitudinal (Saber Ser) | G10: Tiempo Aproximado | H10: 5
G11: Tiene que estar en un rango de 3 a 5 minutos
A12: Nombre del Valor | B12: Legibilidad y mantenibilidad del software
A13: Tiempo Aproximado | B13: 5
A14: Descripcion
A15: Es una forma de programar en la que el código se escribe para que sea claro, entendible y fácil de mantener, no solo para que funcione.
A17: Como se relaciona con los conocimientos de la sesion y se aplicaria
A18: Se relaciona directamente porque el Clean Code no es algo aislado, sino la forma en que aplicas los conocimientos técnicos
A21: 2. Área Conocimiento (Saber) | G21: Tiempo Aproximado | H21: 60
G22: No puede exceder los 60 minutos
A23: Competencia a desarrollar | B23: El estudiante Crea .. soluciones de software basadas en microservicios poniendo en practica los principios SOLID usando herramientas de desarrollo y contenedores en entornos prácticos de laboratorio
A24: Competencia a desarrollar | B24: El estudiante Crea .. soluciones de software basadas en microservicios poniendo en practica los principios SOLID usando herramientas de desarrollo y contenedores en entornos prácticos de laboratorio
A26: 2.1 Contenido
A27: No. | B27: Unidad | D27: Tema | F27: Sub Tema
A28: 1 | B28: =IFERROR(__xludf.DUMMYFUNCTION("FILTER('Diseño'!D:D,'Diseño'!H:H=$C$5)"),"Buenas practicas en el desarrollo de Software") -> Buenas practicas en el desarrollo de Software | D28: =IFERROR(__xludf.DUMMYFUNCTION("FILTER('Diseño'!E:E,'Diseño'!H:H=$C$5)"),"Clean CODE") -> Clean CODE | F28: =IFERROR(__xludf.DUMMYFUNCTION("FILTER('Diseño'!F:F,'Diseño'!H:H=$C$5)"),"SOLID") -> SOLID
A29: 2 | B29: =IFERROR(__xludf.DUMMYFUNCTION("""COMPUTED_VALUE"""),"Buenas practicas en el desarrollo de Software") -> Buenas practicas en el desarrollo de Software | D29: =IFERROR(__xludf.DUMMYFUNCTION("""COMPUTED_VALUE"""),"Clean CODE") -> Clean CODE | F29: =IFERROR(__xludf.DUMMYFUNCTION("""COMPUTED_VALUE"""),"KISS") -> KISS
A30: 3 | B30: =IFERROR(__xludf.DUMMYFUNCTION("""COMPUTED_VALUE"""),"Buenas practicas en el desarrollo de Software") -> Buenas practicas en el desarrollo de Software | D30: =IFERROR(__xludf.DUMMYFUNCTION("""COMPUTED_VALUE"""),"Clean CODE") -> Clean CODE | F30: =IFERROR(__xludf.DUMMYFUNCTION("""COMPUTED_VALUE"""),"STUPID") -> STUPID
A31: 4 | B31: =IFERROR(__xludf.DUMMYFUNCTION("""COMPUTED_VALUE"""),"Buenas practicas en el desarrollo de Software") -> Buenas practicas en el desarrollo de Software | D31: =IFERROR(__xludf.DUMMYFUNCTION("""COMPUTED_VALUE"""),"Deuda Tecnica") -> Deuda Tecnica | F31: =IFERROR(__xludf.DUMMYFUNCTION("""COMPUTED_VALUE"""),"Refactorizacion basada en SOLID") -> Refactorizacion basada en SOLID
A32: 5 | B32: =IFERROR(__xludf.DUMMYFUNCTION("""COMPUTED_VALUE"""),"Buenas practicas en el desarrollo de Software") -> Buenas practicas en el desarrollo de Software | D32: =IFERROR(__xludf.DUMMYFUNCTION("""COMPUTED_VALUE"""),"SOLID") -> SOLID | F32: =IFERROR(__xludf.DUMMYFUNCTION("""COMPUTED_VALUE"""),"Single Responsibility Principle") -> Single Responsibility Principle
A33: 6 | B33: =IFERROR(__xludf.DUMMYFUNCTION("""COMPUTED_VALUE"""),"Buenas practicas en el desarrollo de Software") -> Buenas practicas en el desarrollo de Software | D33: =IFERROR(__xludf.DUMMYFUNCTION("""COMPUTED_VALUE"""),"SOLID") -> SOLID | F33: =IFERROR(__xludf.DUMMYFUNCTION("""COMPUTED_VALUE"""),"Open-Closed Principle") -> Open-Closed Principle
A34: 7 | B34: =IFERROR(__xludf.DUMMYFUNCTION("""COMPUTED_VALUE"""),"Buenas practicas en el desarrollo de Software") -> Buenas practicas en el desarrollo de Software | D34: =IFERROR(__xludf.DUMMYFUNCTION("""COMPUTED_VALUE"""),"SOLID") -> SOLID | F34: =IFERROR(__xludf.DUMMYFUNCTION("""COMPUTED_VALUE"""),"Liskov Substitution Principle") -> Liskov Substitution Principle
A36: 2.2 Recursos Educativos
A38: Tipo de Recurso a utilizar | B38: Tipo | C38: Valor maximo recomendado en Minutos | D38: Tiempo Aproximado ( unicamente el valor de minutos ) | I38: Validacion
A39: Presentacion | B39: Obligatorio | C39: 30 | D39: 30 | I39: =IF(D39<=C39,"Correcto", "Corregir") -> Correcto
A40: Video | B40: Obligatorio | C40: 6 | D40: 0 | I40: =IF(D40<=C40,"Correcto", "Corregir") -> Correcto
A41: Lectura | B41: Optativo | C41: 10 | D41: 10 | I41: =IF(D41<=C41,"Correcto", "Corregir") -> Correcto
A42: Ejercicio Demostrativo | B42: Obligatorio | C42: 30 | D42: 30 | I42: =IF(D42<=C42,"Correcto", "Corregir") -> Correcto
A44: 3. Área de Habilidades (Saber Hacer) | G44: Tiempo Aproximado | H44: 40
G45: Tiene que estar en un rango de 30 a 50 minutos
A46: Actividad 1 (Obligatoria)
A47: Competencia que predomina en la actividad | B47: El estudiante Crea .. soluciones de software basadas en microservicios poniendo en practica los principios SOLID usando herramientas de desarrollo y contenedores en entornos prácticos de laboratorio
A48: Tipo de Actividad | B48: Ejercicio practico
A49: Ponderación | B49: 0
A50: Tiempo Aproximado | B50: 10
A51: Coloca el tiempo que usar en la actividad, un tiempo sugerido 30 minutos
A52: Descripcion de la Actividad
A57: Actividad 2 (Optativa puedes hacerla si lo consideras apropiado)
A58: Competencia que predomina en la actividad
A59: Tipo de Actividad
A60: Ponderación
A61: Tiempo Aproximado
A62: Coloca el tiempo que usar en la actividad, un tiempo sugerido 20 minutos
A63: Descripcion de la Actividad
A68: 3. Cierre | G68: Tiempo Aproximado | H68: 10
G69: Tiene que estar en un rango de 10 a 15 minutos
A70: Tiempo Aproximado | B70: 10
A71: Asignacion de Actividades
A72: Lectura de la practica numero 1 y resolucion de dudas de la misma.
A74: Resuelve alguna duda, asigna las actividades que deben realizar, dudas de proyectos, etc

Sheet S.3
B2: Diseño de la Sesión de Laboratorio
B4: Curso | C4: ='Diseño'!C4 -> 780 - Software Avanzado
B5: Semana | C5: 3
B6: Tiempo | C6: =H10+H21+H44+H68 -> 115
B7: Ponderación | C7: =B49+B60 -> 0
B8: Validación de Tiempo | C8: =IF(H44<=0, "❌ ERROR: La Actividad 1 debe tener un tiempo mayor a 0.", IF(H21>60, "❌ ERROR: El 'Área de Conocimiento' no puede exceder los 60 min.", IF((H10+H21+H44)<100, "❌ ERROR: El tiempo total debe ser de al menos 100 min.", "✅ VALIDACIÓN CORRECTA"))) -> ✅ VALIDACIÓN CORRECTA
A10: 1. Área Actitudinal (Saber Ser) | G10: Tiempo Aproximado | H10: 5
G11: Tiene que estar en un rango de 3 a 5 minutos
A12: Nombre del Valor | B12: Planificación y estrategias de entrega de software
A13: Tiempo Aproximado | B13: 5
A14: Descripcion
A15: Planifica de forma técnica , profunda y estratégica el desarrollo de software utilizando herramientas especializadas para el diseño y modelado de arquitecturas escalables y robustas.
A17: Como se relaciona con los conocimientos de la sesion y se aplicaria
A18: Aplica metodologías ágiles como Scrum o Kanban, combinadas con prácticas DevOps y diseño orientado a servicios (SOA o microservicios), para asegurar una implementación óptima, continua y de alta calidad de los sistemas informáticos.
A21: 2. Área Conocimiento (Saber) | G21: Tiempo Aproximado | H21: 60
G22: No puede exceder los 60 minutos
A23: Competencia a desarrollar | B23: El estudiante Implementa ... servicios y APIs en arquitectura de microservicios mediante Docker y frameworks de desarrollo en proyectos prácticos
A24: Competencia a desarrollar | B24: El estudiante Crea .. soluciones de software basadas en microservicios poniendo en practica los principios SOLID usando herramientas de desarrollo y contenedores en entornos prácticos de laboratorio
A26: 2.1 Contenido
A27: No. | B27: Unidad | D27: Tema | F27: Sub Tema
A28: 1 | B28: =IFERROR(__xludf.DUMMYFUNCTION("FILTER('Diseño'!D:D,'Diseño'!H:H=$C$5)"),"Backend y Frontend") -> Backend y Frontend | D28: =IFERROR(__xludf.DUMMYFUNCTION("FILTER('Diseño'!E:E,'Diseño'!H:H=$C$5)"),"Frameworks: Frontend") -> Frameworks: Frontend | F28: =IFERROR(__xludf.DUMMYFUNCTION("FILTER('Diseño'!F:F,'Diseño'!H:H=$C$5)"),"Angular, Vuejs, Vite") -> Angular, Vuejs, Vite
A29: 2 | B29: =IFERROR(__xludf.DUMMYFUNCTION("""COMPUTED_VALUE"""),"Backend y Frontend") -> Backend y Frontend | D29: =IFERROR(__xludf.DUMMYFUNCTION("""COMPUTED_VALUE"""),"Frameworks: Backend") -> Frameworks: Backend | F29: =IFERROR(__xludf.DUMMYFUNCTION("""COMPUTED_VALUE"""),"NestJs, Springboot, FastAPI") -> NestJs, Springboot, FastAPI
A30: 3 | B30: =IFERROR(__xludf.DUMMYFUNCTION("""COMPUTED_VALUE"""),"Backend y Frontend") -> Backend y Frontend | D30: =IFERROR(__xludf.DUMMYFUNCTION("""COMPUTED_VALUE"""),"Bases de datos") -> Bases de datos | F30: =IFERROR(__xludf.DUMMYFUNCTION("""COMPUTED_VALUE"""),"Redis, Postsql,mysql") -> Redis, Postsql,mysql
A31: 4 | B31: =IFERROR(__xludf.DUMMYFUNCTION("""COMPUTED_VALUE"""),"Backend y Frontend") -> Backend y Frontend | D31: =IFERROR(__xludf.DUMMYFUNCTION("""COMPUTED_VALUE"""),"Metodos de autenticacion") -> Metodos de autenticacion | F31: =IFERROR(__xludf.DUMMYFUNCTION("""COMPUTED_VALUE"""),"JWT,OAuth") -> JWT,OAuth
A32: 5 | B32: =IFERROR(__xludf.DUMMYFUNCTION("""COMPUTED_VALUE"""),"Backend y Frontend") -> Backend y Frontend | D32: =IFERROR(__xludf.DUMMYFUNCTION("""COMPUTED_VALUE"""),"Patrones de diseño") -> Patrones de diseño | F32: =IFERROR(__xludf.DUMMYFUNCTION("""COMPUTED_VALUE"""),"Ventajas") -> Ventajas
A33: 6 | B33: =IFERROR(__xludf.DUMMYFUNCTION("""COMPUTED_VALUE"""),"Backend y Frontend") -> Backend y Frontend | D33: =IFERROR(__xludf.DUMMYFUNCTION("""COMPUTED_VALUE"""),"Patrones de diseño") -> Patrones de diseño | F33: =IFERROR(__xludf.DUMMYFUNCTION("""COMPUTED_VALUE"""),"Clasificacion") -> Clasificacion
A34: 7 | B34: =IFERROR(__xludf.DUMMYFUNCTION("""COMPUTED_VALUE"""),"Backend y Frontend") -> Backend y Frontend | D34: =IFERROR(__xludf.DUMMYFUNCTION("""COMPUTED_VALUE"""),"Patrones de diseño") -> Patrones de diseño | F34: =IFERROR(__xludf.DUMMYFUNCTION("""COMPUTED_VALUE"""),"Difrencias entre Arquitectura y Patrones de diseño") -> Difrencias entre Arquitectura y Patrones de diseño
A36: 2.2 Recursos Educativos
A38: Tipo de Recurso a utilizar | B38: Tipo | C38: Valor maximo recomendado en Minutos | D38: Tiempo Aproximado ( unicamente el valor de minutos ) | I38: Validacion
A39: Presentacion | B39: Obligatorio | C39: 30 | I39: =IF(D39<=C39,"Correcto", "Corregir") -> Correcto
A40: Video | B40: Obligatorio | C40: 6 | I40: =IF(D40<=C40,"Correcto", "Corregir") -> Correcto
A41: Lectura | B41: Optativo | C41: 10 | I41: =IF(D41<=C41,"Correcto", "Corregir") -> Correcto
A42: Ejercicio Demostrativo | B42: Obligatorio | C42: 30 | I42: =IF(D42<=C42,"Correcto", "Corregir") -> Correcto
A44: 3. Área de Habilidades (Saber Hacer) | G44: Tiempo Aproximado | H44: 40
G45: Tiene que estar en un rango de 30 a 50 minutos
A46: Actividad 1 (Obligatoria)
A47: Competencia que predomina en la actividad | B47: El estudiante Crea .. soluciones de software basadas en microservicios poniendo en practica los principios SOLID usando herramientas de desarrollo y contenedores en entornos prácticos de laboratorio
A48: Tipo de Actividad | B48: actividades
A49: Ponderación | B49: 0
A50: Tiempo Aproximado
A51: Coloca el tiempo que usar en la actividad, un tiempo sugerido 30 minutos
A52: Descripcion de la Actividad
A57: Actividad 2 (Optativa puedes hacerla si lo consideras apropiado)
A58: Competencia que predomina en la actividad
A59: Tipo de Actividad
A60: Ponderación
A61: Tiempo Aproximado
A62: Coloca el tiempo que usar en la actividad, un tiempo sugerido 20 minutos
A63: Descripcion de la Actividad
A68: 3. Cierre | G68: Tiempo Aproximado | H68: 10
G69: Tiene que estar en un rango de 10 a 15 minutos
A70: Tiempo Aproximado | B70: 10
A71: Asignacion de Actividades
A72: Asignacion de la practica 2 y su respectiva lectura. Resolucion de dudas de la misma y publicación de horarios de calificacion de la practica 1
A74: Resuelve alguna duda, asigna las actividades que deben realizar, dudas de proyectos, etc

Sheet S.4
B2: Diseño de la Sesión de Laboratorio
B4: Curso | C4: ='Diseño'!C4 -> 780 - Software Avanzado
B5: Semana | C5: 4
B6: Tiempo | C6: =H10+H21+H44+H68 -> 115
B7: Ponderación | C7: =B49+B60 -> 0
B8: Validación de Tiempo | C8: =IF(H44<=0, "❌ ERROR: La Actividad 1 debe tener un tiempo mayor a 0.", IF(H21>60, "❌ ERROR: El 'Área de Conocimiento' no puede exceder los 60 min.", IF((H10+H21+H44)<100, "❌ ERROR: El tiempo total debe ser de al menos 100 min.", "✅ VALIDACIÓN CORRECTA"))) -> ✅ VALIDACIÓN CORRECTA
A10: 1. Área Actitudinal (Saber Ser) | G10: Tiempo Aproximado | H10: 5
G11: Tiene que estar en un rango de 3 a 5 minutos
A12: Nombre del Valor | B12: Mantenibilidad y escalabilidad del software
A13: Tiempo Aproximado | B13: 5
A14: Descripcion
A15: Todas esas arquitecturas (Monolito, Microservicios, SOA, DDD, etc.) buscan lo mismo: Que el sistema sea fácil de entender Que se pueda modificar sin romper todo Que pueda crecer de forma ordenada Que el código esté bien estructurado y desacoplado
A17: Como se relaciona con los conocimientos de la sesion y se aplicaria
A18: todas esas arquitecturas son la forma de llevar a nivel estructural el mismo valor que promueve el Clean Code: claridad, mantenibilidad y orden.
A21: 2. Área Conocimiento (Saber) | G21: Tiempo Aproximado | H21: 50
G22: No puede exceder los 60 minutos
A23: Competencia a desarrollar | B23: El estudiante Analiza .. arquitecturas de software basadas en microservicios utilizando diagramas y patrones arquitectónicos en estudios de caso reales
A24: Competencia a desarrollar | B24: El estudiante Analiza .. arquitecturas de software basadas en microservicios utilizando diagramas y patrones arquitectónicos en estudios de caso reales
A26: 2.1 Contenido
A27: No. | B27: Unidad | D27: Tema | F27: Sub Tema
A28: 1 | B28: =IFERROR(__xludf.DUMMYFUNCTION("FILTER('Diseño'!D:D,'Diseño'!H:H=$C$5)"),"Arquitectura de Software") -> Arquitectura de Software | D28: =IFERROR(__xludf.DUMMYFUNCTION("FILTER('Diseño'!E:E,'Diseño'!H:H=$C$5)"),"Clean Architecture") -> Clean Architecture | F28: =IFERROR(__xludf.DUMMYFUNCTION("FILTER('Diseño'!F:F,'Diseño'!H:H=$C$5)"),"Monolito") -> Monolito
A29: 2 | B29: =IFERROR(__xludf.DUMMYFUNCTION("""COMPUTED_VALUE"""),"Arquitectura de Software") -> Arquitectura de Software | D29: =IFERROR(__xludf.DUMMYFUNCTION("""COMPUTED_VALUE"""),"Clean Architecture") -> Clean Architecture | F29: =IFERROR(__xludf.DUMMYFUNCTION("""COMPUTED_VALUE"""),"Microservicios") -> Microservicios
A30: 3 | B30: =IFERROR(__xludf.DUMMYFUNCTION("""COMPUTED_VALUE"""),"Arquitectura de Software") -> Arquitectura de Software | D30: =IFERROR(__xludf.DUMMYFUNCTION("""COMPUTED_VALUE"""),"Clean Architecture") -> Clean Architecture | F30: =IFERROR(__xludf.DUMMYFUNCTION("""COMPUTED_VALUE"""),"SOA") -> SOA
A31: 4 | B31: =IFERROR(__xludf.DUMMYFUNCTION("""COMPUTED_VALUE"""),"Arquitectura de Software") -> Arquitectura de Software | D31: =IFERROR(__xludf.DUMMYFUNCTION("""COMPUTED_VALUE"""),"Clean Architecture") -> Clean Architecture | F31: =IFERROR(__xludf.DUMMYFUNCTION("""COMPUTED_VALUE"""),"DDD") -> DDD
A32: 5 | B32: =IFERROR(__xludf.DUMMYFUNCTION("""COMPUTED_VALUE"""),"Arquitectura de Software") -> Arquitectura de Software | D32: =IFERROR(__xludf.DUMMYFUNCTION("""COMPUTED_VALUE"""),"Clean Architecture") -> Clean Architecture | F32: =IFERROR(__xludf.DUMMYFUNCTION("""COMPUTED_VALUE"""),"vertical slice architecture") -> vertical slice architecture
A33: 6 | B33: =IFERROR(__xludf.DUMMYFUNCTION("""COMPUTED_VALUE"""),"Arquitectura de Software") -> Arquitectura de Software | D33: =IFERROR(__xludf.DUMMYFUNCTION("""COMPUTED_VALUE"""),"Clean Architecture") -> Clean Architecture | F33: =IFERROR(__xludf.DUMMYFUNCTION("""COMPUTED_VALUE"""),"screaming architecture") -> screaming architecture
A34: 7 | B34: =IFERROR(__xludf.DUMMYFUNCTION("""COMPUTED_VALUE"""),"Arquitectura de Software") -> Arquitectura de Software | D34: =IFERROR(__xludf.DUMMYFUNCTION("""COMPUTED_VALUE"""),"Clean Architecture") -> Clean Architecture | F34: =IFERROR(__xludf.DUMMYFUNCTION("""COMPUTED_VALUE"""),"MVC") -> MVC
A36: 2.2 Recursos Educativos
A38: Tipo de Recurso a utilizar | B38: Tipo | C38: Valor maximo recomendado en Minutos | D38: Tiempo Aproximado ( unicamente el valor de minutos ) | I38: Validacion
A39: Presentacion | B39: Obligatorio | C39: 30 | D39: 30 | I39: =IF(D39<=C39,"Correcto", "Corregir") -> Correcto
A40: Video | B40: Obligatorio | C40: 6 | D40: 5 | I40: =IF(D40<=C40,"Correcto", "Corregir") -> Correcto
A41: Lectura | B41: Optativo | C41: 10 | D41: 0 | I41: =IF(D41<=C41,"Correcto", "Corregir") -> Correcto
A42: Ejercicio Demostrativo | B42: Obligatorio | C42: 30 | D42: 30 | I42: =IF(D42<=C42,"Correcto", "Corregir") -> Correcto
A44: 3. Área de Habilidades (Saber Hacer) | G44: Tiempo Aproximado | H44: 50
G45: Tiene que estar en un rango de 30 a 50 minutos
A46: Actividad 1 (Obligatoria)
A47: Competencia que predomina en la actividad | B47: El estudiante Analiza .. arquitecturas de software basadas en microservicios utilizando diagramas y patrones arquitectónicos en estudios de caso reales
A48: Tipo de Actividad | B48: Analisis
A49: Ponderación | B49: 0
A50: Tiempo Aproximado | B50: 50
A51: Coloca el tiempo que usar en la actividad, un tiempo sugerido 30 minutos
A52: Descripcion de la Actividad
A53: Se analiza un caso de estudio y se busca la solucion mas viable arquitectonicamente hablando. Esta actividad es clave para que comprendan las diferencias entre las direrentes arquitecturas.
A57: Actividad 2 (Optativa puedes hacerla si lo consideras apropiado)
A58: Competencia que predomina en la actividad
A59: Tipo de Actividad
A60: Ponderación
A61: Tiempo Aproximado
A62: Coloca el tiempo que usar en la actividad, un tiempo sugerido 20 minutos
A63: Descripcion de la Actividad
A68: 3. Cierre | G68: Tiempo Aproximado | H68: 10
G69: Tiene que estar en un rango de 10 a 15 minutos
A70: Tiempo Aproximado | B70: 10
A71: Asignacion de Actividades
A72: Asignacion de la practica 3 y su respectiva lectura. Resolucion de dudas de la misma y publicación de horarios de calificacion de la practica 2
A74: Resuelve alguna duda, asigna las actividades que deben realizar, dudas de proyectos, etc

Sheet S.5
B2: Diseño de la Sesión de Laboratorio
B4: Curso | C4: ='Diseño'!C4 -> 780 - Software Avanzado
B5: Semana | C5: 5
B6: Tiempo | C6: =H10+H21+H44+H68 -> 115
B7: Ponderación | C7: =B49+B60 -> 0
B8: Validación de Tiempo | C8: =IF(H44<=0, "❌ ERROR: La Actividad 1 debe tener un tiempo mayor a 0.", IF(H21>60, "❌ ERROR: El 'Área de Conocimiento' no puede exceder los 60 min.", IF((H10+H21+H44)<100, "❌ ERROR: El tiempo total debe ser de al menos 100 min.", "✅ VALIDACIÓN CORRECTA"))) -> ✅ VALIDACIÓN CORRECTA
A10: 1. Área Actitudinal (Saber Ser) | G10: Tiempo Aproximado | H10: 5
G11: Tiene que estar en un rango de 3 a 5 minutos
A12: Nombre del Valor | B12: Integración y Cohesión
A13: Tiempo Aproximado | B13: 5
A14: Descripcion
A15: Integra componentes, servicios y tecnologías de software mediante el uso de APIs, servicios web y herramientas de integración continua
A17: Como se relaciona con los conocimientos de la sesion y se aplicaria
A18: Asegura la interoperabilidad, cohesión funcional y eficiencia en la entrega de soluciones informáticas.
A21: 2. Área Conocimiento (Saber) | G21: Tiempo Aproximado | H21: 60
G22: No puede exceder los 60 minutos
A23: Competencia a desarrollar | B23: El estudiante Implementa ... servicios y APIs en arquitectura de microservicios mediante Docker y frameworks de desarrollo en proyectos prácticos
A24: Competencia a desarrollar | B24: El estudiante Implementa ... servicios y APIs en arquitectura de microservicios mediante Docker y frameworks de desarrollo en proyectos prácticos
A26: 2.1 Contenido
A27: No. | B27: Unidad | D27: Tema | F27: Sub Tema
A28: 1 | B28: =IFERROR(__xludf.DUMMYFUNCTION("FILTER('Diseño'!D:D,'Diseño'!H:H=$C$5)"),"Arquitectura de Software") -> Arquitectura de Software | D28: =IFERROR(__xludf.DUMMYFUNCTION("FILTER('Diseño'!E:E,'Diseño'!H:H=$C$5)"),"Contenedores") -> Contenedores | F28: =IFERROR(__xludf.DUMMYFUNCTION("FILTER('Diseño'!F:F,'Diseño'!H:H=$C$5)"),"Docker image") -> Docker image
A29: 2 | B29: =IFERROR(__xludf.DUMMYFUNCTION("""COMPUTED_VALUE"""),"Arquitectura de Software") -> Arquitectura de Software | D29: =IFERROR(__xludf.DUMMYFUNCTION("""COMPUTED_VALUE"""),"Contenedores") -> Contenedores | F29: =IFERROR(__xludf.DUMMYFUNCTION("""COMPUTED_VALUE"""),"Dockerfile") -> Dockerfile
A30: 3 | B30: =IFERROR(__xludf.DUMMYFUNCTION("""COMPUTED_VALUE"""),"Arquitectura de Software") -> Arquitectura de Software | D30: =IFERROR(__xludf.DUMMYFUNCTION("""COMPUTED_VALUE"""),"Contenedores") -> Contenedores | F30: =IFERROR(__xludf.DUMMYFUNCTION("""COMPUTED_VALUE"""),"Ciclo de vida de un Contenedor") -> Ciclo de vida de un Contenedor
A31: 4 | B31: =IFERROR(__xludf.DUMMYFUNCTION("""COMPUTED_VALUE"""),"Arquitectura de Software") -> Arquitectura de Software | D31: =IFERROR(__xludf.DUMMYFUNCTION("""COMPUTED_VALUE"""),"Despliegue multiple de contenedores") -> Despliegue multiple de contenedores | F31: =IFERROR(__xludf.DUMMYFUNCTION("""COMPUTED_VALUE"""),"Docker Compose") -> Docker Compose
A32: 5 | B32: =IFERROR(__xludf.DUMMYFUNCTION("""COMPUTED_VALUE"""),"Arquitectura de Software") -> Arquitectura de Software | D32: =IFERROR(__xludf.DUMMYFUNCTION("""COMPUTED_VALUE"""),"Despliegue multiple de contenedores") -> Despliegue multiple de contenedores | F32: =IFERROR(__xludf.DUMMYFUNCTION("""COMPUTED_VALUE"""),"Docker vs Docker compose") -> Docker vs Docker compose
A33: 6 | B33: =IFERROR(__xludf.DUMMYFUNCTION("""COMPUTED_VALUE"""),"Arquitectura de Software") -> Arquitectura de Software | D33: =IFERROR(__xludf.DUMMYFUNCTION("""COMPUTED_VALUE"""),"Contenedores") -> Contenedores | F33: =IFERROR(__xludf.DUMMYFUNCTION("""COMPUTED_VALUE"""),"Podman") -> Podman
A34: 7 | B34: =IFERROR(__xludf.DUMMYFUNCTION("""COMPUTED_VALUE"""),"Arquitectura de Software") -> Arquitectura de Software | D34: =IFERROR(__xludf.DUMMYFUNCTION("""COMPUTED_VALUE"""),"Contenedores") -> Contenedores | F34: =IFERROR(__xludf.DUMMYFUNCTION("""COMPUTED_VALUE"""),"Containerd") -> Containerd
A36: 2.2 Recursos Educativos
A38: Tipo de Recurso a utilizar | B38: Tipo | C38: Valor maximo recomendado en Minutos | D38: Tiempo Aproximado ( unicamente el valor de minutos ) | I38: Validacion
A39: Presentacion | B39: Obligatorio | C39: 30 | I39: =IF(D39<=C39,"Correcto", "Corregir") -> Correcto
A40: Video | B40: Obligatorio | C40: 6 | I40: =IF(D40<=C40,"Correcto", "Corregir") -> Correcto
A41: Lectura | B41: Optativo | C41: 10 | I41: =IF(D41<=C41,"Correcto", "Corregir") -> Correcto
A42: Ejercicio Demostrativo | B42: Obligatorio | C42: 30 | I42: =IF(D42<=C42,"Correcto", "Corregir") -> Correcto
A44: 3. Área de Habilidades (Saber Hacer) | G44: Tiempo Aproximado | H44: 40
G45: Tiene que estar en un rango de 30 a 50 minutos
A46: Actividad 1 (Obligatoria)
A47: Competencia que predomina en la actividad | B47: El estudiante Implementa ... servicios y APIs en arquitectura de microservicios mediante Docker y frameworks de desarrollo en proyectos prácticos
A48: Tipo de Actividad | B48: actividades
A49: Ponderación | B49: 0
A50: Tiempo Aproximado
A51: Coloca el tiempo que usar en la actividad, un tiempo sugerido 30 minutos
A52: Descripcion de la Actividad
A57: Actividad 2 (Optativa puedes hacerla si lo consideras apropiado)
A58: Competencia que predomina en la actividad
A59: Tipo de Actividad
A60: Ponderación
A61: Tiempo Aproximado
A62: Coloca el tiempo que usar en la actividad, un tiempo sugerido 20 minutos
A63: Descripcion de la Actividad
A68: 3. Cierre | G68: Tiempo Aproximado | H68: 10
G69: Tiene que estar en un rango de 10 a 15 minutos
A70: Tiempo Aproximado | B70: 10
A71: Asignacion de Actividades
A72: Asignacion de la practica 4 y su respectiva lectura. Resolucion de dudas de la misma y publicación de horarios de calificacion de la practica 3
A74: Resuelve alguna duda, asigna las actividades que deben realizar, dudas de proyectos, etc

Sheet S.6
B2: Diseño de la Sesión de Laboratorio
B4: Curso | C4: ='Diseño'!C4 -> 780 - Software Avanzado
B5: Semana | C5: 6
B6: Tiempo | C6: =H10+H21+H44+H68 -> 115
B7: Ponderación | C7: =B49+B60 -> 0
B8: Validación de Tiempo | C8: =IF(H44<=0, "❌ ERROR: La Actividad 1 debe tener un tiempo mayor a 0.", IF(H21>60, "❌ ERROR: El 'Área de Conocimiento' no puede exceder los 60 min.", IF((H10+H21+H44)<100, "❌ ERROR: El tiempo total debe ser de al menos 100 min.", "✅ VALIDACIÓN CORRECTA"))) -> ✅ VALIDACIÓN CORRECTA
A10: 1. Área Actitudinal (Saber Ser) | G10: Tiempo Aproximado | H10: 5
G11: Tiene que estar en un rango de 3 a 5 minutos
A12: Nombre del Valor | B12: Confiabilidad y seguridad del sistema
A13: Tiempo Aproximado | B13: 5
A14: Descripcion
A15: Define características como: Fiabilidad Usabilidad Mantenibilidad
A17: Como se relaciona con los conocimientos de la sesion y se aplicaria
A18: Porque todos esos elementos buscan que el software: Funcione correctamente (calidad) Sea seguro (protección de información) Sea estable y disponible (infraestructura y despliegue)
A21: 2. Área Conocimiento (Saber) | G21: Tiempo Aproximado | H21: 60
G22: No puede exceder los 60 minutos
A23: Competencia a desarrollar | B23: El estudiante Aplica prácticas de DevOps y DevSecOps mediante pipelines automatizados en proyectos de software
A24: Competencia a desarrollar | B24: El estudiante Analiza .. arquitecturas de software basadas en microservicios utilizando diagramas y patrones arquitectónicos en estudios de caso reales
A26: 2.1 Contenido
A27: No. | B27: Unidad | D27: Tema | F27: Sub Tema
A28: 1 | B28: =IFERROR(__xludf.DUMMYFUNCTION("FILTER('Diseño'!D:D,'Diseño'!H:H=$C$5)"),"Modelo y Calidad de Software") -> Modelo y Calidad de Software | D28: =IFERROR(__xludf.DUMMYFUNCTION("FILTER('Diseño'!E:E,'Diseño'!H:H=$C$5)"),"ISO/IEC 25010") -> ISO/IEC 25010 | F28: =IFERROR(__xludf.DUMMYFUNCTION("FILTER('Diseño'!F:F,'Diseño'!H:H=$C$5)"),"Calidad de Software") -> Calidad de Software
A29: 2 | B29: =IFERROR(__xludf.DUMMYFUNCTION("""COMPUTED_VALUE"""),"Modelo de Seguridad de la Informacion") -> Modelo de Seguridad de la Informacion | D29: =IFERROR(__xludf.DUMMYFUNCTION("""COMPUTED_VALUE"""),"ISO/IEC 27001 ") -> ISO/IEC 27001 | F29: =IFERROR(__xludf.DUMMYFUNCTION("""COMPUTED_VALUE"""),"Control de accesos organizacionales/Políticas de contraseñas") -> Control de accesos organizacionales/Políticas de contraseñas
A30: 3 | B30: =IFERROR(__xludf.DUMMYFUNCTION("""COMPUTED_VALUE"""),"Orquestacion") -> Orquestacion | D30: =IFERROR(__xludf.DUMMYFUNCTION("""COMPUTED_VALUE"""),"K8s") -> K8s | F30: =IFERROR(__xludf.DUMMYFUNCTION("""COMPUTED_VALUE"""),"Tipos de nodos") -> Tipos de nodos
A31: 4 | B31: =IFERROR(__xludf.DUMMYFUNCTION("""COMPUTED_VALUE"""),"Orquestacion") -> Orquestacion | D31: =IFERROR(__xludf.DUMMYFUNCTION("""COMPUTED_VALUE"""),"K8s") -> K8s | F31: =IFERROR(__xludf.DUMMYFUNCTION("""COMPUTED_VALUE"""),"Deployments") -> Deployments
A32: 5 | B32: =IFERROR(__xludf.DUMMYFUNCTION("""COMPUTED_VALUE"""),"Orquestacion") -> Orquestacion | D32: =IFERROR(__xludf.DUMMYFUNCTION("""COMPUTED_VALUE"""),"K8s") -> K8s | F32: =IFERROR(__xludf.DUMMYFUNCTION("""COMPUTED_VALUE"""),"Services") -> Services
A33: 6 | B33: =IFERROR(__xludf.DUMMYFUNCTION("""COMPUTED_VALUE"""),"Orquestacion") -> Orquestacion | D33: =IFERROR(__xludf.DUMMYFUNCTION("""COMPUTED_VALUE"""),"K8s") -> K8s | F33: =IFERROR(__xludf.DUMMYFUNCTION("""COMPUTED_VALUE"""),"Ingress") -> Ingress
A34: 7 | B34: =IFERROR(__xludf.DUMMYFUNCTION("""COMPUTED_VALUE"""),"Orquestacion") -> Orquestacion | D34: =IFERROR(__xludf.DUMMYFUNCTION("""COMPUTED_VALUE"""),"K8s") -> K8s | F34: =IFERROR(__xludf.DUMMYFUNCTION("""COMPUTED_VALUE"""),"Helm") -> Helm
A36: 2.2 Recursos Educativos
A38: Tipo de Recurso a utilizar | B38: Tipo | C38: Valor maximo recomendado en Minutos | D38: Tiempo Aproximado ( unicamente el valor de minutos ) | I38: Validacion
A39: Presentacion | B39: Obligatorio | C39: 30 | D39: 30 | I39: =IF(D39<=C39,"Correcto", "Corregir") -> Correcto
A40: Video | B40: Obligatorio | C40: 6 | D40: 5 | I40: =IF(D40<=C40,"Correcto", "Corregir") -> Correcto
A41: Lectura | B41: Optativo | C41: 10 | D41: 0 | I41: =IF(D41<=C41,"Correcto", "Corregir") -> Correcto
A42: Ejercicio Demostrativo | B42: Obligatorio | C42: 30 | D42: 30 | I42: =IF(D42<=C42,"Correcto", "Corregir") -> Correcto
A44: 3. Área de Habilidades (Saber Hacer) | G44: Tiempo Aproximado | H44: 40
G45: Tiene que estar en un rango de 30 a 50 minutos
A46: Actividad 1 (Obligatoria)
A47: Competencia que predomina en la actividad | B47: El estudiante Crea .. soluciones de software basadas en microservicios poniendo en practica los principios SOLID usando herramientas de desarrollo y contenedores en entornos prácticos de laboratorio
A48: Tipo de Actividad | B48: Ejercicio practico
A49: Ponderación | B49: 0
A50: Tiempo Aproximado | B50: 30
A51: Coloca el tiempo que usar en la actividad, un tiempo sugerido 30 minutos
A52: Descripcion de la Actividad
A53: Ejercicio practico de despliegue de una arquitectura de microservicios utilizando Helm y K8S
A57: Actividad 2 (Optativa puedes hacerla si lo consideras apropiado)
A58: Competencia que predomina en la actividad
A59: Tipo de Actividad
A60: Ponderación
A61: Tiempo Aproximado
A62: Coloca el tiempo que usar en la actividad, un tiempo sugerido 20 minutos
A63: Descripcion de la Actividad
A68: 3. Cierre | G68: Tiempo Aproximado | H68: 10
G69: Tiene que estar en un rango de 10 a 15 minutos
A70: Tiempo Aproximado | B70: 10
A71: Asignacion de Actividades
A72: Asignacion de practica numero 5 y lectura de la misma. Resolucion de dudas de la practica. Publicacion de horarios de calificación de la practica numero 4
A74: Resuelve alguna duda, asigna las actividades que deben realizar, dudas de proyectos, etc

Sheet S.7
B2: Diseño de la Sesión de Laboratorio
B4: Curso | C4: ='Diseño'!C4 -> 780 - Software Avanzado
B5: Semana | C5: 7
B6: Tiempo | C6: =H10+H21+H44+H68 -> 115
B7: Ponderación | C7: =B49+B60 -> 0
B8: Validación de Tiempo | C8: =IF(H44<=0, "❌ ERROR: La Actividad 1 debe tener un tiempo mayor a 0.", IF(H21>60, "❌ ERROR: El 'Área de Conocimiento' no puede exceder los 60 min.", IF((H10+H21+H44)<100, "❌ ERROR: El tiempo total debe ser de al menos 100 min.", "✅ VALIDACIÓN CORRECTA"))) -> ✅ VALIDACIÓN CORRECTA
A10: 1. Área Actitudinal (Saber Ser) | G10: Tiempo Aproximado | H10: 5
G11: Tiene que estar en un rango de 3 a 5 minutos
A12: Nombre del Valor | B12: Modelos de servicios
A13: Tiempo Aproximado | B13: 5
A14: Descripcion
A15: Diseña arquitecturas de software modulares y escalables, seleccionando tecnologías, patrones de diseño y estilos arquitectónicos adecuados (como microservicios, clienteservidor o arquitectura en capas), utilizando herramientas de modelado como UML, ArchiMate o Draw.io, para asegurar la sostenibilidad, mantenibilidad y evolución del sistema.
A17: Como se relaciona con los conocimientos de la sesion y se aplicaria
A18: Mejora continuamente el rendimiento, la seguridad y la mantenibilidad de sistemas de software existentes, mediante el análisis de métricas, refactorización de código, aplicación de principios SOLID y adopción de herramientas de monitoreo y automatización, asegurando soluciones más eficientes y alineadas con los estándares de calidad del sector.
A21: 2. Área Conocimiento (Saber) | G21: Tiempo Aproximado | H21: 60
G22: No puede exceder los 60 minutos
A23: Competencia a desarrollar | B23: El estudiante Identifica conceptos clave de arquitecturas modernas y herramientas DevOps a partir de documentación técnica en actividades teóricas
A24: Competencia a desarrollar | B24: El estudiante Identifica conceptos clave de arquitecturas modernas y herramientas DevOps a partir de documentación técnica en actividades teóricas
A26: 2.1 Contenido
A27: No. | B27: Unidad | D27: Tema | F27: Sub Tema
A28: 1 | B28: =IFERROR(__xludf.DUMMYFUNCTION("FILTER('Diseño'!D:D,'Diseño'!H:H=$C$5)"),"Orquestacion") -> Orquestacion | D28: =IFERROR(__xludf.DUMMYFUNCTION("FILTER('Diseño'!E:E,'Diseño'!H:H=$C$5)"),"Modelos de servicio de Nube") -> Modelos de servicio de Nube | F28: =IFERROR(__xludf.DUMMYFUNCTION("FILTER('Diseño'!F:F,'Diseño'!H:H=$C$5)"),"SaaS") -> SaaS
A29: 2 | B29: =IFERROR(__xludf.DUMMYFUNCTION("""COMPUTED_VALUE"""),"Orquestacion") -> Orquestacion | D29: =IFERROR(__xludf.DUMMYFUNCTION("""COMPUTED_VALUE"""),"Modelos de servicio de Nube") -> Modelos de servicio de Nube | F29: =IFERROR(__xludf.DUMMYFUNCTION("""COMPUTED_VALUE"""),"PaaS") -> PaaS
A30: 3 | B30: =IFERROR(__xludf.DUMMYFUNCTION("""COMPUTED_VALUE"""),"Orquestacion") -> Orquestacion | D30: =IFERROR(__xludf.DUMMYFUNCTION("""COMPUTED_VALUE"""),"Modelos de servicio de Nube") -> Modelos de servicio de Nube | F30: =IFERROR(__xludf.DUMMYFUNCTION("""COMPUTED_VALUE"""),"IaaS") -> IaaS
A31: 4 | B31: =IFERROR(__xludf.DUMMYFUNCTION("""COMPUTED_VALUE"""),"Orquestacion") -> Orquestacion | D31: =IFERROR(__xludf.DUMMYFUNCTION("""COMPUTED_VALUE"""),"IaaS") -> IaaS | F31: =IFERROR(__xludf.DUMMYFUNCTION("""COMPUTED_VALUE"""),"Casos de uso") -> Casos de uso
A32: 5 | B32: =IFERROR(__xludf.DUMMYFUNCTION("""COMPUTED_VALUE"""),"Orquestacion") -> Orquestacion | D32: =IFERROR(__xludf.DUMMYFUNCTION("""COMPUTED_VALUE"""),"Herramientas para Orquestas Infraestructura") -> Herramientas para Orquestas Infraestructura | F32: =IFERROR(__xludf.DUMMYFUNCTION("""COMPUTED_VALUE"""),"Ansible") -> Ansible
A33: 6 | B33: =IFERROR(__xludf.DUMMYFUNCTION("""COMPUTED_VALUE"""),"Orquestacion") -> Orquestacion | D33: =IFERROR(__xludf.DUMMYFUNCTION("""COMPUTED_VALUE"""),"Herramientas para Orquestas Infraestructura") -> Herramientas para Orquestas Infraestructura | F33: =IFERROR(__xludf.DUMMYFUNCTION("""COMPUTED_VALUE"""),"Terraform") -> Terraform
A34: 7 | B34: =IFERROR(__xludf.DUMMYFUNCTION("""COMPUTED_VALUE"""),"Orquestacion") -> Orquestacion | D34: =IFERROR(__xludf.DUMMYFUNCTION("""COMPUTED_VALUE"""),"Servicios Cloud") -> Servicios Cloud | F34: =IFERROR(__xludf.DUMMYFUNCTION("""COMPUTED_VALUE"""),"GCP,AWS, Digital Ocean, Azure") -> GCP,AWS, Digital Ocean, Azure
A36: 2.2 Recursos Educativos
A38: Tipo de Recurso a utilizar | B38: Tipo | C38: Valor maximo recomendado en Minutos | D38: Tiempo Aproximado ( unicamente el valor de minutos ) | I38: Validacion
A39: Presentacion | B39: Obligatorio | C39: 30 | I39: =IF(D39<=C39,"Correcto", "Corregir") -> Correcto
A40: Video | B40: Obligatorio | C40: 6 | I40: =IF(D40<=C40,"Correcto", "Corregir") -> Correcto
A41: Lectura | B41: Optativo | C41: 10 | I41: =IF(D41<=C41,"Correcto", "Corregir") -> Correcto
A42: Ejercicio Demostrativo | B42: Obligatorio | C42: 30 | I42: =IF(D42<=C42,"Correcto", "Corregir") -> Correcto
A44: 3. Área de Habilidades (Saber Hacer) | G44: Tiempo Aproximado | H44: 40
G45: Tiene que estar en un rango de 30 a 50 minutos
A46: Actividad 1 (Obligatoria)
A47: Competencia que predomina en la actividad | B47: El estudiante Identifica conceptos clave de arquitecturas modernas y herramientas DevOps a partir de documentación técnica en actividades teóricas
A48: Tipo de Actividad | B48: actividades
A49: Ponderación | B49: 0
A50: Tiempo Aproximado
A51: Coloca el tiempo que usar en la actividad, un tiempo sugerido 30 minutos
A52: Descripcion de la Actividad
A57: Actividad 2 (Optativa puedes hacerla si lo consideras apropiado)
A58: Competencia que predomina en la actividad
A59: Tipo de Actividad
A60: Ponderación
A61: Tiempo Aproximado
A62: Coloca el tiempo que usar en la actividad, un tiempo sugerido 20 minutos
A63: Descripcion de la Actividad
A68: 3. Cierre | G68: Tiempo Aproximado | H68: 10
G69: Tiene que estar en un rango de 10 a 15 minutos
A70: Tiempo Aproximado | B70: 10
A71: Asignacion de Actividades
A72: Asignacion de la practica 6 y su respectiva lectura. Resolucion de dudas de la misma y publicación de horarios de calificacion de la practica 5
A74: Resuelve alguna duda, asigna las actividades que deben realizar, dudas de proyectos, etc

Sheet S.8
B2: Diseño de la Sesión de Laboratorio
B4: Curso | C4: ='Diseño'!C4 -> 780 - Software Avanzado
B5: Semana | C5: 8
B6: Tiempo | C6: =H10+H21+H44+H68 -> 110
B7: Ponderación | C7: =B49+B60 -> 0
B8: Validación de Tiempo | C8: =IF(H44<=0, "❌ ERROR: La Actividad 1 debe tener un tiempo mayor a 0.", IF(H21>60, "❌ ERROR: El 'Área de Conocimiento' no puede exceder los 60 min.", IF((H10+H21+H44)<100, "❌ ERROR: El tiempo total debe ser de al menos 100 min.", "✅ VALIDACIÓN CORRECTA"))) -> ✅ VALIDACIÓN CORRECTA
A10: 1. Área Actitudinal (Saber Ser) | G10: Tiempo Aproximado | H10: 5
G11: Tiene que estar en un rango de 3 a 5 minutos
A12: Nombre del Valor | B12: Automatización y entrega continua de valor
A13: Tiempo Aproximado | B13: 5
A14: Descripcion
A15: Porque todos los temas de DevOps están enfocados en: Entregar software más rápido Reducir errores mediante automatización Mejorar la colaboración entre desarrollo y operaciones
A17: Como se relaciona con los conocimientos de la sesion y se aplicaria
A18: Desarrollo Tradicional vs DevOps Tradicional → procesos lentos y manuales DevOps → procesos automatizados y continuos
A21: 2. Área Conocimiento (Saber) | G21: Tiempo Aproximado | H21: 60
G22: No puede exceder los 60 minutos
A23: Competencia a desarrollar | B23: El estudiante Aplica prácticas de DevOps y DevSecOps mediante pipelines automatizados en proyectos de software
A24: Competencia a desarrollar | B24: El estudiante Explica el funcionamiento de pipelines CI/CD utilizando herramientas de integración continua mediante ejemplos prácticos
A26: 2.1 Contenido
A27: No. | B27: Unidad | D27: Tema | F27: Sub Tema
A28: 1 | B28: =IFERROR(__xludf.DUMMYFUNCTION("FILTER('Diseño'!D:D,'Diseño'!H:H=$C$5)"),"Introduccion a DevOps") -> Introduccion a DevOps | D28: =IFERROR(__xludf.DUMMYFUNCTION("FILTER('Diseño'!E:E,'Diseño'!H:H=$C$5)"),"Desarrollo Tradicional Vs DevOps") -> Desarrollo Tradicional Vs DevOps | F28: =IFERROR(__xludf.DUMMYFUNCTION("FILTER('Diseño'!F:F,'Diseño'!H:H=$C$5)"),"Desarrollo Tradicional Vs DevOps") -> Desarrollo Tradicional Vs DevOps
A29: 2 | B29: =IFERROR(__xludf.DUMMYFUNCTION("""COMPUTED_VALUE"""),"DevOps") -> DevOps | D29: =IFERROR(__xludf.DUMMYFUNCTION("""COMPUTED_VALUE"""),"Fases del Cliclo de vida DevOps") -> Fases del Cliclo de vida DevOps | F29: =IFERROR(__xludf.DUMMYFUNCTION("""COMPUTED_VALUE"""),"Plan") -> Plan
A30: 3 | B30: =IFERROR(__xludf.DUMMYFUNCTION("""COMPUTED_VALUE"""),"DevOps") -> DevOps | D30: =IFERROR(__xludf.DUMMYFUNCTION("""COMPUTED_VALUE"""),"Fases del Cliclo de vida DevOps") -> Fases del Cliclo de vida DevOps | F30: =IFERROR(__xludf.DUMMYFUNCTION("""COMPUTED_VALUE"""),"Code") -> Code
A31: 4 | B31: =IFERROR(__xludf.DUMMYFUNCTION("""COMPUTED_VALUE"""),"DevOps") -> DevOps | D31: =IFERROR(__xludf.DUMMYFUNCTION("""COMPUTED_VALUE"""),"Fases del Cliclo de vida DevOps") -> Fases del Cliclo de vida DevOps | F31: =IFERROR(__xludf.DUMMYFUNCTION("""COMPUTED_VALUE"""),"Build") -> Build
A32: 5 | B32: =IFERROR(__xludf.DUMMYFUNCTION("""COMPUTED_VALUE"""),"DevOps") -> DevOps | D32: =IFERROR(__xludf.DUMMYFUNCTION("""COMPUTED_VALUE"""),"Fases del Cliclo de vida DevOps") -> Fases del Cliclo de vida DevOps | F32: =IFERROR(__xludf.DUMMYFUNCTION("""COMPUTED_VALUE"""),"Test") -> Test
A33: 6 | B33: =IFERROR(__xludf.DUMMYFUNCTION("""COMPUTED_VALUE"""),"DevOps") -> DevOps | D33: =IFERROR(__xludf.DUMMYFUNCTION("""COMPUTED_VALUE"""),"Test") -> Test | F33: =IFERROR(__xludf.DUMMYFUNCTION("""COMPUTED_VALUE"""),"Tipos de Test") -> Tipos de Test
A34: 7 | B34: =IFERROR(__xludf.DUMMYFUNCTION("""COMPUTED_VALUE"""),"DevOps") -> DevOps | D34: =IFERROR(__xludf.DUMMYFUNCTION("""COMPUTED_VALUE"""),"Tipos de Test") -> Tipos de Test | F34: =IFERROR(__xludf.DUMMYFUNCTION("""COMPUTED_VALUE"""),"Integracion,E2E,Unitarios") -> Integracion,E2E,Unitarios
A36: 2.2 Recursos Educativos
A38: Tipo de Recurso a utilizar | B38: Tipo | C38: Valor maximo recomendado en Minutos | D38: Tiempo Aproximado ( unicamente el valor de minutos ) | I38: Validacion
A39: Presentacion | B39: Obligatorio | C39: 30 | D39: 30 | I39: =IF(D39<=C39,"Correcto", "Corregir") -> Correcto
A40: Video | B40: Obligatorio | C40: 6 | D40: 5 | I40: =IF(D40<=C40,"Correcto", "Corregir") -> Correcto
A41: Lectura | B41: Optativo | C41: 10 | D41: 0 | I41: =IF(D41<=C41,"Correcto", "Corregir") -> Correcto
A42: Ejercicio Demostrativo | B42: Obligatorio | C42: 30 | D42: 30 | I42: =IF(D42<=C42,"Correcto", "Corregir") -> Correcto
A44: 3. Área de Habilidades (Saber Hacer) | G44: Tiempo Aproximado | H44: 35
G45: Tiene que estar en un rango de 30 a 50 minutos
A46: Actividad 1 (Obligatoria)
A47: Competencia que predomina en la actividad | B47: El estudiante Aplica prácticas de DevOps y DevSecOps mediante pipelines automatizados en proyectos de software
A48: Tipo de Actividad | B48: actividades
A49: Ponderación | B49: 0
A50: Tiempo Aproximado | B50: 35
A51: Coloca el tiempo que usar en la actividad, un tiempo sugerido 30 minutos
A52: Descripcion de la Actividad
A53: Ejercicio practico implementando un ciclo de build y test utlizando Jenkins.
A57: Actividad 2 (Optativa puedes hacerla si lo consideras apropiado)
A58: Competencia que predomina en la actividad
A59: Tipo de Actividad
A60: Ponderación
A61: Tiempo Aproximado
A62: Coloca el tiempo que usar en la actividad, un tiempo sugerido 20 minutos
A63: Descripcion de la Actividad
A68: 3. Cierre | G68: Tiempo Aproximado | H68: 10
G69: Tiene que estar en un rango de 10 a 15 minutos
A70: Tiempo Aproximado | B70: 10
A71: Asignacion de Actividades
A72: Asignacion de la practica numero 7 y su respectiva lectura. Resolucion de dudas de la practica 7 y publicación de horarios de califación de la practica numero 6.
A74: Resuelve alguna duda, asigna las actividades que deben realizar, dudas de proyectos, etc

Sheet S.9
B2: Diseño de la Sesión de Laboratorio
B4: Curso | C4: ='Diseño'!C4 -> 780 - Software Avanzado
B5: Semana | C5: 9
B6: Tiempo | C6: =H10+H21+H44+H68 -> 115
B7: Ponderación | C7: =B49+B60 -> 0
B8: Validación de Tiempo | C8: =IF(H44<=0, "❌ ERROR: La Actividad 1 debe tener un tiempo mayor a 0.", IF(H21>60, "❌ ERROR: El 'Área de Conocimiento' no puede exceder los 60 min.", IF((H10+H21+H44)<100, "❌ ERROR: El tiempo total debe ser de al menos 100 min.", "✅ VALIDACIÓN CORRECTA"))) -> ✅ VALIDACIÓN CORRECTA
A10: 1. Área Actitudinal (Saber Ser) | G10: Tiempo Aproximado | H10: 5
G11: Tiene que estar en un rango de 3 a 5 minutos
A12: Nombre del Valor | B12: Gestión de control y versionamiento
A13: Tiempo Aproximado | B13: 5
A14: Descripcion
A15: Utiliza herramientas de control de versiones, entornos de desarrollo integrados (IDE) y sistemas de gestión de incidencias para gestionar eficientemente el código fuente, automatizar tareas del ciclo de vida del software y colaborar de forma efectiva en equipos de desarrollo ágil.
A17: Como se relaciona con los conocimientos de la sesion y se aplicaria
A18: Integra componentes, servicios y tecnologías de software mediante el uso de APIs, servicios web y herramientas de integración continua, asegurando la interoperabilidad, cohesión funcional y eficiencia en la entrega de soluciones informáticas.
A21: 2. Área Conocimiento (Saber) | G21: Tiempo Aproximado | H21: 60
G22: No puede exceder los 60 minutos
A23: Competencia a desarrollar | B23: El estudiante Aplica prácticas de DevOps y DevSecOps mediante pipelines automatizados en proyectos de software
A24: Competencia a desarrollar | B24: El estudiante Aplica prácticas de DevOps y DevSecOps mediante pipelines automatizados en proyectos de software
A26: 2.1 Contenido
A27: No. | B27: Unidad | D27: Tema | F27: Sub Tema
A28: 1 | B28: =IFERROR(__xludf.DUMMYFUNCTION("FILTER('Diseño'!D:D,'Diseño'!H:H=$C$5)"),"DevOps") -> DevOps | D28: =IFERROR(__xludf.DUMMYFUNCTION("FILTER('Diseño'!E:E,'Diseño'!H:H=$C$5)"),"Herramientas DevOps") -> Herramientas DevOps | F28: =IFERROR(__xludf.DUMMYFUNCTION("FILTER('Diseño'!F:F,'Diseño'!H:H=$C$5)"),"Github action, Gitlab CI, Jenkings") -> Github action, Gitlab CI, Jenkings
A29: 2 | B29: =IFERROR(__xludf.DUMMYFUNCTION("""COMPUTED_VALUE"""),"DevSecOps") -> DevSecOps | D29: =IFERROR(__xludf.DUMMYFUNCTION("""COMPUTED_VALUE"""),"Cultura DevSecOps") -> Cultura DevSecOps | F29: =IFERROR(__xludf.DUMMYFUNCTION("""COMPUTED_VALUE"""),"Origin DevSecOps") -> Origin DevSecOps
A30: 3 | B30: =IFERROR(__xludf.DUMMYFUNCTION("""COMPUTED_VALUE"""),"DevSecOps") -> DevSecOps | D30: =IFERROR(__xludf.DUMMYFUNCTION("""COMPUTED_VALUE"""),"Automatización") -> Automatización | F30: =IFERROR(__xludf.DUMMYFUNCTION("""COMPUTED_VALUE"""),"Pipelines") -> Pipelines
A31: 4 | B31: =IFERROR(__xludf.DUMMYFUNCTION("""COMPUTED_VALUE"""),"DevSecOps") -> DevSecOps | D31: =IFERROR(__xludf.DUMMYFUNCTION("""COMPUTED_VALUE"""),"Harramientas") -> Harramientas | F31: =IFERROR(__xludf.DUMMYFUNCTION("""COMPUTED_VALUE"""),"Analisis de codigo Estatico") -> Analisis de codigo Estatico
A32: 5 | B32: =IFERROR(__xludf.DUMMYFUNCTION("""COMPUTED_VALUE"""),"DevSecOps") -> DevSecOps | D32: =IFERROR(__xludf.DUMMYFUNCTION("""COMPUTED_VALUE"""),"Analisis de Codigo Estatico") -> Analisis de Codigo Estatico | F32: =IFERROR(__xludf.DUMMYFUNCTION("""COMPUTED_VALUE"""),"Herramientas") -> Herramientas
A33: 6 | B33: =IFERROR(__xludf.DUMMYFUNCTION("""COMPUTED_VALUE"""),"DevSecOps") -> DevSecOps | D33: =IFERROR(__xludf.DUMMYFUNCTION("""COMPUTED_VALUE"""),"Herramientas Analisis de Codigo Estatico") -> Herramientas Analisis de Codigo Estatico | F33: =IFERROR(__xludf.DUMMYFUNCTION("""COMPUTED_VALUE"""),"Qodana") -> Qodana
A34: 7 | B34: =IFERROR(__xludf.DUMMYFUNCTION("""COMPUTED_VALUE"""),"DevSecOps") -> DevSecOps | D34: =IFERROR(__xludf.DUMMYFUNCTION("""COMPUTED_VALUE"""),"Herramientas Analisis de Codigo Estatico") -> Herramientas Analisis de Codigo Estatico | F34: =IFERROR(__xludf.DUMMYFUNCTION("""COMPUTED_VALUE"""),"SonarKube") -> SonarKube
A36: 2.2 Recursos Educativos
A38: Tipo de Recurso a utilizar | B38: Tipo | C38: Valor maximo recomendado en Minutos | D38: Tiempo Aproximado ( unicamente el valor de minutos ) | I38: Validacion
A39: Presentacion | B39: Obligatorio | C39: 30 | I39: =IF(D39<=C39,"Correcto", "Corregir") -> Correcto
A40: Video | B40: Obligatorio | C40: 6 | I40: =IF(D40<=C40,"Correcto", "Corregir") -> Correcto
A41: Lectura | B41: Optativo | C41: 10 | I41: =IF(D41<=C41,"Correcto", "Corregir") -> Correcto
A42: Ejercicio Demostrativo | B42: Obligatorio | C42: 30 | I42: =IF(D42<=C42,"Correcto", "Corregir") -> Correcto
A44: 3. Área de Habilidades (Saber Hacer) | G44: Tiempo Aproximado | H44: 40
G45: Tiene que estar en un rango de 30 a 50 minutos
A46: Actividad 1 (Obligatoria)
A47: Competencia que predomina en la actividad | B47: El estudiante Aplica prácticas de DevOps y DevSecOps mediante pipelines automatizados en proyectos de software
A48: Tipo de Actividad | B48: actividades
A49: Ponderación | B49: 0
A50: Tiempo Aproximado
A51: Coloca el tiempo que usar en la actividad, un tiempo sugerido 30 minutos
A52: Descripcion de la Actividad
A57: Actividad 2 (Optativa puedes hacerla si lo consideras apropiado)
A58: Competencia que predomina en la actividad
A59: Tipo de Actividad
A60: Ponderación
A61: Tiempo Aproximado
A62: Coloca el tiempo que usar en la actividad, un tiempo sugerido 20 minutos
A63: Descripcion de la Actividad
A68: 3. Cierre | G68: Tiempo Aproximado | H68: 10
G69: Tiene que estar en un rango de 10 a 15 minutos
A70: Tiempo Aproximado | B70: 10
A71: Asignacion de Actividades
A72: Asignacion de la practica numero 8 y respectiva lectura. Resolucion de dudas de la practica numero 8 y publicacion de horarios de calificacion de la practica numero 7
A74: Resuelve alguna duda, asigna las actividades que deben realizar, dudas de proyectos, etc

Sheet S.10
B2: Diseño de la Sesión de Laboratorio
B4: Curso | C4: ='Diseño'!C4 -> 780 - Software Avanzado
B5: Semana | C5: 10
B6: Tiempo | C6: =H10+H21+H44+H68 -> 110
B7: Ponderación | C7: =B49+B60 -> 0
B8: Validación de Tiempo | C8: =IF(H44<=0, "❌ ERROR: La Actividad 1 debe tener un tiempo mayor a 0.", IF(H21>60, "❌ ERROR: El 'Área de Conocimiento' no puede exceder los 60 min.", IF((H10+H21+H44)<100, "❌ ERROR: El tiempo total debe ser de al menos 100 min.", "✅ VALIDACIÓN CORRECTA"))) -> ✅ VALIDACIÓN CORRECTA
A10: 1. Área Actitudinal (Saber Ser) | G10: Tiempo Aproximado | H10: 5
G11: Tiene que estar en un rango de 3 a 5 minutos
A12: Nombre del Valor | B12: Calidad continua del software
A13: Tiempo Aproximado | B13: 5
A14: Descripcion
A15: Continuous Testing en DevOps busca que la calidad no sea una fase final, sino algo que se valida constantemente en todo el ciclo de desarrollo.
A17: Como se relaciona con los conocimientos de la sesion y se aplicaria
A18: Continuous Testing Integración de pruebas en todo el pipeline
A21: 2. Área Conocimiento (Saber) | G21: Tiempo Aproximado | H21: 60
G22: No puede exceder los 60 minutos
A23: Competencia a desarrollar | B23: El estudiante Explica el funcionamiento de pipelines CI/CD utilizando herramientas de integración continua mediante ejemplos prácticos
A24: Competencia a desarrollar | B24: El estudiante Explica el funcionamiento de pipelines CI/CD utilizando herramientas de integración continua mediante ejemplos prácticos
A26: 2.1 Contenido
A27: No. | B27: Unidad | D27: Tema | F27: Sub Tema
A28: 1 | B28: =IFERROR(__xludf.DUMMYFUNCTION("FILTER('Diseño'!D:D,'Diseño'!H:H=$C$5)"),"DevOps") -> DevOps | D28: =IFERROR(__xludf.DUMMYFUNCTION("FILTER('Diseño'!E:E,'Diseño'!H:H=$C$5)"),"Testing en DevOps") -> Testing en DevOps | F28: =IFERROR(__xludf.DUMMYFUNCTION("FILTER('Diseño'!F:F,'Diseño'!H:H=$C$5)"),"Continuous Testing") -> Continuous Testing
A29: 2 | B29: =IFERROR(__xludf.DUMMYFUNCTION("""COMPUTED_VALUE"""),"DevOps") -> DevOps | D29: =IFERROR(__xludf.DUMMYFUNCTION("""COMPUTED_VALUE"""),"Continuous Testing") -> Continuous Testing | F29: =IFERROR(__xludf.DUMMYFUNCTION("""COMPUTED_VALUE"""),"Pruebas Unitarias") -> Pruebas Unitarias
A30: 3 | B30: =IFERROR(__xludf.DUMMYFUNCTION("""COMPUTED_VALUE"""),"DevOps") -> DevOps | D30: =IFERROR(__xludf.DUMMYFUNCTION("""COMPUTED_VALUE"""),"Continuous Testing") -> Continuous Testing | F30: =IFERROR(__xludf.DUMMYFUNCTION("""COMPUTED_VALUE"""),"Pruebas de Integración") -> Pruebas de Integración
A31: 4 | B31: =IFERROR(__xludf.DUMMYFUNCTION("""COMPUTED_VALUE"""),"DevOps") -> DevOps | D31: =IFERROR(__xludf.DUMMYFUNCTION("""COMPUTED_VALUE"""),"Continuous Testing") -> Continuous Testing | F31: =IFERROR(__xludf.DUMMYFUNCTION("""COMPUTED_VALUE"""),"Pruebas de Regresión") -> Pruebas de Regresión
A32: 5 | B32: =IFERROR(__xludf.DUMMYFUNCTION("""COMPUTED_VALUE"""),"DevOps") -> DevOps | D32: =IFERROR(__xludf.DUMMYFUNCTION("""COMPUTED_VALUE"""),"Continuous Testing") -> Continuous Testing | F32: =IFERROR(__xludf.DUMMYFUNCTION("""COMPUTED_VALUE"""),"Pruebas Funcionales y de UI") -> Pruebas Funcionales y de UI
A33: 6 | B33: =IFERROR(__xludf.DUMMYFUNCTION("""COMPUTED_VALUE"""),"DevOps") -> DevOps | D33: =IFERROR(__xludf.DUMMYFUNCTION("""COMPUTED_VALUE"""),"Continuous Testing") -> Continuous Testing | F33: =IFERROR(__xludf.DUMMYFUNCTION("""COMPUTED_VALUE"""),"Pruebas de Seguridad (DevSecOps)") -> Pruebas de Seguridad (DevSecOps)
A34: 7 | B34: =IFERROR(__xludf.DUMMYFUNCTION("""COMPUTED_VALUE"""),"DevOps") -> DevOps | D34: =IFERROR(__xludf.DUMMYFUNCTION("""COMPUTED_VALUE"""),"Continuous Testing") -> Continuous Testing | F34: =IFERROR(__xludf.DUMMYFUNCTION("""COMPUTED_VALUE"""),"Pruebas de Rendimiento") -> Pruebas de Rendimiento
A36: 2.2 Recursos Educativos
A38: Tipo de Recurso a utilizar | B38: Tipo | C38: Valor maximo recomendado en Minutos | D38: Tiempo Aproximado ( unicamente el valor de minutos ) | I38: Validacion
A39: Presentacion | B39: Obligatorio | C39: 30 | D39: 30 | I39: =IF(D39<=C39,"Correcto", "Corregir") -> Correcto
A40: Video | B40: Obligatorio | C40: 6 | D40: 5 | I40: =IF(D40<=C40,"Correcto", "Corregir") -> Correcto
A41: Lectura | B41: Optativo | C41: 10 | D41: 0 | I41: =IF(D41<=C41,"Correcto", "Corregir") -> Correcto
A42: Ejercicio Demostrativo | B42: Obligatorio | C42: 30 | D42: 30 | I42: =IF(D42<=C42,"Correcto", "Corregir") -> Correcto
A44: 3. Área de Habilidades (Saber Hacer) | G44: Tiempo Aproximado | H44: 35
G45: Tiene que estar en un rango de 30 a 50 minutos
A46: Actividad 1 (Obligatoria)
A47: Competencia que predomina en la actividad | B47: El estudiante Explica el funcionamiento de pipelines CI/CD utilizando herramientas de integración continua mediante ejemplos prácticos
A48: Tipo de Actividad | B48: Ejercicio practico
A49: Ponderación | B49: 0
A50: Tiempo Aproximado | B50: 35
A51: Coloca el tiempo que usar en la actividad, un tiempo sugerido 30 minutos
A52: Descripcion de la Actividad
A53: Diseño de un pipeline integrando fase de build, test, analisis de codigo estatico y despliegue en la nube
A57: Actividad 2 (Optativa puedes hacerla si lo consideras apropiado)
A58: Competencia que predomina en la actividad
A59: Tipo de Actividad
A60: Ponderación
A61: Tiempo Aproximado
A62: Coloca el tiempo que usar en la actividad, un tiempo sugerido 20 minutos
A63: Descripcion de la Actividad
A68: 3. Cierre | G68: Tiempo Aproximado | H68: 10
G69: Tiene que estar en un rango de 10 a 15 minutos
A70: Tiempo Aproximado | B70: 10
A71: Asignacion de Actividades
A72: Asignacion de la practica numero 9 y respectiva lectura. Resolucion de dudas de la practica numero 9 y publicacion de horarios de calificacion de la practica numero 8
A74: Resuelve alguna duda, asigna las actividades que deben realizar, dudas de proyectos, etc

Sheet S.11
B2: Diseño de la Sesión de Laboratorio
B4: Curso | C4: ='Diseño'!C4 -> 780 - Software Avanzado
B5: Semana | C5: 11
B6: Tiempo | C6: =H10+H21+H44+H68 -> 115
B7: Ponderación | C7: =B49+B60 -> 0
B8: Validación de Tiempo | C8: =IF(H44<=0, "❌ ERROR: La Actividad 1 debe tener un tiempo mayor a 0.", IF(H21>60, "❌ ERROR: El 'Área de Conocimiento' no puede exceder los 60 min.", IF((H10+H21+H44)<100, "❌ ERROR: El tiempo total debe ser de al menos 100 min.", "✅ VALIDACIÓN CORRECTA"))) -> ✅ VALIDACIÓN CORRECTA
A10: 1. Área Actitudinal (Saber Ser) | G10: Tiempo Aproximado | H10: 5
G11: Tiene que estar en un rango de 3 a 5 minutos
A12: Nombre del Valor | B12: Automatización del software
A13: Tiempo Aproximado | B13: 5
A14: Descripcion
A15: Utiliza herramientas de control de versiones, entornos de desarrollo integrados (IDE) y sistemas de gestión de incidencias para gestionar eficientemente el código fuente, automatizar tareas del ciclo de vida del software y colaborar de forma efectiva en equipos de desarrollo ágil.
A17: Como se relaciona con los conocimientos de la sesion y se aplicaria
A18: Mejora continuamente el rendimiento, la seguridad y la mantenibilidad de sistemas de software existentes, mediante el análisis de métricas, refactorización de código, aplicación de principios SOLID y adopción de herramientas de monitoreo y automatización, asegurando soluciones más eficientes y alineadas con los estándares de calidad del sector.
A21: 2. Área Conocimiento (Saber) | G21: Tiempo Aproximado | H21: 60
G22: No puede exceder los 60 minutos
A23: Competencia a desarrollar | B23: El estudiante Aplica prácticas de DevOps y DevSecOps mediante pipelines automatizados en proyectos de software
A24: Competencia a desarrollar | B24: El estudiante Aplica prácticas de DevOps y DevSecOps mediante pipelines automatizados en proyectos de software
A26: 2.1 Contenido
A27: No. | B27: Unidad | D27: Tema | F27: Sub Tema
A28: 1 | B28: =IFERROR(__xludf.DUMMYFUNCTION("FILTER('Diseño'!D:D,'Diseño'!H:H=$C$5)"),"DevOps") -> DevOps | D28: =IFERROR(__xludf.DUMMYFUNCTION("FILTER('Diseño'!E:E,'Diseño'!H:H=$C$5)"),"Deployment en DevOps") -> Deployment en DevOps | F28: =IFERROR(__xludf.DUMMYFUNCTION("FILTER('Diseño'!F:F,'Diseño'!H:H=$C$5)"),"Sistemas de Control de VersionesS") -> Sistemas de Control de VersionesS
A29: 2 | B29: =IFERROR(__xludf.DUMMYFUNCTION("""COMPUTED_VALUE"""),"DevOps") -> DevOps | D29: =IFERROR(__xludf.DUMMYFUNCTION("""COMPUTED_VALUE"""),"Deployment en DevOps") -> Deployment en DevOps | F29: =IFERROR(__xludf.DUMMYFUNCTION("""COMPUTED_VALUE"""),"Pipeline de CI/CD") -> Pipeline de CI/CD
A30: 3 | B30: =IFERROR(__xludf.DUMMYFUNCTION("""COMPUTED_VALUE"""),"DevOps") -> DevOps | D30: =IFERROR(__xludf.DUMMYFUNCTION("""COMPUTED_VALUE"""),"Deployment en DevOps") -> Deployment en DevOps | F30: =IFERROR(__xludf.DUMMYFUNCTION("""COMPUTED_VALUE"""),"Infraestructura como Código (IaC)") -> Infraestructura como Código (IaC)
A31: 4 | B31: =IFERROR(__xludf.DUMMYFUNCTION("""COMPUTED_VALUE"""),"DevOps") -> DevOps | D31: =IFERROR(__xludf.DUMMYFUNCTION("""COMPUTED_VALUE"""),"Deployment en DevOps") -> Deployment en DevOps | F31: =IFERROR(__xludf.DUMMYFUNCTION("""COMPUTED_VALUE"""),"Pruebas Automatizadas") -> Pruebas Automatizadas
A32: 5 | B32: =IFERROR(__xludf.DUMMYFUNCTION("""COMPUTED_VALUE"""),"DevOps") -> DevOps | D32: =IFERROR(__xludf.DUMMYFUNCTION("""COMPUTED_VALUE"""),"Deployment en DevOps") -> Deployment en DevOps | F32: =IFERROR(__xludf.DUMMYFUNCTION("""COMPUTED_VALUE"""),"Continuous Delivery") -> Continuous Delivery
A33: 6 | B33: =IFERROR(__xludf.DUMMYFUNCTION("""COMPUTED_VALUE"""),"DevOps") -> DevOps | D33: =IFERROR(__xludf.DUMMYFUNCTION("""COMPUTED_VALUE"""),"Deployment en DevOps") -> Deployment en DevOps | F33: =IFERROR(__xludf.DUMMYFUNCTION("""COMPUTED_VALUE"""),"Continuous Delivery Vs Continuous Deployment") -> Continuous Delivery Vs Continuous Deployment
A34: 7 | B34: =IFERROR(__xludf.DUMMYFUNCTION("""COMPUTED_VALUE"""),"DesOps") -> DesOps | D34: =IFERROR(__xludf.DUMMYFUNCTION("""COMPUTED_VALUE"""),"CI/CD Automatizado") -> CI/CD Automatizado | F34: =IFERROR(__xludf.DUMMYFUNCTION("""COMPUTED_VALUE"""),"Herramientas de CI/CD") -> Herramientas de CI/CD
A36: 2.2 Recursos Educativos
A38: Tipo de Recurso a utilizar | B38: Tipo | C38: Valor maximo recomendado en Minutos | D38: Tiempo Aproximado ( unicamente el valor de minutos ) | I38: Validacion
A39: Presentacion | B39: Obligatorio | C39: 30 | I39: =IF(D39<=C39,"Correcto", "Corregir") -> Correcto
A40: Video | B40: Obligatorio | C40: 6 | I40: =IF(D40<=C40,"Correcto", "Corregir") -> Correcto
A41: Lectura | B41: Optativo | C41: 10 | I41: =IF(D41<=C41,"Correcto", "Corregir") -> Correcto
A42: Ejercicio Demostrativo | B42: Obligatorio | C42: 30 | I42: =IF(D42<=C42,"Correcto", "Corregir") -> Correcto
A44: 3. Área de Habilidades (Saber Hacer) | G44: Tiempo Aproximado | H44: 40
G45: Tiene que estar en un rango de 30 a 50 minutos
A46: Actividad 1 (Obligatoria)
A47: Competencia que predomina en la actividad | B47: El estudiante Aplica prácticas de DevOps y DevSecOps mediante pipelines automatizados en proyectos de software
A48: Tipo de Actividad | B48: actividades
A49: Ponderación | B49: 0
A50: Tiempo Aproximado
A51: Coloca el tiempo que usar en la actividad, un tiempo sugerido 30 minutos
A52: Descripcion de la Actividad
A57: Actividad 2 (Optativa puedes hacerla si lo consideras apropiado)
A58: Competencia que predomina en la actividad
A59: Tipo de Actividad
A60: Ponderación
A61: Tiempo Aproximado
A62: Coloca el tiempo que usar en la actividad, un tiempo sugerido 20 minutos
A63: Descripcion de la Actividad
A68: 3. Cierre | G68: Tiempo Aproximado | H68: 10
G69: Tiene que estar en un rango de 10 a 15 minutos
A70: Tiempo Aproximado | B70: 10
A71: Asignacion de Actividades
A72: Asignacion de la practica numero 10 y respectiva lectura. Resolucion de dudas de la practica numero 10 y publicacion de horarios de calificacion de la practica numero 9
A74: Resuelve alguna duda, asigna las actividades que deben realizar, dudas de proyectos, etc

Sheet Proyectos
B2: Proyectos
B4: Curso | C4: ='Diseño'!C4 -> 780 - Software Avanzado
B5: Tiempo | C5: =H9+H26+H43 -> 252
B6: Ponderación | C6: =F9+F26+F43 -> 60
B7: La sumatoria de los puntos de los proyectos debe superar el 60% del total de la nota, no puede ser un 100%
A9: 1. Primer Proyecto | E9: Ponderación | F9: 15 | G9: Horas para realizarlo | H9: 84
A10: Obligatorio
A11: Competencia a desarrollar | B11: El estudiante Crea .. soluciones de software basadas en microservicios poniendo en practica los principios SOLID usando herramientas de desarrollo y contenedores en entornos prácticos de laboratorio
A12: Competencia a desarrollar | B12: El estudiante Identifica conceptos clave de arquitecturas modernas y herramientas DevOps a partir de documentación técnica en actividades teóricas
A13: Competencia a desarrollar | B13: El estudiante Analiza .. arquitecturas de software basadas en microservicios utilizando diagramas y patrones arquitectónicos en estudios de caso reales
A14: Titulo | B14: BANK USAC. SA Fase I
A15: Qué tecnologías, lenguajes de programación, plataformas, hardware o software se utilizaran
A16: Lenguajes: TypeScript, JavaScript, Java, Golang. Frameworks: NestJS, Java Springboot 4, Fiber, GIN Orquestación: Docker y Kubernetes Bases de datos: Libre
A19: Descripción de lo que se realizara
A20: Es el estudiante deberá de desarrollar una arquitectura de microservicios de una plataforma bancaria. Llevando cada una de las areas de negocio del mismo. Separando la lógica de negocio en los respectivos microservicios según criterio del estudiante. Además deberá diseñar la documentación respectiva. Debera realizar como mínimo 4 microservicios, API gateway y la comunicación debe ser asíncrona utilizando el transport de su preferencia (RabbitMQ, NATS, KAFFKA, ect...) El despliegue de la arquitectura se realizara de manera local en K8S. Además debe de existir una base de datos por microservicios para no caer en anti patrones de microservicios. Debe de trabajar con diferentes bases de datos (Mongo, MySQL, Oracle db, PostgreSQL, ect..)
A26: 2. Segundo Proyecto | E26: Ponderación | F26: 21 | G26: Horas para realizarlo | H26: 84
A27: Obligatorio
A28: Competencia a desarrollar | B28: El estudiante Aplica prácticas de DevOps y DevSecOps mediante pipelines automatizados en proyectos de software
A29: Competencia a desarrollar | B29: El estudiante Explica el funcionamiento de pipelines CI/CD utilizando herramientas de integración continua mediante ejemplos prácticos
A30: Competencia a desarrollar | B30: El estudiante Identifica conceptos clave de arquitecturas modernas y herramientas DevOps a partir de documentación técnica en actividades teóricas
A31: Titulo | B31: BANK USAC. SA Fase II
A32: Qué tecnologías, lenguajes de programación, plataformas, hardware o software se utilizaran
A33: Orquestación: Docker y Kubernetes Nubes: AWS o GCP CI/CD: Jenkings, GitHub Actions, Gitlab CI. TEST SUIT: Jasmine, Mocka, JUnit, Mockito, Selenium, handStage, Jest
A36: Descripción de lo que se realizara
A37: El estudiante deberá realizar nuevas funcionabilidades para el sistema bancario de BANK USAC. SA. Debera diseñar un flujo de CI/CD con las siguientes características: - Stages: Build, test, análisis de código estático. - Solicitud de merge Request para pasar de una feature a la rama de desarrollo. - Repetir las respectivas Stages de en el ambiente de desarrollo y realizar un nuevo merge request - Publicar las imágenes actualizadas de docker y realizar un tag. - Desplegar cambios en el cluster de k8s Nota: Todo debe de realizarse de manera automática y debe de estar en un entorno clound. Pruebas a realizar por microservicio: Unitarias, E2E, Integración y test de aceptacion
A43: 3. Tercer Proyecto | E43: Ponderación | F43: 24 | G43: Horas para realizarlo | H43: 84
A44: Optativa
A45: Competencia a desarrollar | B45: El estudiante Evalúa estrategias de despliegue y monitoreo utilizando Kubernetes y herramientas de observabilidad en distintos escenarios de implementación
A46: Competencia a desarrollar | B46: El estudiante Analiza .. arquitecturas de software basadas en microservicios utilizando diagramas y patrones arquitectónicos en estudios de caso reales
A47: Competencia a desarrollar | B47: El estudiante Aplica prácticas de DevOps y DevSecOps mediante pipelines automatizados en proyectos de software
A48: Titulo | B48: BANK USAC. SA Fase III
A49: Qué tecnologías, lenguajes de programación, plataformas, hardware o software se utilizaran
A50: Orquestación: Docker y Kubernetes Nubes: AWS o GCP CI/CD: Jenkings, GitHub Actions, Gitlab CI. TEST SUIT: Jasmine, Mocka, JUnit, Mockito, Selenium, handStage, Jest Monitorización: Grafana, ELK Stack (Elasticsearch, Logstash, Kibana)
A53: Descripción de lo que se realizara
A54: Como fase final del ciclo devops el estudiante deberá realizar la fase de monitorización del sistema bancario BANK USAC. SA. Implementación de Monitoreo con Prometheus Se deberá desplegar Prometheus dentro del clúster de Kubernetes con el objetivo de recolectar métricas de: • CPU y memoria por Pod • Latencia de respuestas de microservicios • Número de requests • Errores HTTP • Reinicios de Pods • Uso de recursos del clúster • ServiceMonitor o PodMonitor • Scraping automático de endpoints /metrics • Configuración de targets dinámicos Visualización de Métricas con Grafana Se deberá implementar Grafana conectado a Prometheus para crear dashboards personalizados. Se deberán construir al menos: Dashboard por microservicio • Requests por segundo • Tiempo de respuesta • Errores • Uso de CPU y RAM Dashboard del clúster Kubernetes • Uso total de nodos • Pods activos • Uso de memoria del cluster • HPA scaling events Implementación de Gestión de Logs con ELK Stack Se deberá desplegar una arquitectura de logging centralizada basada en: • Elasticsearch → almacenamiento e indexación • Logstash → procesamiento de logs • Kibana → visualización Software Avanzado Laboratorio Sección B Se deberá implementar: • Envío automático de logs desde los microservicios • Parsing estructurado de logs • Indexación por microservicio • Búsqueda avanzada Generación de Logs en Microservicios Cada microservicio deberá implementar logging estructurado usando librerías según el lenguaje: • Java → Log4j / Logback • NodeJS → Winston • Python → logging Los logs deberán incluir: • timestamp • nivel • servicio • mensaje • traceId Alertas Proactivas Se deberá configurar Prometheus AlertManager o Grafana Alerts para: • CPU > 80% • Pods reiniciándose constantemente • Latencia elevada • Errores HTTP críticos

Sheet Practicas
B2: Practicas
B4: Curso | C4: ='Diseño'!C4 -> 780 - Software Avanzado
B5: Tiempo | C5: =H9+H26+H43+H60+H77+H94+H111 -> 56
B6: Ponderación | C6: =F9+F26+F43+F60+F77+F94+F111 -> 20
B7: La sumatoria de los puntos de los practicas debe no debe super el 20%
A9: 1. Primera Practica | E9: Ponderación | F9: 2 | G9: Horas para realizarlo | H9: 8
A10: Obligatoria
A11: Competencia a desarrollar | B11: El estudiante Crea .. soluciones de software basadas en microservicios poniendo en practica los principios SOLID usando herramientas de desarrollo y contenedores en entornos prácticos de laboratorio
A12: Competencia a desarrollar
A13: Competencia a desarrollar
A14: Titulo | B14: Practica 1
A15: Qué tecnologías, lenguajes de programación, plataformas, hardware o software se utilizaran
A16: Lenguajes: Libre Framework: Libre
A19: Descripción de lo que se realizara
A20: El estudiante debe crear un programa backend que implemente una API REST para gestionar misiones asignadas a dentro de una academia ficticia. Cada solicitud operativa tendrá los siguientes atributos: • id (entero o UUID) • titulo (string) • area_solicitante (string) • prioridad (entero del 1 al 5) • costo_estimado (decimal) • estado (string: registrada, en_proceso, finalizada) Toda la información debe manejarse de forma persistente en base de datos PostgreSQL de prueba. Como recomendación de bases de datos de prueba supabase, neonDB o en un entorno local. Las operaciones mínimas que el sistema debe soportar son: • Obtener la información de las solicitudes operativas. • Registrar una nueva solicitud operativa. • Actualizar la información de una solicitud existente (Toda la información). • Eliminar una solicitud operativa. • Actualizar exclusivamente el estado de una solicitud operativa, sin modificar el resto de sus atributos. Cada endpoint debe cumplir con los principios SOLID y con las buenas prácticas de diseño REST.
A26: 2. Segunda Practica | E26: Ponderación | F26: 2 | G26: Horas para realizarlo | H26: 8
A27: Optativa
A28: Competencia a desarrollar | B28: El estudiante Analiza .. arquitecturas de software basadas en microservicios utilizando diagramas y patrones arquitectónicos en estudios de caso reales
A29: Competencia a desarrollar
A30: Competencia a desarrollar
A31: Titulo | B31: Practica 2
A32: Qué tecnologías, lenguajes de programación, plataformas, hardware o software se utilizaran
A33: Tecnologia: Libre
A36: Descripción de lo que se realizara
A37: Se debe crear un módulo de registro y login como parte del sprint de desarrollo del proyecto en el que se encuentra involucrado. Para esto, el líder de proyecto le da la facultad de elegir la herramienta de backend y frontend que mejor domine, así como una base de datos de tipo relacional que prefiera. Sin embargo, impone unas restricciones específicas para que este código pueda reutilizarse a futuro: 1. La comunicación entre el frontend y backend se realizará usando una API REST. 2. La autenticación debe de hacerse utilizando el método de JWT 3. Este token, por razones de seguridad, no puede estar almacenado en ningún lugar visible por el usuario. (Se le recomienda el uso de cookies, especialmente del tipo HTTPS) 4. El JWT debe de tener un tiempo de vida que será definido en una variable de entorno. 5. Se debe de considerar la renovación automática del JWT cuando el tiempo de vida de este expire y hayan pasado menos de X cantidad de tiempo desde su vencimiento. (Esta cantidad de tiempo también debe de ser declarada en una variable de entorno) 6. Al tratarse de información delicada, toda información como lo son nombres, correos, contraseñas, etc. deben de ser almacenadas de forma encriptada (para no complicarse, se recomienda utilizar el algoritmo AES). Recuerde que debe de existir una página para comprobar que el login fue exitoso. Al mismo tiempo, se le recuerda el uso de buenas prácticas de programación para que el código sea reutilizable a futuro. Autorización Se manejarán dos tipos de roles en la aplicación, los cuales serán Admin y Cliente, debe de realizar dos endpoints validando que el admin tenga acceso a los dos endpoints y que el cliente solo tenga acceso a una de las rutas. • Ruta 1: admin • Ruta 2: Cliente y admin.
A43: 3. Tercera Practica | E43: Ponderación | F43: 2 | G43: Horas para realizarlo | H43: 8
A44: Optativa
A45: Competencia a desarrollar | B45: El estudiante Identifica conceptos clave de arquitecturas modernas y herramientas DevOps a partir de documentación técnica en actividades teóricas
A46: Competencia a desarrollar
A47: Competencia a desarrollar
A48: Titulo | B48: Practica 3
A49: Qué tecnologías, lenguajes de programación, plataformas, hardware o software se utilizaran
A50: Tecnologia: Libre
A53: Descripción de lo que se realizara
A54: En la empresa donde labora actualmente, el sistema de planillas funciona bajo un esquema monolítico, lo que provoca un lento funcionamiento en épocas de alta demanda como quincenas, fin de mes, pago de aguinaldo, etc. Por ende, se acude a su equipo de trabajo para poder realizar el diseño inicial de una nueva solución para darle fin a este problema. Software Avanzado Sección B El sistema depende de un servicio de autenticación OAuth de la empresa, cuyo tiempo de vida del token es de 12 horas, sin embargo, es necesario llevar un sistema de autenticación complementario para administrar los permisos y accesos de los usuarios. Así mismo, existe un sistema externo que es el que se encarga del proceso financiero, y es al que el sistema actual termina enviando las planillas. Se debe tomar en consideración que las planillas son cargadas en un archivo del tipo CSV, y que las mismas deben de ser validadas por los reglajes internos, así como seguir un sistema de aprobación de 3 pasos por distintos usuarios. Considere que estos archivos CSV deben de ser almacenados en algún servidor (puede considerar el uso de servicios de nube asi como la implementación de un servidor FTP, por ejemplo). También se debe ser capaz de consultar el historial de todas las planillas que fueron procesadas, así como el contenido de las mismas y descarga. Cuando una planilla está en el paso final (paso 3) y cambia al estado final de aprobado, se debe enviar un correo a todos los empleados de esa planilla donde se detalle que su pago está en proceso de depósito. Es de vital importancia que se tenga un log de todo lo que ocurre en el sistema para llevar un control de seguridad y que este log pueda ser consultado. 2.1 Descripción del problema a resolver • Diseñarse bajo arquitectura de microservicios. • Integrarse con un sistema OAuth corporativo (token 12h). • Implementar control de permisos complementario. • Procesar archivos CSV de planillas. • Gestionar flujo de aprobación en 3 pasos. • Integrarse con sistema financiero externo. • Enviar correos al aprobar planilla. • Mantener historial consultable. • Implementar sistema de logging auditable. 2.2 Alcance de la práctica • Diagrama de Arquitectura General • Uso del servicio de autenticación de la practica 2 • Diseño de microservicios (mínimo 3 servicios) • Diagrama ER por servicio • Definición de flujo de aprobación • Diseño de almacenamiento de archivos CSV • Diseño de estrategia de logging • Explicación de comunicación entre servicios Propuesta de API Gateway 2.3 Requerimientos técnicos Arquitectura de Microservicios API Gateway P2 Integración Base de datos por servicio Almacenamiento de archivos (Cloud Storage o FTP) Logging centralizado  Comunicación REST y/o Mensajería
A60: 4. Cuarta Practica | E60: Ponderación | F60: 4 | G60: Horas para realizarlo | H60: 8
A61: Optativa
A62: Competencia a desarrollar | B62: El estudiante Implementa ... servicios y APIs en arquitectura de microservicios mediante Docker y frameworks de desarrollo en proyectos prácticos
A63: Competencia a desarrollar
A64: Competencia a desarrollar
A65: Titulo
A66: Qué tecnologías, lenguajes de programación, plataformas, hardware o software se utilizaran
A67: Tecnologia: Libre
A70: Descripción de lo que se realizara
A71: Se requiere que el estudiante diseñe un sistema basado en arquitectura de microservicios con temática libre. El sistema deberá: • Estar compuesto por mínimo 4 microservicios. • Cada microservicio debe tener al menos un endpoint funcional. • Implementar Docker para cada servicio. • Implementar un API Gateway que consuma todos los microservicios. • Al menos 2 microservicios deben usar GraphQL. • Deben utilizarse al menos 2 lenguajes de programación distintos. El objetivo es simular un entorno empresarial moderno basado en contenedores y arquitectura distribuida. 2.2 Alcance de la práctica Obligatorio: • 4 microservicios mínimo. • 1 endpoint funcional por microservicio. • Dockerfile por servicio. • Archivo docker-compose.yml. • API Gateway funcional. • 2 microservicios con GraphQL. • 2 lenguajes distintos. • Diagrama de arquitectura. • Diagrama ER completo de las bases de datos. • Manual básico de uso de GraphQL. • Documentación técnica completa. • Repositorio en la nube. No requerido (pero recomendado): • Autenticación JWT. • Comunicación entre microservicios. • Implementación de base de datos separada por servicio. • Pruebas unitarias. 2.3 Requerimientos técnicos El estudiante deberá utilizar: • Docker • Docker Compose • Repositorio en la nube (GitHub, GitLab, Bitbucket) • Mínimo 2 lenguajes de programación • Implementación de GraphQL en al menos 2 servicios • Diseño adecuado de microservicios (principios de desacoplamiento)
A77: 5. Quinta Practica | E77: Ponderación | F77: 2.5 | G77: Horas para realizarlo | H77: 8
A78: Optativa
A79: Competencia a desarrollar | B79: El estudiante Identifica conceptos clave de arquitecturas modernas y herramientas DevOps a partir de documentación técnica en actividades teóricas
A80: Competencia a desarrollar
A81: Competencia a desarrollar
A82: Titulo | B82: Practica 5
A83: Qué tecnologías, lenguajes de programación, plataformas, hardware o software se utilizaran
A84: Orquestacion: K8s Lenguaje: Libre FrameWork: Libre
A87: Descripción de lo que se realizara
A88: Utilizando los microservicios desarrollados en la práctica 4, se le pide que realice la implementación de un entorno local de kubernetes. Para esto deberán hacer uso de un namespace llamado “sa-p5”. Cada uno de los servicios detallados deberá de ser implementado como despliegue de tipo deployment. Además de esto, cada deployment deberá tener definido un mínimo y un máximo uso de recursos (ram y cpu), una configuración de autoescalado de mínimo 1 pod y un máximo de 2 pods cuando el pod inicial alcance el 80% de carga. Recuerde buscar optimizar el uso de recursos, por lo que la optimización de la imagen de docker generada para cada microservicio será tomada en cuenta. Ninguno de estos deployments podrá ser accedidos de forma externa al cluster, el único al que se puede hacer referencia de las llamadas del API será el simulador del API gateway. Recuerde de hacer uso del despliegue de tipo service para esto. Por último, deberá de crear un nuevo trabajo del tipo cronjob, el cual contendrá en él un despliegue de un script de python, el cual deberá ejecutarse cada 2 minutos, e insertará en una base de datos únicamente un registro en el cual detalle la fecha y hora de la ejecución del script en base de la zona horaria GMT-6 y el número de carné del estudiante (es libre de elegir si utiliza una base de datos de tipo relacional o no relacional). Recuerde la utilización de las expresiones de tipo cron para setear su cronjob Laboratorio Software Avanzado S
A94: 6. Sexta Practica | E94: Ponderación | F94: 2.5 | G94: Horas para realizarlo | H94: 8
A95: Optativa
A96: Competencia a desarrollar | B96: El estudiante Identifica conceptos clave de arquitecturas modernas y herramientas DevOps a partir de documentación técnica en actividades teóricas
A97: Competencia a desarrollar
A98: Competencia a desarrollar
A99: Titulo
A100: Qué tecnologías, lenguajes de programación, plataformas, hardware o software se utilizaran
A101: Lenguaje y Framework; Libre, Herramienta de analis de codigo estatico: Qodana
A104: Descripción de lo que se realizara
A105: En proyectos de software modernos, es necesario garantizar que el código mantenga estándares de calidad y seguridad antes de ser desplegado. Para esto se utilizan herramientas de análisis estático de código, las cuales permiten detectar problemas potenciales sin necesidad de ejecutar el programa. En esta práctica, el estudiante deberá realizar un primer acercamiento al análisis estático utilizando Qodana, una herramienta desarrollada por JetBrains para analizar proyectos de software. El análisis se realizará sobre el repositorio desarrollado en las prácticas anteriores, el cual contiene los microservicios del sistema. 2.2 Alcance de la práctica 1. Instalar y ejecutar Qodana utilizando Docker. 2. Analizar al menos dos microservicios del repositorio. 3. Generar el reporte de análisis. 4. Revisar los problemas detectados. 5. Documentar los hallazgos encontrados.
A111: 7. Septima Practica | E111: Ponderación | F111: 5 | G111: Horas para realizarlo | H111: 8
A112: Optativa
A113: Competencia a desarrollar | B113: El estudiante Explica el funcionamiento de pipelines CI/CD utilizando herramientas de integración continua mediante ejemplos prácticos
A114: Competencia a desarrollar
A115: Competencia a desarrollar
A116: Titulo | B116: practica 7
A117: Qué tecnologías, lenguajes de programación, plataformas, hardware o software se utilizaran
A118: Lenguajes: TypeScript, JavaScript, Java, Golang. Frameworks: NestJS, Java Springboot 4, Fiber, GIN
A121: Descripción de lo que se realizara
A122: Luego de haber desarrollado una arquitectura basada en microservicios, se requiere automatizar el proceso de integración, pruebas y despliegue del sistema. Las empresas modernas requieren pipelines CI/CD que permitan: • Validar cambios automáticamente • Construir imágenes Docker • Ejecutar pruebas • Desplegar servicios El estudiante deberá implementar un pipeline que permita simular este flujo empresarial. 2.2 Alcance de la práctica • Pipeline CI configurado en GitHub Actions • Automatización de build del proyecto • Ejecución de pruebas automáticas • Construcción automática de imágenes Docker • Push de imágenes a DockerHub o GitHub Container Registry • Despliegue automático usando k8s • Uso del sistema de microservicios de la práctica anterior

Sheet Tareas
B2: Tareas
B4: Curso | C4: ='Diseño'!C4 -> 780 - Software Avanzado
B5: Tiempo | C5: =H9+H26+H43+H60+H77+H94+H111+H128 -> 0
B6: Ponderación | C6: =F9+F26+F43+F60+F77+F94+F111+F128 -> 0
B7: La sumatoria de los puntos de los practicas debe no debe super el 10% de la nota
A9: Tarea de fortalecimiento académico | E9: Ponderación | G9: Horas para realizarlo
A10: Obligatoria se debe dejar en la sesion de diagnistico
A11: Competencia a desarrollar
A12: Competencia a desarrollar
A13: Competencia a desarrollar
A14: Titulo
A15: Qué tecnologías, lenguajes de programación, plataformas, hardware o software se utilizaran
A19: Que conocimientos base y competencias esenciales se deben reforzar que permitan al estudiante afrontar con mayor solidez los contenidos del curso
A26: 1. Primera Tarea | E26: Ponderación | G26: Horas para realizarlo
A27: Obligatoria
A28: Competencia a desarrollar
A29: Competencia a desarrollar
A30: Competencia a desarrollar
A31: Titulo
A32: Qué tecnologías, lenguajes de programación, plataformas, hardware o software se utilizaran
A36: Descripción de lo que se realizara
A43: 2. Segunda Tarea | E43: Ponderación | G43: Horas para realizarlo
A44: Obligatoria
A45: Competencia a desarrollar
A46: Competencia a desarrollar
A47: Competencia a desarrollar
A48: Titulo
A49: Qué tecnologías, lenguajes de programación, plataformas, hardware o software se utilizaran
A53: Descripción de lo que se realizara
A60: 3. Tercera Tarea | E60: Ponderación | G60: Horas para realizarlo
A61: Optativa
A62: Competencia a desarrollar
A63: Competencia a desarrollar
A64: Competencia a desarrollar
A65: Titulo
A66: Qué tecnologías, lenguajes de programación, plataformas, hardware o software se utilizaran
A70: Descripción de lo que se realizara
A77: 4. Cuarta Tarea | E77: Ponderación | G77: Horas para realizarlo
A78: Optativa
A79: Competencia a desarrollar
A80: Competencia a desarrollar
A81: Competencia a desarrollar
A82: Titulo
A83: Qué tecnologías, lenguajes de programación, plataformas, hardware o software se utilizaran
A87: Descripción de lo que se realizara
A94: 5. Quinta Tarea | E94: Ponderación | G94: Horas para realizarlo
A95: Optativa
A96: Competencia a desarrollar
A97: Competencia a desarrollar
A98: Competencia a desarrollar
A99: Titulo
A100: Qué tecnologías, lenguajes de programación, plataformas, hardware o software se utilizaran
A104: Descripción de lo que se realizara
A111: 6. Sexta Tarea | E111: Ponderación | G111: Horas para realizarlo
A112: Optativa
A113: Competencia a desarrollar
A114: Competencia a desarrollar
A115: Competencia a desarrollar
A116: Titulo
A117: Qué tecnologías, lenguajes de programación, plataformas, hardware o software se utilizaran
A121: Descripción de lo que se realizara
A128: 7. Septima Tarea | E128: Ponderación | G128: Horas para realizarlo
A129: Optativa
A130: Competencia a desarrollar
A131: Competencia a desarrollar
A132: Competencia a desarrollar
A133: Titulo
A134: Qué tecnologías, lenguajes de programación, plataformas, hardware o software se utilizaran
A138: Descripción de lo que se realizara

Sheet Metadata
A1: Codigo-Nombre | B1: Competencias | C1: Competencias relacionadas al perfil del egresado (Especifica) | D1: Competencias relacionadas al perfil del egresado (General)
A2: 17 - Área Social Humanística 1 | B2: =Competencias!C13 -> El estudiante Analiza .. arquitecturas de software basadas en microservicios utilizando diagramas y patrones arquitectónicos en estudios de caso reales | C2: Aplica los conocimientos de su disciplina en la elaboración, fundamentación y defensa de argumentos para prevenir y resolver problemas complejos en su campo profesional, identificando y aplicando innovaciones. | D2: Aplica principios básicos de ingeniería, ciencias de computación y sistemas de información y comunicación, en la formulación y resolución adecuada de problemas complejos.
A3: 101 - Área Matemática Básica 1 | B3: =Competencias!C15 -> El estudiante Crea .. soluciones de software basadas en microservicios poniendo en practica los principios SOLID usando herramientas de desarrollo y contenedores en entornos prácticos de laboratorio | C3: Identifica oportunidades y riesgos para la innovación y adaptación de conocimientos y tecnologías para resolver problemas. | D3: Aplica estándares de calidad, eficiencia y seguridad en la implementación adecuada de soluciones de software, hardware y TIC en general.
A4: 5 - Técnicas de Estudio e Investigación | B4: =Competencias!C17 -> El estudiante Implementa ... servicios y APIs en arquitectura de microservicios mediante Docker y frameworks de desarrollo en proyectos prácticos | C4: Demuestra pensamiento crítico, actitud investigativa y rigor analítico en el planteamiento y la resolución de problemas complejos. | D4: Aplica conocimientos tecnológicos con ética profesional y respetando y cuidando los recursos naturales, humanos y financieros.
A5: 39 - Deportes 1 | B5: =Competencias!C19 -> El estudiante Explica el funcionamiento de pipelines CI/CD utilizando herramientas de integración continua mediante ejemplos prácticos | C5: Toma decisiones profesionales con base en fundamentos teóricos, datos e información pertinente, válida y confiable. | D5: Maneja e Interpreta adecuadamente datos masivos, sean estos estructurados o no estructurados, facilitando su visualización e interpretación de forma eficaz en apoyo a la toma de decisiones.
A6: 6 - Idioma Tecnico 1 | B6: =Competencias!C21 -> El estudiante Evalúa estrategias de despliegue y monitoreo utilizando Kubernetes y herramientas de observabilidad en distintos escenarios de implementación | C6: Demuestra destreza y habilidad en la selección, uso y adaptación de herramientas metodológicas, tecnológicas, equipos especializados y en la lectura e interpretación de datos, pertinentes al contexto de su ejercicio profesional. | D6: Domina diversos recursos de comunicación con el objetivo de presentar adecuadamente sus propuestas a variados tipos de audiencias, en idioma español, inglés e idealmente en un tercer idioma acorde a las necesidades globales.
A7: 19 - Área Social Humanística 2 | B7: =Competencias!C23 -> El estudiante Aplica prácticas de DevOps y DevSecOps mediante pipelines automatizados en proyectos de software | C7: Identifica sus necesidades de actualización, capacitación y formación, durante su proceso formativo y en el ejercicio profesional, y busca los medios para cubrirlas por medios formales e informales, nacionales e internacionales, presenciales y en línea. | D7: Construye soluciones integrales trabajando en forma colaborativa y propositiva en equipos interdisciplinarios, en forma presencial o utilizando plataformas virtuales.
A8: 103 - Área Matemática Básica 2 | B8: =Competencias!C25 -> El estudiante Identifica conceptos clave de arquitecturas modernas y herramientas DevOps a partir de documentación técnica en actividades teóricas | C8: Comunica a diversos públicos, información de su campo profesional, en varios lenguajes y formatos de manera asertiva, clara, rigurosa y precisa, con el uso apropiado de recursos tecnológicos. | D8: Actualiza permanente sus conocimientos relacionados con TIC en general, apoyándose en las estrategias de aprendizaje apropiadas.
A9: 960 - Matemática Para Computación 1 | C9: Se comunica correctamente en su lengua oficial y utiliza una lengua extranjera con el dominio requerido para el ejercicio de su profesión.
A10: 147 - Física Básica | C10: Lidera y colabora proactivamente en equipos de trabajo y en comunidades profesionales para el logro de objetivos y mejoramiento de la calidad de vida.
A11: 40 - Deportes 2
A12: 8 - Idioma Técnico 2
A13: 795 - Logica de Sitemas
A14: 962 - Matemática Para Computación 2
A15: 770 - Introducción a ala programación y computación 1
A16: 107 - Área Matemática Intermedia 1
A17: 150 - Fisica 1
A18: 1 - Ética Profesional
A19: 9 - Idioma Técnico 3
A20: 796 - Lenguajes Formales y de Programación
A21: 771 - Introducción a la Programación y Computación 2
A22: 112 - Área Matemática Intermedia 2
... A81: 0089 - Comunicación Asertiva
